Workbook
Name Criticidad: '[1]Tablas valores'!$B$2:$B$4
Name estadocdp: '[1]Tablas valores'!$D$2:$D$5
Name tipocdp: '[1]Tablas valores'!$C$2:$C$3
Name Tipoejecucion: '[1]Tablas valores'!$A$2:$A$3

Sheet Resumen Avance
B3: Módulo | C3: Casos de prueba | D3: OK | E3: KO | F3: Pendientes | G3: Avance
B4: Facturas SAP NI | C4: ='Facturas SAP NI'!T80 -> 20 | D4: ='Facturas SAP NI'!T79 -> 0 | E4: ='Facturas SAP NI'!T78 -> 0 | F4: ='Facturas SAP NI'!T77 -> 20 | G4: ='Facturas SAP NI'!T76 -> 0
B5: Facturas GNCOM | C5: ='Facturas GNCOM'!P43 -> 37 | D5: ='Facturas GNCOM'!P42 -> 0 | E5: ='Facturas GNCOM'!P41 -> 0 | F5: ='Facturas GNCOM'!P40 -> 37 | G5: ='Facturas GNCOM'!P39 -> 0
B6: Cartas GNCOM | C6: ='Cartas GNCOM'!P23 -> 17 | D6: ='Cartas GNCOM'!P22 -> 0 | E6: ='Cartas GNCOM'!P21 -> 0 | F6: ='Cartas GNCOM'!P20 -> 17 | G6: ='Cartas GNCOM'!P19 -> 0
B7: Facturas GNCOMP | C7: ='Facturas GNCOMP'!P17 -> 11 | D7: ='Facturas GNCOMP'!P16 -> 0 | E7: ='Facturas GNCOMP'!P15 -> 0 | F7: ='Facturas GNCOMP'!P14 -> 11 | G7: ='Facturas GNCOMP'!P13 -> 0
B8: Cartas GNOMP | C8: ='Cartas GNOMP'!P8 -> 2 | D8: ='Cartas GNOMP'!P7 -> 0 | E8: ='Cartas GNOMP'!P6 -> 0 | F8: ='Cartas GNOMP'!P5 -> 2 | G8: ='Cartas GNOMP'!P4 -> 0
B9: Facturas CRGP | C9: ='Facturas CRGP'!R108 -> 102 | D9: ='Facturas CRGP'!R107 -> 0 | E9: ='Facturas CRGP'!R106 -> 0 | F9: ='Facturas CRGP'!R105 -> 102 | G9: ='Facturas CRGP'!R104 -> 0
B10: Cartas CRGP | C10: ='Cartas CRGP'!Q42 -> 36 | D10: ='Cartas CRGP'!Q41 -> 0 | E10: ='Cartas CRGP'!Q40 -> 0 | F10: ='Cartas CRGP'!Q39 -> 36 | G10: ='Cartas CRGP'!Q38 -> 0
B11: Contratos CRGP | C11: ='Contratos CRGP'!Q11 -> 5 | D11: ='Contratos CRGP'!Q10 -> 0 | E11: ='Contratos CRGP'!Q9 -> 0 | F11: ='Contratos CRGP'!Q8 -> 5 | G11: ='Contratos CRGP'!Q7 -> 0
B12: MEGA | C12: =MEGA!AL62 -> 49 | D12: =MEGA!AL61 -> 10 | E12: =MEGA!AL60 -> 5 | F12: =MEGA!AL59 -> 34 | G12: =MEGA!AL58 -> 0.20408163

Sheet Facturas SAP NI
A1: Sistema / Aplicación | B1: Modulo | C1: Proceso | D1: Subproceso | E1: Funcionalidad | F1: COD CdP | G1: Nombre CdP | H1: Resumen | I1: Precondiciones | J1: Tipo de Ejecución | K1: Criticidad | L1: Autor | M1: Datos del CdP | N1: Resultado esperado | O1: COMENTARIOS NEGOCIO | P1: Responsable | Q1: Fecha inicio | R1: Fecha Fin | S1: Fecha Liberado | T1: Resultado OK/KO
A2: SAP ISU | B2: Facturación | C2: Facturación ISU | D2: Facturación | E2: Impresión | F2: CP_001 | G2: =CONCATENATE(F2,"_",H2) -> CP_001_Impresión factura de ciclo (FE*), sector ELE, tarifa 2.0TD - ES | H2: Impresión factura de ciclo (FE*), sector ELE, tarifa 2.0TD - ES | J2: Manual | K2: Alta | L2: IBM | M2: Factura: | O2: Revisión OK | P2: Sergi Monte / Angel Jaime (M. Simón) | Q2: 46013 | R2: 45666
A3: SAP ISU | B3: Facturación | C3: Facturación ISU | D3: Facturación | E3: Impresión | F3: CP_002 | G3: =CONCATENATE(F3,"_",H3) -> CP_002_Impresión factura de ciclo (FE*), sector ELE, tarifa 2.0TD - CA | H3: Impresión factura de ciclo (FE*), sector ELE, tarifa 2.0TD - CA | J3: Manual | K3: Alta | L3: IBM | M3: Factura: | O3: Revisión OK | P3: Sergi Monte / Angel Jaime (M. Simón) | Q3: 46013 | R3: 45666 | T3: N/A
A4: SAP ISU | B4: Facturación | C4: Facturación ISU | D4: Facturación | E4: Impresión | F4: CP_003 | G4: =CONCATENATE(F4,"_",H4) -> CP_003_Impresión factura de ciclo (FE*), sector ELE, tarifa 2.0TD - EU | H4: Impresión factura de ciclo (FE*), sector ELE, tarifa 2.0TD - EU | J4: Manual | K4: Alta | L4: IBM | M4: Factura: | O4: Revisión OK | P4: Sergi Monte / Angel Jaime (M. Simón) | Q4: 46013 | R4: 45666 | T4: N/A
A5: SAP ISU | B5: Facturación | C5: Facturación ISU | D5: Facturación | E5: Impresión | F5: CP_004 | G5: =CONCATENATE(F5,"_",H5) -> CP_004_Impresión factura de ciclo (FE*), sector ELE, tarifa 2.0TD - GA | H5: Impresión factura de ciclo (FE*), sector ELE, tarifa 2.0TD - GA | J5: Manual | K5: Alta | L5: IBM | M5: Factura: | O5: Revisión OK | P5: Sergi Monte / Angel Jaime (M. Simón) | Q5: 46013 | R5: 45666 | T5: N/A
A6: SAP ISU | B6: Facturación | C6: Facturación ISU | D6: Facturación | E6: Impresión | F6: CP_005 | G6: =CONCATENATE(F6,"_",H6) -> CP_005_Impresión Refacturación (RE*), sector ELE, tarifa 2.0TD - ES | H6: Impresión Refacturación (RE*), sector ELE, tarifa 2.0TD - ES | J6: Manual | K6: Alta | L6: IBM | M6: Factura: | O6: Revisión OK | P6: Sergi Monte / Angel Jaime (M. Simón) | Q6: 46013 | R6: 45666
A7: SAP ISU | B7: Facturación | C7: Facturación ISU | D7: Facturación | E7: Impresión | F7: CP_006 | G7: =CONCATENATE(F7,"_",H7) -> CP_006_Impresión Refacturación (RE*), sector ELE, tarifa 2.0TD - CA | H7: Impresión Refacturación (RE*), sector ELE, tarifa 2.0TD - CA | J7: Manual | K7: Alta | L7: IBM | M7: Factura: | O7: Revisión OK | P7: Sergi Monte / Angel Jaime (M. Simón) | Q7: 46013 | R7: 45666 | T7: N/A
A8: SAP ISU | B8: Facturación | C8: Facturación ISU | D8: Facturación | E8: Impresión | F8: CP_007 | G8: =CONCATENATE(F8,"_",H8) -> CP_007_Impresión Refacturación (RE*), sector ELE, tarifa 2.0TD - EU | H8: Impresión Refacturación (RE*), sector ELE, tarifa 2.0TD - EU | J8: Manual | K8: Alta | L8: IBM | M8: Factura: | O8: Revisión OK | P8: Sergi Monte / Angel Jaime (M. Simón) | Q8: 46013 | R8: 45666 | T8: N/A
A9: SAP ISU | B9: Facturación | C9: Facturación ISU | D9: Facturación | E9: Impresión | F9: CP_008 | G9: =CONCATENATE(F9,"_",H9) -> CP_008_Impresión Refacturación (RE*), sector ELE, tarifa 2.0TD - GA | H9: Impresión Refacturación (RE*), sector ELE, tarifa 2.0TD - GA | J9: Manual | K9: Alta | L9: IBM | M9: Factura: | O9: Revisión OK | P9: Sergi Monte / Angel Jaime (M. Simón) | Q9: 46013 | R9: 45666 | T9: N/A
A10: SAP ISU | B10: Facturación | C10: Facturación ISU | D10: Facturación | E10: Impresión | F10: CP_009 | G10: =CONCATENATE(F10,"_",H10) -> CP_009_Impresión factura de anulación (SU*), sector ELE, tarifa 2.0TD -ES | H10: Impresión factura de anulación (SU*), sector ELE, tarifa 2.0TD -ES | J10: Manual | K10: Alta | L10: IBM | M10: Factura: | O10: Revisión OK | P10: Sergi Monte / Angel Jaime (M. Simón) | Q10: 46013 | R10: 45666
A11: SAP ISU | B11: Facturación | C11: Facturación ISU | D11: Facturación | E11: Impresión | F11: CP_010 | G11: =CONCATENATE(F11,"_",H11) -> CP_010_Impresión factura de anulación (SU*), sector ELE, tarifa 2.0TD -CA | H11: Impresión factura de anulación (SU*), sector ELE, tarifa 2.0TD -CA | J11: Manual | K11: Alta | L11: IBM | M11: Factura: | O11: Revisión OK | P11: Sergi Monte / Angel Jaime (M. Simón) | Q11: 46013 | R11: 45666 | T11: N/A
A12: SAP ISU | B12: Facturación | C12: Facturación ISU | D12: Facturación | E12: Impresión | F12: CP_011 | G12: =CONCATENATE(F12,"_",H12) -> CP_011_Impresión factura de anulación (SU*), sector ELE, tarifa 2.0TD -EU | H12: Impresión factura de anulación (SU*), sector ELE, tarifa 2.0TD -EU | J12: Manual | K12: Alta | L12: IBM | M12: Factura: | O12: Revisión OK | P12: Sergi Monte / Angel Jaime (M. Simón) | Q12: 46013 | R12: 45666 | T12: N/A
A13: SAP ISU | B13: Facturación | C13: Facturación ISU | D13: Facturación | E13: Impresión | F13: CP_012 | G13: =CONCATENATE(F13,"_",H13) -> CP_012_Impresión factura de anulación (SU*), sector ELE, tarifa 2.0TD -GA | H13: Impresión factura de anulación (SU*), sector ELE, tarifa 2.0TD -GA | J13: Manual | K13: Alta | L13: IBM | M13: Factura: | O13: Revisión OK | P13: Sergi Monte / Angel Jaime (M. Simón) | Q13: 46013 | R13: 45666 | T13: N/A
A14: SAP ISU | B14: Facturación | C14: Facturación ISU | D14: Facturación | E14: Impresión | F14: CP_013 | G14: =CONCATENATE(F14,"_",H14) -> CP_013_Impresión factura de Ajuste (AE*), sector ELE, tarifa 2.0TD -ES | H14: Impresión factura de Ajuste (AE*), sector ELE, tarifa 2.0TD -ES | J14: Manual | K14: Alta | L14: IBM | M14: Factura: | O14: Revisión OK | P14: Sergi Monte / Angel Jaime (M. Simón) | Q14: 46013 | R14: 45666
A15: SAP ISU | B15: Facturación | C15: Facturación ISU | D15: Facturación | E15: Impresión | F15: CP_014 | G15: =CONCATENATE(F15,"_",H15) -> CP_014_Impresión factura de Ajuste (AE*), sector ELE, tarifa 2.0TD -CA | H15: Impresión factura de Ajuste (AE*), sector ELE, tarifa 2.0TD -CA | J15: Manual | K15: Alta | L15: IBM | M15: Factura: | O15: Revisión OK | P15: Sergi Monte / Angel Jaime (M. Simón) | Q15: 46013 | R15: 45666 | T15: N/A
A16: SAP ISU | B16: Facturación | C16: Facturación ISU | D16: Facturación | E16: Impresión | F16: CP_015 | G16: =CONCATENATE(F16,"_",H16) -> CP_015_Impresión factura de Ajuste (AE*), sector ELE, tarifa 2.0TD -EU | H16: Impresión factura de Ajuste (AE*), sector ELE, tarifa 2.0TD -EU | J16: Manual | K16: Alta | L16: IBM | M16: Factura: | O16: Revisión OK | P16: Sergi Monte / Angel Jaime (M. Simón) | Q16: 46013 | R16: 45666 | T16: N/A
A17: SAP ISU | B17: Facturación | C17: Facturación ISU | D17: Facturación | E17: Impresión | F17: CP_016 | G17: =CONCATENATE(F17,"_",H17) -> CP_016_Impresión factura de Ajuste (AE*), sector ELE, tarifa 2.0TD -GA | H17: Impresión factura de Ajuste (AE*), sector ELE, tarifa 2.0TD -GA | J17: Manual | K17: Alta | L17: IBM | M17: Factura: | O17: Revisión OK | P17: Sergi Monte / Angel Jaime (M. Simón) | Q17: 46013 | R17: 45666 | T17: N/A
A18: SAP ISU | B18: Facturación | C18: Facturación ISU | D18: Facturación | E18: Impresión | F18: CP_017 | G18: =CONCATENATE(F18,"_",H18) -> CP_017_Impresión factura de ciclo (FE*), sector ELE, tarifa 3.0TD - ES | H18: Impresión factura de ciclo (FE*), sector ELE, tarifa 3.0TD - ES | J18: Manual | K18: Alta | L18: IBM | M18: Factura: | O18: Revisión OK | P18: Sergi Monte / Angel Jaime (M. Simón) | Q18: 46013 | R18: 45666
A19: SAP ISU | B19: Facturación | C19: Facturación ISU | D19: Facturación | E19: Impresión | F19: CP_018 | G19: =CONCATENATE(F19,"_",H19) -> CP_018_Impresión factura de ciclo (FE*), sector ELE, tarifa 3.0TD - CA | H19: Impresión factura de ciclo (FE*), sector ELE, tarifa 3.0TD - CA | J19: Manual | K19: Alta | L19: IBM | M19: Factura: | O19: Revisión OK | P19: Sergi Monte / Angel Jaime (M. Simón) | Q19: 46013 | R19: 45666 | T19: N/A
A20: SAP ISU | B20: Facturación | C20: Facturación ISU | D20: Facturación | E20: Impresión | F20: CP_019 | G20: =CONCATENATE(F20,"_",H20) -> CP_019_Impresión factura de ciclo (FE*), sector ELE, tarifa 3.0TD - EU | H20: Impresión factura de ciclo (FE*), sector ELE, tarifa 3.0TD - EU | J20: Manual | K20: Alta | L20: IBM | M20: Factura: | O20: Revisión OK | P20: Sergi Monte / Angel Jaime (M. Simón) | Q20: 46013 | R20: 45666 | T20: N/A
A21: SAP ISU | B21: Facturación | C21: Facturación ISU | D21: Facturación | E21: Impresión | F21: CP_020 | G21: =CONCATENATE(F21,"_",H21) -> CP_020_Impresión factura de ciclo (FE*), sector ELE, tarifa 3.0TD - GA | H21: Impresión factura de ciclo (FE*), sector ELE, tarifa 3.0TD - GA | J21: Manual | K21: Alta | L21: IBM | M21: Factura: | O21: Revisión OK | P21: Sergi Monte / Angel Jaime (M. Simón) | Q21: 46013 | R21: 45666 | T21: N/A
A22: SAP ISU | B22: Facturación | C22: Facturación ISU | D22: Facturación | E22: Impresión | F22: CP_021 | G22: =CONCATENATE(F22,"_",H22) -> CP_021_Impresión Refacturación (RE*), sector ELE, tarifa 3.0TD - ES | H22: Impresión Refacturación (RE*), sector ELE, tarifa 3.0TD - ES | J22: Manual | K22: Alta | L22: IBM | M22: Factura: | O22: Revisión OK | P22: Sergi Monte / Angel Jaime (M. Simón) | Q22: 46013 | R22: 45666
A23: SAP ISU | B23: Facturación | C23: Facturación ISU | D23: Facturación | E23: Impresión | F23: CP_022 | G23: =CONCATENATE(F23,"_",H23) -> CP_022_Impresión Refacturación (RE*), sector ELE, tarifa 3.0TD - CA | H23: Impresión Refacturación (RE*), sector ELE, tarifa 3.0TD - CA | J23: Manual | K23: Alta | L23: IBM | M23: Factura: | O23: Revisión OK | P23: Sergi Monte / Angel Jaime (M. Simón) | Q23: 46013 | R23: 45666 | T23: N/A
A24: SAP ISU | B24: Facturación | C24: Facturación ISU | D24: Facturación | E24: Impresión | F24: CP_023 | G24: =CONCATENATE(F24,"_",H24) -> CP_023_Impresión Refacturación (RE*), sector ELE, tarifa 3.0TD - EU | H24: Impresión Refacturación (RE*), sector ELE, tarifa 3.0TD - EU | J24: Manual | K24: Alta | L24: IBM | M24: Factura: | O24: Revisión OK | P24: Sergi Monte / Angel Jaime (M. Simón) | Q24: 46013 | R24: 45666 | T24: N/A
A25: SAP ISU | B25: Facturación | C25: Facturación ISU | D25: Facturación | E25: Impresión | F25: CP_024 | G25: =CONCATENATE(F25,"_",H25) -> CP_024_Impresión Refacturación (RE*), sector ELE, tarifa 3.0TD - GA | H25: Impresión Refacturación (RE*), sector ELE, tarifa 3.0TD - GA | J25: Manual | K25: Alta | L25: IBM | M25: Factura: | O25: Revisión OK | P25: Sergi Monte / Angel Jaime (M. Simón) | Q25: 46013 | R25: 45666 | T25: N/A
A26: SAP ISU | B26: Facturación | C26: Facturación ISU | D26: Facturación | E26: Impresión | F26: CP_025 | G26: =CONCATENATE(F26,"_",H26) -> CP_025_Impresión factura de anulación (SU*), sector ELE, tarifa 3.0TD - ES | H26: Impresión factura de anulación (SU*), sector ELE, tarifa 3.0TD - ES | J26: Manual | K26: Alta | L26: IBM | M26: Factura: | O26: Revisión OK | P26: Sergi Monte / Angel Jaime (M. Simón) | Q26: 46013 | R26: 45666
A27: SAP ISU | B27: Facturación | C27: Facturación ISU | D27: Facturación | E27: Impresión | F27: CP_026 | G27: =CONCATENATE(F27,"_",H27) -> CP_026_Impresión factura de anulación (SU*), sector ELE, tarifa 3.0TD - CA | H27: Impresión factura de anulación (SU*), sector ELE, tarifa 3.0TD - CA | J27: Manual | K27: Alta | L27: IBM | M27: Factura: | O27: Revisión OK | P27: Sergi Monte / Angel Jaime (M. Simón) | Q27: 46013 | R27: 45666 | T27: N/A
A28: SAP ISU | B28: Facturación | C28: Facturación ISU | D28: Facturación | E28: Impresión | F28: CP_027 | G28: =CONCATENATE(F28,"_",H28) -> CP_027_Impresión factura de anulación (SU*), sector ELE, tarifa 3.0TD - EU | H28: Impresión factura de anulación (SU*), sector ELE, tarifa 3.0TD - EU | J28: Manual | K28: Alta | L28: IBM | M28: Factura: | O28: Revisión OK | P28: Sergi Monte / Angel Jaime (M. Simón) | Q28: 46013 | R28: 45666 | T28: N/A
A29: SAP ISU | B29: Facturación | C29: Facturación ISU | D29: Facturación | E29: Impresión | F29: CP_028 | G29: =CONCATENATE(F29,"_",H29) -> CP_028_Impresión factura de anulación (SU*), sector ELE, tarifa 3.0TD - GA | H29: Impresión factura de anulación (SU*), sector ELE, tarifa 3.0TD - GA | J29: Manual | K29: Alta | L29: IBM | M29: Factura: | O29: Revisión OK | P29: Sergi Monte / Angel Jaime (M. Simón) | Q29: 46013 | R29: 45666 | T29: N/A
A30: SAP ISU | B30: Facturación | C30: Facturación ISU | D30: Facturación | E30: Impresión | F30: CP_029 | G30: =CONCATENATE(F30,"_",H30) -> CP_029_Impresión factura de ciclo (FE*), sector ELE, tarifa 6.0TD - ES | H30: Impresión factura de ciclo (FE*), sector ELE, tarifa 6.0TD - ES | J30: Manual | K30: Alta | L30: IBM | M30: Factura: | O30: Revisión OK | P30: Sergi Monte / Angel Jaime (M. Simón) | Q30: 46013 | R30: 45666
A31: SAP ISU | B31: Facturación | C31: Facturación ISU | D31: Facturación | E31: Impresión | F31: CP_030 | G31: =CONCATENATE(F31,"_",H31) -> CP_030_Impresión factura de ciclo (FE*), sector ELE, tarifa 6.0TD - CA | H31: Impresión factura de ciclo (FE*), sector ELE, tarifa 6.0TD - CA | J31: Manual | K31: Alta | L31: IBM | M31: Factura: | O31: Revisión OK | P31: Sergi Monte / Angel Jaime (M. Simón) | Q31: 46013 | R31: 45666 | T31: N/A
A32: SAP ISU | B32: Facturación | C32: Facturación ISU | D32: Facturación | E32: Impresión | F32: CP_031 | G32: =CONCATENATE(F32,"_",H32) -> CP_031_Impresión factura de ciclo (FE*), sector ELE, tarifa 6.0TD - EU | H32: Impresión factura de ciclo (FE*), sector ELE, tarifa 6.0TD - EU | J32: Manual | K32: Alta | L32: IBM | M32: Factura: | O32: Revisión OK | P32: Sergi Monte / Angel Jaime (M. Simón) | Q32: 46013 | R32: 45666 | T32: N/A
A33: SAP ISU | B33: Facturación | C33: Facturación ISU | D33: Facturación | E33: Impresión | F33: CP_032 | G33: =CONCATENATE(F33,"_",H33) -> CP_032_Impresión factura de ciclo (FE*), sector ELE, tarifa 6.0TD - GA | H33: Impresión factura de ciclo (FE*), sector ELE, tarifa 6.0TD - GA | J33: Manual | K33: Alta | L33: IBM | M33: Factura: | O33: Revisión OK | P33: Sergi Monte / Angel Jaime (M. Simón) | Q33: 46013 | R33: 45666 | T33: N/A
A34: SAP ISU | B34: Facturación | C34: Facturación ISU | D34: Facturación | E34: Impresión | F34: CP_033 | G34: =CONCATENATE(F34,"_",H34) -> CP_033_Impresión Refacturación (RE*), sector ELE, tarifa 6.xTD - ES | H34: Impresión Refacturación (RE*), sector ELE, tarifa 6.xTD - ES | J34: Manual | K34: Alta | L34: IBM | M34: Factura: | O34: Revisión OK | P34: Sergi Monte / Angel Jaime (M. Simón) | Q34: 46013 | R34: 45666
A35: SAP ISU | B35: Facturación | C35: Facturación ISU | D35: Facturación | E35: Impresión | F35: CP_034 | G35: =CONCATENATE(F35,"_",H35) -> CP_034_Impresión Refacturación (RE*), sector ELE, tarifa 6.xTD - CA | H35: Impresión Refacturación (RE*), sector ELE, tarifa 6.xTD - CA | J35: Manual | K35: Alta | L35: IBM | M35: Factura: | O35: Revisión OK | P35: Sergi Monte / Angel Jaime (M. Simón) | Q35: 46013 | R35: 45666 | T35: N/A
A36: SAP ISU | B36: Facturación | C36: Facturación ISU | D36: Facturación | E36: Impresión | F36: CP_035 | G36: =CONCATENATE(F36,"_",H36) -> CP_035_Impresión Refacturación (RE*), sector ELE, tarifa 6.xTD - EU | H36: Impresión Refacturación (RE*), sector ELE, tarifa 6.xTD - EU | J36: Manual | K36: Alta | L36: IBM | M36: Factura: | O36: Revisión OK | P36: Sergi Monte / Angel Jaime (M. Simón) | Q36: 46013 | R36: 45666 | T36: N/A
A37: SAP ISU | B37: Facturación | C37: Facturación ISU | D37: Facturación | E37: Impresión | F37: CP_036 | G37: =CONCATENATE(F37,"_",H37) -> CP_036_Impresión Refacturación (RE*), sector ELE, tarifa 6.xTD - GA | H37: Impresión Refacturación (RE*), sector ELE, tarifa 6.xTD - GA | J37: Manual | K37: Alta | L37: IBM | M37: Factura: | O37: Revisión OK | P37: Sergi Monte / Angel Jaime (M. Simón) | Q37: 46013 | R37: 45666 | T37: N/A
A38: SAP ISU | B38: Facturación | C38: Facturación ISU | D38: Facturación | E38: Impresión | F38: CP_037 | G38: =CONCATENATE(F38,"_",H38) -> CP_037_Impresión factura de anulación (SU*), sector ELE, tarifa 6.xTD - ES | H38: Impresión factura de anulación (SU*), sector ELE, tarifa 6.xTD - ES | J38: Manual | K38: Alta | L38: IBM | M38: Factura: | O38: Revisión OK | P38: Sergi Monte / Angel Jaime (M. Simón) | Q38: 46013 | R38: 45666
A39: SAP ISU | B39: Facturación | C39: Facturación ISU | D39: Facturación | E39: Impresión | F39: CP_038 | G39: =CONCATENATE(F39,"_",H39) -> CP_038_Impresión factura de anulación (SU*), sector ELE, tarifa 6.xTD - CA | H39: Impresión factura de anulación (SU*), sector ELE, tarifa 6.xTD - CA | J39: Manual | K39: Alta | L39: IBM | M39: Factura: | O39: Revisión OK | P39: Sergi Monte / Angel Jaime (M. Simón) | Q39: 46013 | R39: 45666 | T39: N/A
A40: SAP ISU | B40: Facturación | C40: Facturación ISU | D40: Facturación | E40: Impresión | F40: CP_039 | G40: =CONCATENATE(F40,"_",H40) -> CP_039_Impresión factura de anulación (SU*), sector ELE, tarifa 6.xTD - EU | H40: Impresión factura de anulación (SU*), sector ELE, tarifa 6.xTD - EU | J40: Manual | K40: Alta | L40: IBM | M40: Factura: | O40: Revisión OK | P40: Sergi Monte / Angel Jaime (M. Simón) | Q40: 46013 | R40: 45666 | T40: N/A
A41: SAP ISU | B41: Facturación | C41: Facturación ISU | D41: Facturación | E41: Impresión | F41: CP_040 | G41: =CONCATENATE(F41,"_",H41) -> CP_040_Impresión factura de anulación (SU*), sector ELE, tarifa 6.xTD - GA | H41: Impresión factura de anulación (SU*), sector ELE, tarifa 6.xTD - GA | J41: Manual | K41: Alta | L41: IBM | M41: Factura: | O41: Revisión OK | P41: Sergi Monte / Angel Jaime (M. Simón) | Q41: 46013 | R41: 45666 | T41: N/A
A42: SAP ISU | B42: Facturación | C42: Facturación ISU | D42: Facturación | E42: Impresión | F42: CP_041 | G42: =CONCATENATE(F42,"_",H42) -> CP_041_Impresión factura de ciclo (FE*), sector GAS - ES | H42: Impresión factura de ciclo (FE*), sector GAS - ES | J42: Manual | K42: Alta | L42: IBM | M42: Factura: | O42: Revisión OK | P42: Sergi Monte / Angel Jaime (M. Simón) | Q42: 46013 | R42: 45666
A43: SAP ISU | B43: Facturación | C43: Facturación ISU | D43: Facturación | E43: Impresión | F43: CP_042 | G43: =CONCATENATE(F43,"_",H43) -> CP_042_Impresión factura de ciclo (FE*), sector GAS - CA | H43: Impresión factura de ciclo (FE*), sector GAS - CA | J43: Manual | K43: Alta | L43: IBM | M43: Factura: | O43: Revisión OK | P43: Sergi Monte / Angel Jaime (M. Simón) | Q43: 46013 | R43: 45666 | T43: N/A
A44: SAP ISU | B44: Facturación | C44: Facturación ISU | D44: Facturación | E44: Impresión | F44: CP_043 | G44: =CONCATENATE(F44,"_",H44) -> CP_043_Impresión factura de ciclo (FE*), sector GAS - EU | H44: Impresión factura de ciclo (FE*), sector GAS - EU | J44: Manual | K44: Alta | L44: IBM | M44: Factura: | O44: Revisión OK | P44: Sergi Monte / Angel Jaime (M. Simón) | Q44: 46013 | R44: 45666 | T44: N/A
A45: SAP ISU | B45: Facturación | C45: Facturación ISU | D45: Facturación | E45: Impresión | F45: CP_044 | G45: =CONCATENATE(F45,"_",H45) -> CP_044_Impresión factura de ciclo (FE*), sector GAS - GA | H45: Impresión factura de ciclo (FE*), sector GAS - GA | J45: Manual | K45: Alta | L45: IBM | M45: Factura: | O45: Revisión OK | P45: Sergi Monte / Angel Jaime (M. Simón) | Q45: 46013 | R45: 45666 | T45: N/A
A46: SAP ISU | B46: Facturación | C46: Facturación ISU | D46: Facturación | E46: Impresión | F46: CP_045 | G46: =CONCATENATE(F46,"_",H46) -> CP_045_Impresión Refacturación (RE*), sector GAS - ES | H46: Impresión Refacturación (RE*), sector GAS - ES | J46: Manual | K46: Muy Alta | L46: IBM | M46: Factura: | O46: Revisión OK | P46: Sergi Monte / Angel Jaime (M. Simón) | Q46: 46013 | R46: 45666
A47: SAP ISU | B47: Facturación | C47: Facturación ISU | D47: Facturación | E47: Impresión | F47: CP_046 | G47: =CONCATENATE(F47,"_",H47) -> CP_046_Impresión Refacturación (RE*), sector GAS - CA | H47: Impresión Refacturación (RE*), sector GAS - CA | J47: Manual | K47: Muy Alta | L47: IBM | M47: Factura: | O47: Revisión OK | P47: Sergi Monte / Angel Jaime (M. Simón) | Q47: 46013 | R47: 45666 | T47: N/A
A48: SAP ISU | B48: Facturación | C48: Facturación ISU | D48: Facturación | E48: Impresión | F48: CP_047 | G48: =CONCATENATE(F48,"_",H48) -> CP_047_Impresión Refacturación (RE*), sector GAS - EU | H48: Impresión Refacturación (RE*), sector GAS - EU | J48: Manual | K48: Muy Alta | L48: IBM | M48: Factura: | O48: Revisión OK | P48: Sergi Monte / Angel Jaime (M. Simón) | Q48: 46013 | R48: 45666 | T48: N/A
A49: SAP ISU | B49: Facturación | C49: Facturación ISU | D49: Facturación | E49: Impresión | F49: CP_048 | G49: =CONCATENATE(F49,"_",H49) -> CP_048_Impresión Refacturación (RE*), sector GAS - GA | H49: Impresión Refacturación (RE*), sector GAS - GA | J49: Manual | K49: Muy Alta | L49: IBM | M49: Factura: | O49: Revisión OK | P49: Sergi Monte / Angel Jaime (M. Simón) | Q49: 46013 | R49: 45666 | T49: N/A
A50: SAP ISU | B50: Facturación | C50: Facturación ISU | D50: Facturación | E50: Impresión | F50: CP_049 | G50: =CONCATENATE(F50,"_",H50) -> CP_049_Impresión factura de anulación (SU*),sector GAS - ES | H50: Impresión factura de anulación (SU*),sector GAS - ES | J50: Manual | K50: Muy Alta | L50: IBM | M50: Factura: | O50: Revisión OK | P50: Sergi Monte / Angel Jaime (M. Simón) | Q50: 46013 | R50: 45666
A51: SAP ISU | B51: Facturación | C51: Facturación ISU | D51: Facturación | E51: Impresión | F51: CP_050 | G51: =CONCATENATE(F51,"_",H51) -> CP_050_Impresión factura de anulación (SU*),sector GAS - CA | H51: Impresión factura de anulación (SU*),sector GAS - CA | J51: Manual | K51: Muy Alta | L51: IBM | M51: Factura: | O51: Revisión OK | P51: Sergi Monte / Angel Jaime (M. Simón) | Q51: 46013 | R51: 45666 | T51: N/A
A52: SAP ISU | B52: Facturación | C52: Facturación ISU | D52: Facturación | E52: Impresión | F52: CP_051 | G52: =CONCATENATE(F52,"_",H52) -> CP_051_Impresión factura de anulación (SU*),sector GAS - EU | H52: Impresión factura de anulación (SU*),sector GAS - EU | J52: Manual | K52: Muy Alta | L52: IBM | M52: Factura: | O52: Revisión OK | P52: Sergi Monte / Angel Jaime (M. Simón) | Q52: 46013 | R52: 45666 | T52: N/A
A53: SAP ISU | B53: Facturación | C53: Facturación ISU | D53: Facturación | E53: Impresión | F53: CP_052 | G53: =CONCATENATE(F53,"_",H53) -> CP_052_Impresión factura de anulación (SU*),sector GAS - GA | H53: Impresión factura de anulación (SU*),sector GAS - GA | J53: Manual | K53: Muy Alta | L53: IBM | M53: Factura: | O53: Revisión OK | P53: Sergi Monte / Angel Jaime (M. Simón) | Q53: 46013 | R53: 45666 | T53: N/A
A54: SAP ISU | B54: Facturación | C54: Facturación ISU | D54: Facturación | E54: Impresión | F54: CP_053 | G54: =CONCATENATE(F54,"_",H54) -> CP_053_Impresión factura de Ajuste (AE*), sector GAS - ES | H54: Impresión factura de Ajuste (AE*), sector GAS - ES | J54: Manual | K54: Muy Alta | L54: IBM | M54: Factura: | O54: Revisión OK | P54: Sergi Monte / Angel Jaime (M. Simón) | Q54: 46013 | R54: 45666 | S54: 46027
A55: SAP ISU | B55: Facturación | C55: Facturación ISU | D55: Facturación | E55: Impresión | F55: CP_054 | G55: =CONCATENATE(F55,"_",H55) -> CP_054_Impresión factura de Ajuste (AE*), sector GAS - CA | H55: Impresión factura de Ajuste (AE*), sector GAS - CA | J55: Manual | K55: Muy Alta | L55: IBM | M55: Factura: | O55: Revisión OK | P55: Sergi Monte / Angel Jaime (M. Simón) | Q55: 46013 | R55: 45666 | T55: N/A
A56: SAP ISU | B56: Facturación | C56: Facturación ISU | D56: Facturación | E56: Impresión | F56: CP_055 | G56: =CONCATENATE(F56,"_",H56) -> CP_055_Impresión factura de Ajuste (AE*), sector GAS - EU | H56: Impresión factura de Ajuste (AE*), sector GAS - EU | J56: Manual | K56: Muy Alta | L56: IBM | M56: Factura: | O56: Revisión OK | P56: Sergi Monte / Angel Jaime (M. Simón) | Q56: 46013 | R56: 45666 | T56: N/A
A57: SAP ISU | B57: Facturación | C57: Facturación ISU | D57: Facturación | E57: Impresión | F57: CP_056 | G57: =CONCATENATE(F57,"_",H57) -> CP_056_Impresión factura de Ajuste (AE*), sector GAS - GA | H57: Impresión factura de Ajuste (AE*), sector GAS - GA | J57: Manual | K57: Muy Alta | L57: IBM | M57: Factura: | O57: Revisión OK | P57: Sergi Monte / Angel Jaime (M. Simón) | Q57: 46013 | R57: 45666 | T57: N/A
A58: SAP ISU | B58: Facturación | C58: Facturación ISU | D58: Facturación | E58: Impresión | F58: CP_057 | G58: =CONCATENATE(F58,"_",H58) -> CP_057_Impresión factura de empleado - ES | H58: Impresión factura de empleado - ES | J58: Manual | K58: Alta | L58: IBM | M58: Factura: | O58: Revisión OK | P58: Sergi Monte / Angel Jaime (M. Simón) | Q58: 46013 | R58: 45666
A59: SAP ISU | B59: Facturación | C59: Facturación ISU | D59: Facturación | E59: Impresión | F59: CP_058 | G59: =CONCATENATE(F59,"_",H59) -> CP_058_Impresión factura de empleado - CA | H59: Impresión factura de empleado - CA | J59: Manual | K59: Alta | L59: IBM | M59: Factura: | O59: Revisión OK | P59: Sergi Monte / Angel Jaime (M. Simón) | Q59: 46013 | R59: 45666 | T59: N/A
A60: SAP ISU | B60: Facturación | C60: Facturación ISU | D60: Facturación | E60: Impresión | F60: CP_059 | G60: =CONCATENATE(F60,"_",H60) -> CP_059_Impresión factura de empleado - EU | H60: Impresión factura de empleado - EU | J60: Manual | K60: Alta | L60: IBM | M60: Factura: | O60: Revisión OK | P60: Sergi Monte / Angel Jaime (M. Simón) | Q60: 46013 | R60: 45666 | T60: N/A
A61: SAP ISU | B61: Facturación | C61: Facturación ISU | D61: Facturación | E61: Impresión | F61: CP_060 | G61: =CONCATENATE(F61,"_",H61) -> CP_060_Impresión factura de empleado - GA | H61: Impresión factura de empleado - GA | J61: Manual | K61: Alta | L61: IBM | M61: Factura: | O61: Revisión OK | P61: Sergi Monte / Angel Jaime (M. Simón) | Q61: 46013 | R61: 45666 | T61: N/A
A62: SAP ISU | B62: Facturación | C62: Facturación ISU | D62: Facturación | E62: Impresión | F62: CP_061 | G62: =CONCATENATE(F62,"_",H62) -> CP_061_Impresión factura TP ELE - ES | H62: Impresión factura TP ELE - ES | J62: Manual | K62: Alta | L62: IBM | M62: Factura: | O62: Revisión OK | P62: Sergi Monte / Angel Jaime (M. Simón) | Q62: 46013 | R62: 45666
A63: SAP ISU | B63: Facturación | C63: Facturación ISU | D63: Facturación | E63: Impresión | F63: CP_062 | G63: =CONCATENATE(F63,"_",H63) -> CP_062_Impresión factura TP ELE - CA | H63: Impresión factura TP ELE - CA | J63: Manual | K63: Alta | L63: IBM | M63: Factura: | O63: Revisión OK | P63: Sergi Monte / Angel Jaime (M. Simón) | Q63: 46013 | R63: 45666 | T63: N/A
A64: SAP ISU | B64: Facturación | C64: Facturación ISU | D64: Facturación | E64: Impresión | F64: CP_063 | G64: =CONCATENATE(F64,"_",H64) -> CP_063_Impresión factura TP ELE - EU | H64: Impresión factura TP ELE - EU | J64: Manual | K64: Alta | L64: IBM | M64: Factura: | O64: Revisión OK | P64: Sergi Monte / Angel Jaime (M. Simón) | Q64: 46013 | R64: 45666 | T64: N/A
A65: SAP ISU | B65: Facturación | C65: Facturación ISU | D65: Facturación | E65: Impresión | F65: CP_064 | G65: =CONCATENATE(F65,"_",H65) -> CP_064_Impresión factura TP ELE - GA | H65: Impresión factura TP ELE - GA | J65: Manual | K65: Alta | L65: IBM | M65: Factura: | O65: Revisión OK | P65: Sergi Monte / Angel Jaime (M. Simón) | Q65: 46013 | R65: 45666 | T65: N/A
A66: SAP ISU | B66: Facturación | C66: Facturación ISU | D66: Facturación | E66: Impresión | F66: CP_065 | G66: =CONCATENATE(F66,"_",H66) -> CP_065_Impresión factura TP GAS - ES | H66: Impresión factura TP GAS - ES | J66: Manual | K66: Alta | L66: IBM | M66: Factura: | O66: Revisión OK | P66: Sergi Monte / Angel Jaime (M. Simón) | Q66: 46013 | R66: 45666
A67: SAP ISU | B67: Facturación | C67: Facturación ISU | D67: Facturación | E67: Impresión | F67: CP_066 | G67: =CONCATENATE(F67,"_",H67) -> CP_066_Impresión factura TP GAS - CA | H67: Impresión factura TP GAS - CA | J67: Manual | K67: Alta | L67: IBM | M67: Factura: | O67: Revisión OK | P67: Sergi Monte / Angel Jaime (M. Simón) | Q67: 46013 | R67: 45666 | T67: N/A
A68: SAP ISU | B68: Facturación | C68: Facturación ISU | D68: Facturación | E68: Impresión | F68: CP_067 | G68: =CONCATENATE(F68,"_",H68) -> CP_067_Impresión factura TP GAS - EU | H68: Impresión factura TP GAS - EU | J68: Manual | K68: Alta | L68: IBM | M68: Factura: | O68: Revisión OK | P68: Sergi Monte / Angel Jaime (M. Simón) | Q68: 46013 | R68: 45666 | T68: N/A
A69: SAP ISU | B69: Facturación | C69: Facturación ISU | D69: Facturación | E69: Impresión | F69: CP_068 | G69: =CONCATENATE(F69,"_",H69) -> CP_068_Impresión factura TP GAS - GA | H69: Impresión factura TP GAS - GA | J69: Manual | K69: Alta | L69: IBM | M69: Factura: | O69: Revisión OK | P69: Sergi Monte / Angel Jaime (M. Simón) | Q69: 46013 | R69: 45666 | T69: N/A
A70: SAP ISU | B70: Facturación | C70: Facturación ISU | D70: Facturación | E70: Impresión | F70: CP_069 | G70: =CONCATENATE(F70,"_",H70) -> CP_069_Impresión factura IGIC | H70: Impresión factura IGIC | J70: Manual | K70: Alta | L70: IBM | M70: Factura: | O70: Revisión OK | P70: Sergi Monte / Angel Jaime (M. Simón) | Q70: 46013 | R70: 45666
A71: SAP ISU | B71: Facturación | C71: Facturación ISU | D71: Facturación | E71: Impresión | F71: CP_070 | G71: =CONCATENATE(F71,"_",H71) -> CP_070_Impresión factura IPSI | H71: Impresión factura IPSI | J71: Manual | K71: Alta | L71: IBM | M71: Factura: | O71: Revisión OK | P71: Sergi Monte / Angel Jaime (M. Simón) | Q71: 46013 | R71: 45666
A72: SAP ISU | B72: Facturación | C72: Facturación ISU | D72: Facturación | E72: Impresión | F72: CP_071 | G72: =CONCATENATE(F72,"_",H72) -> CP_071_Impresión factura con troquelado - ES | H72: Impresión factura con troquelado - ES | J72: Manual | K72: Alta | L72: IBM | M72: Factura: | O72: Revisión OK | P72: Sergi Monte / Angel Jaime (M. Simón) | Q72: 46013 | R72: 45666
A73: SAP ISU | B73: Facturación | C73: Facturación ISU | D73: Facturación | E73: Impresión | F73: CP_072 | G73: =CONCATENATE(F73,"_",H73) -> CP_072_Impresión factura con troquelado - CA | H73: Impresión factura con troquelado - CA | J73: Manual | K73: Alta | L73: IBM | M73: Factura: | O73: Revisión OK | P73: Sergi Monte / Angel Jaime (M. Simón) | Q73: 46013 | R73: 45666 | T73: N/A
A74: SAP ISU | B74: Facturación | C74: Facturación ISU | D74: Facturación | E74: Impresión | F74: CP_073 | G74: =CONCATENATE(F74,"_",H74) -> CP_073_Impresión factura con troquelado - EU | H74: Impresión factura con troquelado - EU | J74: Manual | K74: Alta | L74: IBM | M74: Factura: | O74: Revisión OK | P74: Sergi Monte / Angel Jaime (M. Simón) | Q74: 46013 | R74: 45666 | T74: N/A
A75: SAP ISU | B75: Facturación | C75: Facturación ISU | D75: Facturación | E75: Impresión | F75: CP_074 | G75: =CONCATENATE(F75,"_",H75) -> CP_074_Impresión factura con troquelado - GA | H75: Impresión factura con troquelado - GA | J75: Manual | K75: Alta | L75: IBM | M75: Factura: | O75: Revisión OK | P75: Sergi Monte / Angel Jaime (M. Simón) | Q75: 46013 | R75: 45666 | T75: N/A
T76: =(COUNTIF(T2:T75,"OK")/(COUNTBLANK(T2:T75)+(COUNTA(T2:T75)-(COUNTIF(T2:T75,"N/A"))))) -> 0 | U76: Porcentaje de Avance
T77: =COUNTBLANK(T2:T75)+(COUNTA(T2:T75)-(COUNTIF(T2:T75,"N/A"))-(COUNTIF(T2:T75,"OK"))-(COUNTIF(T2:T75,"KO"))) -> 20 | U77: Pendiente
T78: =COUNTIF(T2:T75,"KO") -> 0 | U78: KO
T79: =COUNTIF(T2:T75,"OK") -> 0 | U79: OK
T80: =COUNTBLANK(T2:T75)+(COUNTA(T2:T75)-(COUNTIF(T2:T75,"N/A"))) -> 20 | U80: Total

Sheet Facturas GNCOM
A1: Proyecto | B1: Tipo | C1: Estado | D1: Prioridad | E1: Codigo de Prueba | F1: Asunto | G1: Módulos Delta | H1: Datos de prueba | I1: Técnica de pruebas | J1: Resultado esperado | K1: COMENTARIOS NEGOCIO | L1: Responsable | M1: Fecha inicio | N1: Fecha Fin | O1: Fecha Liberado | P1: Resultado OK/KO | Q1: xml papyrus | R1: pdf papyrus
A2: Proyecto Compositor Documental - GNCOM | B2: Caso prueba | C2: Nueva | D2: Normal | E2: FAC_001 | F2: Factura Gas España F001-F031 Subformulario Gas España Lectura mensual | G2: FACTURACIÓN | H2: Factura Gas España con Lectura mensual Formulario: F001 Subformulario: F031 Idioma: CA, ES, EU, GA | I2: Impresión facturas en los distintos idiomas | J2: Generación de xml y PDF | K2: Revisión OK | L2: Javi Granadino / Esther Rigo (M. Simón) | M2: 46013 | N2: 45666 | O2: 46027 | Q2: FAC_001_GA_PI25142000355153.xml FAC_001_ES_PI25142000355153.xml FAC_001_CA_PI25142000355153.xml FAC_001_EU_PI25142000355153.xml | R2: FAC_001_GA_PI25142000355153.pdf FAC_001_ES_PI25142000355153.pdf FAC_001_CA_PI25142000355153.des.afp.pdf FAC_001_EU_PI25142000355153.des.afp.pdf
A3: Proyecto Compositor Documental - GNCOM | B3: Caso prueba | C3: Nueva | D3: Normal | E3: FAC_002 | F3: Factura Gas España F001-F011 Subformulario Gas España Lectura diaria con curva | G3: FACTURACIÓN | H3: Factura Gas España con Lectura diaria con curva Formulario: F001 Subformulario: F011 Idioma: CA, ES, EU, GA | I3: Impresión facturas en los distintos idiomas | J3: Generación de xml y PDF | K3: Revisión OK | L3: Javi Granadino / Esther Rigo (M. Simón) | M3: 46013 | N3: 45666 | O3: 46027 | Q3: FAC_002_ES_PI25142000387240.xml FAC_002_GA_PI25142000387240.xml FAC_002_EU_PI25142000387240.xml FAC_002_CA_PI25142000387240.xml | R3: FAC_002_ES_PI25142000387240.pdf FAC_002_GA_PI25142000387240.pdf FAC_002_EU_PI25142000387240.pdf FAC_002_CA_PI25142000387240.pdf
A4: Proyecto Compositor Documental - GNCOM | B4: Caso prueba | C4: Nueva | D4: Normal | E4: FAC_003 | F4: Factura Gas España F001-F061 Subformulario Gas España mixta | G4: FACTURACIÓN | H4: Factura Gas España con lectura mixta Formulario: F001 Subformulario: F061 Idioma: CA, ES, EU, GA | I4: Impresión facturas en los distintos idiomas | J4: Generación de xml y PDF | K4: Revisión OK | L4: Javi Granadino / Esther Rigo (M. Simón) | M4: 46013 | N4: 45666 | O4: 46027 | Q4: FAC_003_ES_PI25142000363098.xml FAC_003_EU_PI25142000363098.xml FAC_003_CA_PI25142000363098.xml FAC_003_GA_PI25142000363098.xml | R4: FAC_003_ES_PI25142000363098.pdf FAC_003_EU_PI25142000363098.pdf FAC_003_CA_PI25142000363098.pdf FAC_003_GA_PI25142000363098.pdf
A5: Proyecto Compositor Documental - GNCOM | B5: Caso prueba | C5: Nueva | D5: Normal | E5: FAC_004 | F5: Factura Gas España GFU (F001) | G5: FACTURACIÓN | H5: Factura Gas España GFU (Multipunto) Formulario: F001 Subformulario: F031/F011/F061 Idioma: CA, ES, EU, GA | I5: Impresión facturas en los distintos idiomas | J5: Generación de xml y PDF | K5: Revisión OK | L5: Javi Granadino / Esther Rigo (M. Simón) | M5: 46013 | N5: 45666 | O5: 46027 | Q5: FAC_004_GA_PI25142000389656.xml FAC_004_CA_PI25142000389656.xml FAC_004_ES_PI25142000389656.xml FAC_004_EU_PI25142000389656.xml | R5: FAC_004_GA_PI25142000389656.pdf FAC_004_CA_PI25142000389656.afp.pdf FAC_004_ES_PI25142000389656.afp.pdf FAC_004_EU_PI25142000389656.afp.pdf
A6: Proyecto Compositor Documental - GNCOM | B6: Caso prueba | C6: Nueva | D6: Normal | E6: FAC_005 | F6: Factura Gas España Agrupación diaria (F001) | G6: FACTURACIÓN | H6: Factura Gas España Agrupación diaria Formulario: F001 Subformulario: F011 Idioma: CA, ES, EU, GA | I6: Impresión facturas en los distintos idiomas | J6: Generación de xml y PDF | K6: Revisión OK | L6: Javi Granadino / Esther Rigo (M. Simón) | M6: 46013 | N6: 45666 | O6: 46027 | Q6: FAC_005_ES_PI25142000386327.xml FAC_005_CA_PI25142000386327.xml FAC_005_EU_PI25142000386327.xml FAC_005_GA_PI25142000386327.xml | R6: FAC_005_ES_PI25142000386327.pdf FAC_005_CA_PI25142000386327.pdf FAC_005_EU_PI25142000386327.pdf FAC_005_GA_PI25142000386327.pdf
A7: Proyecto Compositor Documental - GNCOM | B7: Caso prueba | C7: Nueva | D7: Normal | E7: FAC_006 | F7: Factura Gas España CV (F001) | G7: FACTURACIÓN | H7: Factura Gas España CV (Cargo Vario) Formulario: F001 Subformulario: N/A Idioma: CA, ES, EU, GA | I7: Impresión facturas en los distintos idiomas | J7: Generación de xml y PDF | K7: Revisión OK | L7: Javi Granadino / Esther Rigo (M. Simón) | M7: 46013 | N7: 45666 | O7: 46027 | Q7: FAC_006_ES_PO24142000002567.xml FAC_006_CA_PO24142000002567.xml FAC_006_GA_PO24142000002567.xml FAC_006_EU_PO24142000002567.xml | R7: FAC_006_ES_PO24142000002567.afp.pdf FAC_006_CA_PO24142000002567.afp.pdf FAC_006_GA_PO24142000002567.afp.pdf FAC_006_EU_PO24142000002567.afp.pdf
A8: Proyecto Compositor Documental - GNCOM | B8: Caso prueba | C8: Nueva | D8: Normal | E8: FAC_007 | F8: Factura de ajuste Gas España (F001) | G8: FACTURACIÓN | H8: Factura de ajuste Gas España Formulario: F001 Subformulario: F011/F031/F061 Idioma: CA, ES, EU, GA | I8: Impresión facturas en los distintos idiomas | J8: Generación de xml y PDF | K8: Revisión OK | L8: Javi Granadino / Esther Rigo (M. Simón) | M8: 46013 | N8: 45666 | Q8: | PA25142000045897 | DazelMessage_378632.xml | DazelMessage_378632_F001.afp.pdf | F001 | F031 | CatalÃ¡n | | PA25142000045897 | DazelMessage_378628.xml | DazelMessage_378628.afp.pdf | F001 | F031 | EspaÃ±ol | | PA25142000045897 | DazelMessage_378678.xml | DazelMessage_378678_F001.afp.pdf | F001 | F031 | Euskera | | PA25142000045897 | DazelMessage_378647.xml | DazelMessage_378647_F001.afp.pdf | F001 | F031 | Gallego | | R8: | PA25142000045897 | DazelMessage_378632.xml | DazelMessage_378632_F001.afp.pdf | F001 | F031 | CatalÃ¡n | | PA25142000045897 | DazelMessage_378628.xml | DazelMessage_378628.afp.pdf | F001 | F031 | EspaÃ±ol | | PA25142000045897 | DazelMessage_378678.xml | DazelMessage_378678_F001.afp.pdf | F001 | F031 | Euskera | | PA25142000045897 | DazelMessage_378647.xml | DazelMessage_378647_F001.afp.pdf | F001 | F031 | Gallego |
A9: Proyecto Compositor Documental - GNCOM | B9: Caso prueba | C9: Nueva | D9: Normal | E9: FAC_008 | F9: Factura de recálculo Gas España (F001) | G9: FACTURACIÓN | H9: Factura de recálculo Gas España Formulario: F001 Subformulario: F011/F031/F061 Idioma: CA, ES, EU, GA | I9: Impresión facturas en los distintos idiomas | J9: Generación de xml y PDF | K9: Revisión OK | L9: Javi Granadino / Esther Rigo (M. Simón) | M9: 46013 | N9: 45666 | Q9: | PR25142000004972 | DazelMessage_378633.xml | DazelMessage_378633_F001.afp.pdf | F001 | F011 | CatalÃ¡n | | PR25142000004972 | DazelMessage_378627.xml | DazelMessage_378627.afp.pdf | F001 | F011 | EspaÃ±ol | | PR25142000004972 | DazelMessage_378677.xml | DazelMessage_378677_F001.afp.pdf | F001 | F011 | Euskera | | PR25142000004972 | DazelMessage_378640.xml | DazelMessage_378640_F001.afp.pdf | F001 | F011 | Gallego | | R9: | PR25142000004972 | DazelMessage_378633.xml | DazelMessage_378633_F001.afp.pdf | F001 | F011 | CatalÃ¡n | | PR25142000004972 | DazelMessage_378627.xml | DazelMessage_378627.afp.pdf | F001 | F011 | EspaÃ±ol | | PR25142000004972 | DazelMessage_378677.xml | DazelMessage_378677_F001.afp.pdf | F001 | F011 | Euskera | | PR25142000004972 | DazelMessage_378640.xml | DazelMessage_378640_F001.afp.pdf | F001 | F011 | Gallego |
A10: Proyecto Compositor Documental - GNCOM | B10: Caso prueba | C10: Nueva | D10: Normal | E10: FAC_009 | F10: Factura de anulación Gas España (F001) | G10: FACTURACIÓN | H10: Factura de anulación Gas España Formulario: F001 Subformulario: F011/F031/F061 Idioma: CA, ES, EU, GA | I10: Impresión facturas en los distintos idiomas | J10: Generación de xml y PDF | K10: Revisión OK | L10: Javi Granadino / Esther Rigo (M. Simón) | M10: 46013 | N10: 45666 | Q10: | PS25142000009265 | DazelMessage_378632.xml | DazelMessage_378632_F001.afp.pdf | F001 | | CatalÃ¡n | | PS25142000009265 | DazelMessage_378628.xml | DazelMessage_378628.afp.pdf | F001 | | EspaÃ±ol | | PS25142000009265 | DazelMessage_378678.xml | DazelMessage_378678_F001.afp.pdf | F001 | | Euskera | | PS25142000009265 | DazelMessage_378647.xml | DazelMessage_378647_F001.afp.pdf | F001 | | Gallego | | R10: | PS25142000009265 | DazelMessage_378632.xml | DazelMessage_378632_F001.afp.pdf | F001 | | CatalÃ¡n | | PS25142000009265 | DazelMessage_378628.xml | DazelMessage_378628.afp.pdf | F001 | | EspaÃ±ol | | PS25142000009265 | DazelMessage_378678.xml | DazelMessage_378678_F001.afp.pdf | F001 | | Euskera | | PS25142000009265 | DazelMessage_378647.xml | DazelMessage_378647_F001.afp.pdf | F001 | | Gallego |
A11: Proyecto Compositor Documental - GNCOM | B11: Caso prueba | C11: Nueva | D11: Normal | E11: FAC_010 | F11: Factura de ajuste Gas España GFU (F001) | G11: FACTURACIÓN | H11: Factura de ajuste Gas España GFU (Multipunto) Formulario: F001 Subformulario: F011/F031/F061 Idioma: CA, ES, EU, GA | I11: Impresión facturas en los distintos idiomas | J11: Generación de xml y PDF | K11: Revisión OK | L11: Javi Granadino / Esther Rigo (M. Simón) | M11: 46013 | N11: 45666 | Q11: | PA25142000044574 | DazelMessage_378633.xml | DazelMessage_378633_F001.afp.pdf | F001 | F031 | CatalÃ¡n | | PA25142000044574 | DazelMessage_378627.xml | DazelMessage_378627.afp.pdf | F001 | F031 | EspaÃ±ol | | PA25142000044574 | DazelMessage_378677.xml | DazelMessage_378677_F001.afp.pdf | F001 | F031 | Euskera | | PA25142000044574 | DazelMessage_378640.xml | DazelMessage_378640_F001.afp.pdf | F001 | F031 | Gallego | | R11: | PA25142000044574 | DazelMessage_378633.xml | DazelMessage_378633_F001.afp.pdf | F001 | F031 | CatalÃ¡n | | PA25142000044574 | DazelMessage_378627.xml | DazelMessage_378627.afp.pdf | F001 | F031 | EspaÃ±ol | | PA25142000044574 | DazelMessage_378677.xml | DazelMessage_378677_F001.afp.pdf | F001 | F031 | Euskera | | PA25142000044574 | DazelMessage_378640.xml | DazelMessage_378640_F001.afp.pdf | F001 | F031 | Gallego |
A12: Proyecto Compositor Documental - GNCOM | B12: Caso prueba | C12: Nueva | D12: Normal | E12: FAC_011 | F12: Factura de recálculo Gas España GFU (F001) | G12: FACTURACIÓN | H12: Factura de recálculo Gas España GFU (Multipunto) Formulario: F001 Subformulario: F011/F031/F061 Idioma: CA, ES, EU, GA | I12: Impresión facturas en los distintos idiomas | J12: Generación de xml y PDF | K12: Revisión OK | L12: Javi Granadino / Esther Rigo (M. Simón) | M12: 46013 | N12: 45666 | Q12: | PR25142000004874 | DazelMessage_378633.xml | DazelMessage_378633_F001.afp.pdf | F001 | F031 | CatalÃ¡n | | PR25142000004874 | DazelMessage_378627.xml | DazelMessage_378627.afp.pdf | F001 | F031 | EspaÃ±ol | | PR25142000004874 | DazelMessage_378677.xml | DazelMessage_378677_F001.afp.pdf | F001 | F031 | Euskera | | PR25142000004874 | DazelMessage_378640.xml | DazelMessage_378640_F001.afp.pdf | F001 | F031 | Gallego | | R12: | PR25142000004874 | DazelMessage_378633.xml | DazelMessage_378633_F001.afp.pdf | F001 | F031 | CatalÃ¡n | | PR25142000004874 | DazelMessage_378627.xml | DazelMessage_378627.afp.pdf | F001 | F031 | EspaÃ±ol | | PR25142000004874 | DazelMessage_378677.xml | DazelMessage_378677_F001.afp.pdf | F001 | F031 | Euskera | | PR25142000004874 | DazelMessage_378640.xml | DazelMessage_378640_F001.afp.pdf | F001 | F031 | Gallego |
A13: Proyecto Compositor Documental - GNCOM | B13: Caso prueba | C13: Nueva | D13: Normal | E13: FAC_012 | F13: Factura de anulación Gas España GFU (F001) | G13: FACTURACIÓN | H13: Factura de anulación Gas España GFU (Multipunto) Formulario: F001 Subformulario: F011/F031/F061 Idioma: CA, ES, EU, GA | I13: Impresión facturas en los distintos idiomas | J13: Generación de xml y PDF | K13: Revisión OK | L13: Javi Granadino / Esther Rigo (M. Simón) | M13: 46013 | N13: 45666 | Q13: | PS25142000008202 | DazelMessage_378633.xml | DazelMessage_378633_F001.afp.pdf | F001 | | CatalÃ¡n | | PS25142000008202 | DazelMessage_378627.xml | DazelMessage_378627.afp.pdf | F001 | | EspaÃ±ol | | PS25142000008202 | DazelMessage_378677.xml | DazelMessage_378677_F001.afp.pdf | F001 | | Euskera | | PS25142000008202 | DazelMessage_378640.xml | DazelMessage_378640_F001.afp.pdf | F001 | | Gallego | | R13: | PS25142000008202 | DazelMessage_378633.xml | DazelMessage_378633_F001.afp.pdf | F001 | | CatalÃ¡n | | PS25142000008202 | DazelMessage_378627.xml | DazelMessage_378627.afp.pdf | F001 | | EspaÃ±ol | | PS25142000008202 | DazelMessage_378677.xml | DazelMessage_378677_F001.afp.pdf | F001 | | Euskera | | PS25142000008202 | DazelMessage_378640.xml | DazelMessage_378640_F001.afp.pdf | F001 | | Gallego |
A14: Proyecto Compositor Documental - GNCOM | B14: Caso prueba | C14: Nueva | D14: Normal | E14: FAC_013 | F14: Factura Electricidad España F002-F012 Subformulario Electricidad España 1 y 3 periodos | G14: FACTURACIÓN | H14: Factura Electricidad España con 1 o 3 periodos Formulario: F002 Subformulario: F012 Idioma: CA, ES, EU, GA | I14: Impresión facturas en los distintos idiomas | J14: Generación de xml y PDF | K14: Revisión OK | L14: Javi Granadino / Esther Rigo (M. Simón) | M14: 46013 | N14: 45666 | Q14: FAC_013_ES_PI25142000386163.xml FAC_013_CA_PI25142000386163.xml FAC_013_EU_PI25142000386163.xml FAC_013_GA_PI25142000386163.xml | R14: FAC_013_ES_PI25142000386163.afp.pdf FAC_013_CA_PI25142000386163.pdf FAC_013_EU_PI25142000386163.pdf FAC_013_GA_PI25142000386163.pdf
A15: Proyecto Compositor Documental - GNCOM | B15: Caso prueba | C15: Nueva | D15: Normal | E15: FAC_014 | F15: Factura Electricidad España F002-F022 Subformulario Electricidad España 6 periodos | G15: FACTURACIÓN | H15: Factura Electricidad España con 6 periodos Formulario: F002 Subformulario: F022 Idioma: CA, ES, EU, GA | I15: Impresión facturas en los distintos idiomas | J15: Generación de xml y PDF | K15: Revisión OK | L15: Javi Granadino / Esther Rigo (M. Simón) | M15: 46013 | N15: 45666 | Q15: FAC_014_ES_PI25142000387226.xml FAC_014_CA_PI25142000387226.xml FAC_014_EU_PI25142000387226.xml FAC_014_GA_PI25142000387226.xml | R15: FAC_014_ES_PI25142000387226.afp.pdf FAC_014_CA_PI25142000387226.afp.pdf FAC_014_EU_PI25142000387226.afp.pdf FAC_014_GA_PI25142000387226.afp.pdf
A16: Proyecto Compositor Documental - GNCOM | B16: Caso prueba | C16: Nueva | D16: Normal | E16: FAC_015 | F16: Factura Electricidad España GFU (F002) | G16: FACTURACIÓN | H16: Factura Electricidad España GFU (Multipunto) Formulario: F002 Subformulario: F012/F022 Idioma: CA, ES, EU, GA | I16: Impresión facturas en los distintos idiomas | J16: Generación de xml y PDF | K16: Revisión OK | L16: Javi Granadino / Esther Rigo (M. Simón) | M16: 46013 | N16: 45666 | Q16: FAC_015_GA_PI25142000343027.xml FAC_015_ES_PI25142000343027.xml FAC_015_CA_PI25142000343027.xml FAC_015_EU_PI25142000343027.xml | R16: FAC_015_GA_PI25142000343027.afp.pdf FAC_015_CA_PI25142000343027.afp.pdf FAC_015_ES_PI25142000343027.afp.pdf FAC_015_EU_PI25142000343027.afp.pdf
A17: Proyecto Compositor Documental - GNCOM | B17: Caso prueba | C17: Nueva | D17: Normal | E17: FAC_016 | F17: Factura Electricidad España CV (F002) | G17: FACTURACIÓN | H17: Factura Electricidad España CV (Cargo Vario) Formulario: F002 Subformulario: N/A Idioma: CA, ES, EU, GA | I17: Impresión facturas en los distintos idiomas | J17: Generación de xml y PDF | K17: Revisión OK | L17: Javi Granadino / Esther Rigo (M. Simón) | M17: 46013 | N17: 45666 | Q17: FAC_016_ES_PO24142000002805.xml FAC_016_CA_PO24142000002805.xml FAC_016_GA_PO24142000002805.xml FAC_016_EU_PO24142000002805.xml | R17: FAC_016_ES_PO24142000002805.afp.pdf FAC_016_CA_PO24142000002805.afp.pdf FAC_016_GA_PO24142000002805.afp.pdf FAC_016_EU_PO24142000002805.afp.pdf
A18: Proyecto Compositor Documental - GNCOM | B18: Caso prueba | C18: Nueva | D18: Normal | E18: FAC_017 | F18: Factura de ajuste Electricidad España (F002) | G18: FACTURACIÓN | H18: Factura de ajuste Electricidad España Formulario: F002 Subformulario: F012/F022 Idioma: CA, ES, EU, GA | I18: Impresión facturas en los distintos idiomas | J18: Generación de xml y PDF | K18: Revisión OK | L18: Javi Granadino / Esther Rigo (M. Simón) | M18: 46013 | N18: 45666 | Q18: FAC_017_ES_PA25142000032972.xml FAC_017_CA_PA25142000032972.xml FAC_017_EU_PA25142000032972.xml FAC_017_GA_PA25142000032972.xml | R18: FAC_017_ES_PA25142000032972.pdf FAC_017_CA_PA25142000032972.afp.pdf FAC_017_EU_PA25142000032972.afp.pdf FAC_017_GA_PA25142000032972.afp.pdf
A19: Proyecto Compositor Documental - GNCOM | B19: Caso prueba | C19: Nueva | D19: Normal | E19: FAC_018 | F19: Factura de recálculo Electricidad España (F002) | G19: FACTURACIÓN | H19: Factura de recálculo Electricidad España Formulario: F002 Subformulario: F012/F022 Idioma: CA, ES, EU, GA | I19: Impresión facturas en los distintos idiomas | J19: Generación de xml y PDF | K19: Revisión OK | L19: Javi Granadino / Esther Rigo (M. Simón) | M19: 46013 | N19: 45666 | Q19: | PR25142000004750 | DazelMessage_378650_Cat.xml | DazelMessage_378650_Cat_F002.afp.pdf | F002 | F022 | CatalÃ¡n | | PR25142000004750 | DazelMessage_378649_Cas.xml | DazelMessage_378649_Cas_F002.afp.pdf | F002 | F022 | EspaÃ±ol | | PR25142000004750 | DazelMessage_378680.xml | DazelMessage_378680_F002.afp.pdf | F002 | F022 | Euskera | | PR25142000004750 | DazelMessage_378639.xml | DazelMessage_378639_F002.afp.pdf | F002 | F022 | Gallego | | R19: | PR25142000004750 | DazelMessage_378650_Cat.xml | DazelMessage_378650_Cat_F002.afp.pdf | F002 | F022 | CatalÃ¡n | | PR25142000004750 | DazelMessage_378649_Cas.xml | DazelMessage_378649_Cas_F002.afp.pdf | F002 | F022 | EspaÃ±ol | | PR25142000004750 | DazelMessage_378680.xml | DazelMessage_378680_F002.afp.pdf | F002 | F022 | Euskera | | PR25142000004750 | DazelMessage_378639.xml | DazelMessage_378639_F002.afp.pdf | F002 | F022 | Gallego |
... A35: Proyecto Compositor Documental - GNCOM | B35: Caso prueba | C35: Nueva | D35: Normal | E35: FAC_034 | F35: Impresión agrupadores OOEE Eletricidad España Listado facturas y facturas | G35: FACTURACIÓN | H35: Carta de agrupador de Electricidad España con lista de facturas y facturas Carta: OOEE Con facturas: Formulario: F002 Subformulario: F012/F022 Idioma: CA, ES, EU, GA | I35: Impresión facturas en los distintos idiomas | J35: Generación de xml y PDF | K35: Revisión OK | L35: Javi Granadino / Esther Rigo (M. Simón) | M35: 46013 | N35: 45666 | Q35: DazelMessage_378684_OOEE_E_LLISTA+FACT.xml | R35: DazelMessage_378684_OOEE_E_LLISTA+FACT.afp.pdf
A36: Proyecto Compositor Documental - GNCOM | B36: Caso prueba | C36: Nueva | D36: Normal | E36: FAC_035 | F36: Factura Gas España F001-F011 Subformulario Gas España Lectura diaria con curva con más de 5 UMs | G36: FACTURACIÓN | H36: Factura Gas España con Lectura diaria con curva y más de 5 UMs Formulario: F001 Subformulario: F011 Idioma: CA, ES, EU, GA | I36: Impresión facturas en los distintos idiomas | J36: Generación de xml y PDF | L36: Javi Granadino / Esther Rigo (M. Simón) | M36: 46013 | N36: 45666 | O36: 46027 | Q36: FAC_035_CA_PI25142000322521.xml FAC_035_ES_PI25142000322521.xml FAC_035_EU_PI25142000322521.xml FAC_035_GA_PI25142000322521.xml | R36: FAC_035_CA_PI25142000322521.pdf FAC_035_ES_PI25142000322521.pdf FAC_035_EU_PI25142000322521.pdf FAC_035_GA_PI25142000322521.pdf
A37: Proyecto Compositor Documental - GNCOM | B37: Caso prueba | C37: Nueva | D37: Normal | E37: FAC_036 | F37: Factura Gas España GFU (F001) Diario y mensual | G37: FACTURACIÓN | H37: Factura Gas España GFU (Multipunto) Formulario: F001 Subformulario: F031/F011/F061 Idioma: ES | I37: Impresión facturas en los distintos idiomas | J37: Generación de xml y PDF | L37: Javi Granadino / Esther Rigo (M. Simón) | M37: 46013 | N37: 45666 | O37: 46027 | Q37: FAC_036_ES_PI25142000325752.xml | R37: FAC_036_ES_PI25142000325752.afp.pdf
C38: Nueva | D38: Normal | E38: FAC_037 | F38: Factura Electriciad España (F002) Excesos de potencia | G38: FACTURACIÓN | H38: Factura Electricidad España Formulario: F002 Subformulario: F022 Idioma: ES | I38: Impresión facturas en los distintos idiomas | J38: Generación de xml y PDF | L38: Javi Granadino / Esther Rigo (M. Simón) | M38: 46013 | N38: 45666 | Q38: FAC_037_ES_PI25142000348578.pdf | R38: FAC_037_ES_PI25142000348578.xml
P39: =(COUNTIF(P2:P35,"OK")/(COUNTBLANK(P2:P35)+(COUNTA(P2:P35)-(COUNTIF(P2:P35,"N/A"))))) -> 0 | Q39: Porcentaje de Avance
P40: =COUNTBLANK(P2:P38)+(COUNTA(P2:P38)-(COUNTIF(P2:P38,"N/A"))-(COUNTIF(P2:P38,"OK"))-(COUNTIF(P2:P38,"KO"))) -> 37 | Q40: Pendiente
P41: =COUNTIF(P2:P35,"KO") -> 0 | Q41: KO
P42: =COUNTIF(P2:P35,"OK") -> 0 | Q42: OK
P43: =COUNTBLANK(P2:P38)+(COUNTA(P2:P38)-(COUNTIF(P2:P38,"N/A"))) -> 37 | Q43: Total

Sheet Cartas GNCOM
A1: Proyecto | B1: Tipo | C1: Estado | D1: Prioridad | E1: Codigo de Prueba | F1: Asunto | G1: Módulos Delta | H1: Datos de prueba | I1: Técnica de pruebas | J1: Resultado esperado | K1: COMENTARIOS NEGOCIO | L1: Responsable | M1: Fecha inicio | N1: Fecha Fin | O1: Fecha Liberado | P1: Resultado OK/KO | Q1: xml papyrus | R1: pdf papyrus
A2: Proyecto Compositor Documental - GNCOM | B2: Caso prueba | C2: Nueva | D2: Normal | E2: COB_001 | F2: Generar carta C001__Carta 347 Totales | G2: Cobros | H2: Carta anterior de la tipología C001 Idioma: CA, ES, EU, GA | I2: Se marcan los eventos para reprocesar. Se ejecutan los procesos de procesamiento de eventos. Se ejecuta el proceso de generación de xml. | J2: Se genera el xml. | K2: Revisión OK | L2: Conchi Martinez | M2: 45662 | N2: 45666 | Q2: COB_001_Generar carta C001__Carta 347 Totales_Castellano_DazelMessage_376949 COB_001_C001_Carta 347 Totales_Catalan_DazelMessage_377025 COB_001_C001_Carta 347 Totales_Euskera_DazelMessage_377043 COB_001_C001_Carta 347 Totales_Gallego_DazelMessage_377044 | R2: COB_001_Generar carta C001__Carta 347 Totales_Castellano COB_001_C001_Carta_347_Totales_Catalan_DazelMessage_377025.afp COB_001_C001_Carta 347 Totales_Euskera_DazelMessage_377043 COB_001_C001_Carta 347 Totales_Gallego_DazelMessage_377044
A3: Proyecto Compositor Documental - GNCOM | B3: Caso prueba | C3: Nueva | D3: Normal | E3: COB_002 | F3: Generar carta C002__Carta 347 Detalle | G3: Cobros | H3: Carta anterior de la tipología C002 Idioma: CA, ES, EU, GA | I3: Se marcan los eventos para reprocesar. Se ejecutan los procesos de procesamiento de eventos. Se ejecuta el proceso de generación de xml. | J3: Se genera el xml. | K3: Revisión OK | L3: Conchi Martinez | M3: 45662 | N3: 45666 | Q3: COB_002_C002_Castellano_DazelMessage_376246 COB_002_C002_Catalan_DazelMessage_377045 COB_002_C002_Euskera_DazelMessage_377046 COB_002_C002_Gallego_DazelMessage_377047 | R3: COB_002_C002_Castellano_DazelMessage_376246.afp COB_002_C002_Catalan_DazelMessage_377045.afp COB_002_C002_Euskera_DazelMessage_377046.afp COB_002_C002_Gallego_DazelMessage_377047.afp
A4: Proyecto Compositor Documental - GNCOM | B4: Caso prueba | C4: Nueva | D4: Normal | E4: COB_003 | F4: Generar carta C003_1__Carta auditor deuda 0 | G4: Cobros | H4: Carta anterior de la tipología C003_1 Idioma: CA, ES, EU, GA | I4: Se marcan los eventos para reprocesar. Se ejecutan los procesos de procesamiento de eventos. Se ejecuta el proceso de generación de xml. | J4: Se genera el xml. | K4: Revisión OK | L4: Conchi Martinez | M4: 45662 | N4: 45666 | Q4: COB_003_C003_1__Carta auditor deuda 0_Castellano_DazelMessage_377131 COB_003_C003_1__Carta auditor deuda 0_Catalan COB_003_C003_1__Carta auditor deuda 0_Euskera COB_003_C003_1__Carta auditor deuda 0_Gallego | R4: COB_003_C003_1__Carta_auditor_deuda_0_Castellano_DazelMessage_377131.afp COB_003_C003_1__Carta_auditor_deuda_0_Catalan_DazelMessage_377131.afp COB_003_C003_1__Carta_auditor_deuda_0_Euskera_DazelMessage_377131.afp COB_003_C003_1__Carta_auditor_deuda_0_Gallego_DazelMessage_377131.afp
A5: Proyecto Compositor Documental - GNCOM | B5: Caso prueba | C5: Nueva | D5: Normal | E5: COB_004 | F5: Generar carta C003__Carta de auditoría | G5: Cobros | H5: Carta anterior de la tipología C003 Idioma: CA, ES, EU, GA | I5: Se marcan los eventos para reprocesar. Se ejecutan los procesos de procesamiento de eventos. Se ejecuta el proceso de generación de xml. | J5: Se genera el xml. | K5: Revisión OK | L5: Conchi Martinez | M5: 45662 | N5: 45666 | Q5: COB_004_C003_Carta de auditoría_castellano_DazelMessage_376915 COB_004_C003_Carta de auditoría_Catalan_DazelMessage_377048 COB_004_C003_Carta de auditoría_Euskera_DazelMessage_377049 COB_004_C003_Carta de auditoría_Gallego_DazelMessage_377050 | R5: COB_004_C003_Carta de auditoría_castellano_DazelMessage_376915.afp COB_004_C003_Carta_de_auditorÝa_Catalan_DazelMessage_377048.afp COB_004_C003_Carta_de_auditorÝa_Euskera_DazelMessage_377049.afp COB_004_C003_Carta_de_auditorÝa_Gallego_DazelMessage_377050.afp
A6: Proyecto Compositor Documental - GNCOM | B6: Caso prueba | C6: Nueva | D6: Normal | E6: COB_005 | F6: Generar carta C004__AAPP Modelo 1 | G6: Cobros | H6: Carta anterior de la tipología C004 Idioma: CA, ES, EU, GA | I6: Se marcan los eventos para reprocesar. Se ejecutan los procesos de procesamiento de eventos. Se ejecuta el proceso de generación de xml. | J6: Se genera el xml. | K6: Revisión OK | L6: Joaquin Pozo | M6: 45662 | N6: 45666
A7: Proyecto Compositor Documental - GNCOM | B7: Caso prueba | C7: Nueva | D7: Normal | E7: COB_006 | F7: Generar carta C005__AAPP Modelo 2 | G7: Cobros | H7: Carta anterior de la tipología C005 Idioma: CA, ES, EU, GA | I7: Se marcan los eventos para reprocesar. Se ejecutan los procesos de procesamiento de eventos. Se ejecuta el proceso de generación de xml. | J7: Se genera el xml. | K7: Revisión OK | L7: Joaquin Pozo | M7: 45662 | N7: 45666
A8: Proyecto Compositor Documental - GNCOM | B8: Caso prueba | C8: Nueva | D8: Normal | E8: COB_007 | F8: Generar carta C009__Carta Aviso Impago Domiciliado | G8: Cobros | H8: Carta anterior de la tipología C009 Idioma: CA, ES, EU, GA | I8: Se marcan los eventos para reprocesar. Se ejecutan los procesos de procesamiento de eventos. Se ejecuta el proceso de generación de xml. | J8: Se genera el xml. | K8: Revisión OK | L8: Joaquin Pozo | M8: 45662 | N8: 45666 | Q8: COB_007_C009_castellano COB_007_C009_catalan COB_007_C009_euskera COB_007_C009_gallego | R8: COB_007_C009_castellano COB_007_C009_catalan.afp COB_007_C009_euskera.afp COB_007_C009_gallego.afp
A9: Proyecto Compositor Documental - GNCOM | B9: Caso prueba | C9: Nueva | D9: Normal | E9: COB_008 | F9: Generar carta C010__Carta aviso impago no domiciliado | G9: Cobros | H9: Carta anterior de la tipología C010 Idioma: CA, ES, EU, GA | I9: Se marcan los eventos para reprocesar. Se ejecutan los procesos de procesamiento de eventos. Se ejecuta el proceso de generación de xml. | J9: Se genera el xml. | K9: Revisión OK | L9: Joaquin Pozo | M9: 45662 | N9: 45666 | Q9: COB_008_carta C010_castellano_DazelMessage_376311 COB_008_carta C010_catalan_DazelMessage_377300 COB_008_carta C010_Euskera_DazelMessage_377301 COB_008_carta C010_Gallego_DazelMessage_377312 | R9: COB_008_carta C010_castellano COB_008_carta C010_Euskera_DazelMessage_377301.afp COB_008_carta C010_Gallego_DazelMessage_377312.afp COB_008_carta C010_catalan_DazelMessage_377300.afp
A10: Proyecto Compositor Documental - GNCOM | B10: Caso prueba | C10: Nueva | D10: Normal | E10: COB_009 | F10: Generar carta C011__Carta Aviso Corte Gas | G10: Cobros | H10: Carta anterior de la tipología C011 Idioma: CA, ES, EU, GA | I10: Se marcan los eventos para reprocesar. Se ejecutan los procesos de procesamiento de eventos. Se ejecuta el proceso de generación de xml. | J10: Se genera el xml. | K10: Revisión OK | L10: Joaquin Pozo | M10: 45662 | N10: 45666 | Q10: COB_009_carta C011_castellano COB_009_carta C011_catalan_DazelMessage_377492 COB_009_carta C011_euskera_DazelMessage_377513 COB_009_carta C011_gallego_DazelMessage_377539 | R10: COB_009_carta C011_castellano.afp COB_009_carta C011_catalan_DazelMessage_377492.afp COB_009_carta C011_euskera_DazelMessage_377513.afp COB_009_carta C011_gallego_DazelMessage_377539.afp
A11: Proyecto Compositor Documental - GNCOM | B11: Caso prueba | C11: Nueva | D11: Normal | E11: COB_010 | F11: Generar carta C012__Carta Aviso Corte Electricidad | G11: Cobros | H11: Carta anterior de la tipología C012 Idioma: CA, ES, EU, GA | I11: Se marcan los eventos para reprocesar. Se ejecutan los procesos de procesamiento de eventos. Se ejecuta el proceso de generación de xml. | J11: Se genera el xml. | K11: Revisión OK | L11: Joaquin Pozo | M11: 45662 | N11: 45666 | Q11: DazelMessage_376558_C012_E.xml DazelMessage_376558_C012_E.xml DazelMessage_377160_C012_K.xml DazelMessage_377163_C012_G.xml | R11: DazelMessage_376558_C012_E.afp.pdf DazelMessage_377080_C012_C.afp.pdf DazelMessage_377160_C012_K.afp.pdf DazelMessage_377163_C012_G.afp.pdf
A12: Proyecto Compositor Documental - GNCOM | B12: Caso prueba | C12: Nueva | D12: Normal | E12: COB_011 | F12: Generar carta C013__Carta Aviso Corte GNL | G12: Cobros | H12: Carta anterior de la tipología C013 Idioma: CA, ES, EU, GA | I12: Se marcan los eventos para reprocesar. Se ejecutan los procesos de procesamiento de eventos. Se ejecuta el proceso de generación de xml. | J12: Se genera el xml. | K12: Revisión OK | L12: Joaquin Pozo | M12: 45662 | N12: 45666 | Q12: DazelMessage_376312_C013_E.xml DazelMessage_377161_C013_K.xml DazelMessage_377079_C013_C.xml DazelMessage_377164_C013_G.xml | R12: DazelMessage_376312_C013_E.afp.pdf DazelMessage_377161_C013_K.afp.pdf DazelMessage_377164_C013_G.afp.pdf DazelMessage_377079_C013_C.afp.pdf
A13: Proyecto Compositor Documental - GNCOM | B13: Caso prueba | C13: Nueva | D13: Normal | E13: COB_012 | F13: Generar carta C014__Carta Aviso Rescisión | G13: Cobros | H13: Carta anterior de la tipología C014 Idioma: CA, ES, EU, GA | I13: Se marcan los eventos para reprocesar. Se ejecutan los procesos de procesamiento de eventos. Se ejecuta el proceso de generación de xml. | J13: Se genera el xml. | K13: Revisión OK | L13: Joaquin Pozo | M13: 45662 | N13: 45666 | Q13: DazelMessage_376638_C014.xml DazelMessage_377302_C014_K.xml DazelMessage_376638_C014_C.xml DazelMessage_377298_C014_G.xml | R13: DazelMessage_377302_C014_K.afp.pdf DazelMessage_376638_C014.afp.pdf DazelMessage_377298_C014_G.afp.pdf DazelMessage_376638_C014_C.afp.pdf
A14: Proyecto Compositor Documental - GNCOM | B14: Caso prueba | C14: Nueva | D14: Normal | E14: COB_013 | F14: Generar carta C015__Jurídico | G14: Cobros | H14: Carta anterior de la tipología C015 Idioma: CA, ES, EU, GA | I14: Se marcan los eventos para reprocesar. Se ejecutan los procesos de procesamiento de eventos. Se ejecuta el proceso de generación de xml. | J14: Se genera el xml. | K14: Revisión OK | L14: Joaquin Pozo | M14: 45662 | N14: 45666 | Q14: DazelMessage_376584_C015_C.xml DazelMessage_377219_C015_G.xml DazelMessage_377406_C015_K.xml DazelMessage_376584_C015.xml | R14: DazelMessage_376584_C015.afp.pdf DazelMessage_377219_C015_G.afp.pdf DazelMessage_376584_C015_C.afp.pdf DazelMessage_377406_C015_K.afp.pdf
A15: Proyecto Compositor Documental - GNCOM | B15: Caso prueba | C15: Nueva | D15: Normal | E15: COB_014 | F15: Generar carta C016__Carta de reconocimiento de deuda Mayoristas modelo Impago | G15: Cobros | H15: Carta anterior de la tipología C016 Idioma: CA, ES, EU, GA | I15: Se marcan los eventos para reprocesar. Se ejecutan los procesos de procesamiento de eventos. Se ejecuta el proceso de generación de xml. | J15: Se genera el xml. | K15: Revisión OK | L15: Joaquin Pozo | M15: 45662 | N15: 45666 | Q15: DazelMessage_377458_C016_K.xml DazelMessage_376339_C016_G.xml DazelMessage_376339_C016.xml DazelMessage_377486_C016_C.xml | R15: DazelMessage_377458_C016_K.afp.pdf DazelMessage_376339_C016_G.afp.pdf DazelMessage_377486_C016_C.afp.pdf DazelMessage_376339_C016.afp.pdf
A16: Proyecto Compositor Documental - GNCOM | B16: Caso prueba | C16: Nueva | D16: Normal | E16: COB_015 | F16: Generar carta C017__Carta de reconocimiento de deuda Mayoristas modelo Fact acumulada | G16: Cobros | H16: Carta anterior de la tipología C017 Idioma: CA, ES, EU, GA | I16: Se marcan los eventos para reprocesar. Se ejecutan los procesos de procesamiento de eventos. Se ejecuta el proceso de generación de xml. | J16: Se genera el xml. | K16: Revisión OK | L16: Joaquin Pozo | M16: 45662 | N16: 45666 | Q16: DazelMessage_376637_C017.xml DazelMessage_377485_C017_C.xml DazelMessage_377457_C017_K.xml DazelMessage_376637_C017_G.xml | R16: DazelMessage_376637_C017.afp.pdf DazelMessage_377485_C017_C.afp.pdf DazelMessage_377457_C017_K.afp.pdf DazelMessage_376637_C017_G.afp.pdf
A17: Proyecto Compositor Documental - GNCOM | B17: Caso prueba | C17: Nueva | D17: Normal | E17: COB_016 | F17: Generar carta C018__Carta de reconocimiento de deuda Mayoristas modelo Sin clausulas | G17: Cobros | H17: Carta anterior de la tipología C018 Idioma: CA, ES, EU, GA | I17: Se marcan los eventos para reprocesar. Se ejecutan los procesos de procesamiento de eventos. Se ejecuta el proceso de generación de xml. | J17: Se genera el xml. | K17: Revisión OK | L17: Joaquin Pozo | M17: 45662 | N17: 45666 | Q17: DazelMessage_376340_C018_G.xml DazelMessage_377643_C018_K.xml DazelMessage_376340_C018.xml DazelMessage_377566_C018_C.xml | R17: DazelMessage_376340_C018_G.afp.pdf DazelMessage_377643_C018_K.afp.pdf DazelMessage_377566_C018_C.afp.pdf DazelMessage_376340_C018.afp.pdf
A18: Proyecto Compositor Documental - GNCOM | B18: Caso prueba | C18: Nueva | D18: Normal | E18: COB_017 | F18: Generar carta C019__Carta Intereses de demora | G18: Cobros | H18: Carta anterior de la tipología C019 Idioma: CA, ES, EU, GA | I18: Se marcan los eventos para reprocesar. Se ejecutan los procesos de procesamiento de eventos. Se ejecuta el proceso de generación de xml. | J18: Se genera el xml. | K18: Revisión OK | L18: Joaquin Pozo | M18: 45662 | N18: 45666 | Q18: DazelMessage_377565_C019_G.xml DazelMessage_377617_C019_K.xml DazelMessage_377565_C019_E.xml DazelMessage_377565_C019_C.xml | R18: DazelMessage_377565_C019_E.afp.pdf DazelMessage_377565_C019_C.afp.pdf DazelMessage_377617_C019_K.afp.pdf DazelMessage_377565_C019_G.afp.pdf
P19: =(COUNTIF(P2:P18,"OK")/(COUNTBLANK(P2:P18)+(COUNTA(P2:P18)-(COUNTIF(P2:P18,"N/A"))))) -> 0 | Q19: Porcentaje de Avance
P20: =COUNTBLANK(P2:P18)+(COUNTA(P2:P18)-(COUNTIF(P2:P18,"N/A"))-(COUNTIF(P2:P18,"OK"))-(COUNTIF(P2:P18,"KO"))) -> 17 | Q20: Pendiente
P21: =COUNTIF(P2:P18,"KO") -> 0 | Q21: KO
P22: =COUNTIF(P2:P18,"OK") -> 0 | Q22: OK
P23: =COUNTBLANK(P2:P18)+(COUNTA(P2:P18)-(COUNTIF(P2:P18,"N/A"))) -> 17 | Q23: Total

Sheet Facturas GNCOMP
A1: Proyecto | B1: Tipo | C1: Estado | D1: Prioridad | E1: Codigo de Prueba | F1: Asunto | G1: Módulos Delta | H1: Datos de prueba | I1: Técnica de pruebas | J1: Resultado esperado | K1: COMENTARIOS NEGOCIO | L1: Responsable | M1: Fecha inicio | N1: Fecha Fin | O1: Fecha Liberado | P1: Resultado OK/KO | Q1: xml papyrus | R1: pdf papyrus
A2: Proyecto Compositor Documental - GNCOM | B2: Caso prueba | C2: Nueva | D2: Normal | E2: FAC_001 | F2: Factura Gas Portugal F401-F411 Subformulario Gas Portugal Lectura mensual | G2: FACTURACIÓN | H2: Factura Gas Portugal con Lectura mensual Formulario: F401 Subformulario: F411 Idioma: PT | I2: Impresión facturas en los distintos idiomas | J2: Generación de xml y PDF | K2: Revisión OK | L2: Javi Granadino / Esther Rigo (M. Simón) | M2: 45669 | N2: 45673 | Q2: FAC_001_PT_FT 259800004336.xml | R2: FAC_001_PT_FT_259800004336.afp.pdf
A3: Proyecto Compositor Documental - GNCOM | B3: Caso prueba | C3: Nueva | D3: Normal | E3: FAC_002 | F3: Factura Gas Portugal F401-F421 Subformulario Gas Portugal Lectura diaria con curva | G3: FACTURACIÓN | H3: Factura Gas Portugal con Lectura diaria con curvaFormulario: F401 Subformulario: F421 Idioma: PT | I3: Impresión facturas en los distintos idiomas | J3: Generación de xml y PDF | K3: Revisión OK | L3: Javi Granadino / Esther Rigo (M. Simón) | M3: 45669 | N3: 45673 | Q3: FAC_002_PT_FT 259800003947 | R3: FAC_002_PT_FT 259800003947.pdf
A4: Proyecto Compositor Documental - GNCOM | B4: Caso prueba | C4: Nueva | D4: Normal | E4: FAC_003 | F4: Factura Gas Portugal CV (F401) | G4: FACTURACIÓN | H4: Factura Gas Portugal CV (Cargo Vario) Formulario: F401 Subformulario: N/A Idioma: PT | I4: Impresión facturas en los distintos idiomas | J4: Generación de xml y PDF | K4: Revisión OK | L4: Javi Granadino / Esther Rigo (M. Simón) | M4: 45669 | N4: 45673 | Q4: FAC_003_PT_FT 259300000082.xml | R4: FAC_003_PT_FT 259300000082.pdf
A5: Proyecto Compositor Documental - GNCOM | B5: Caso prueba | C5: Nueva | D5: Normal | E5: FAC_004 | F5: Factura de ajuste Gas Portugal (F401) | G5: FACTURACIÓN | H5: Factura de ajuste Gas Portugal Formulario: F401 Subformulario: F411/F421 Idioma: PT | I5: Impresión facturas en los distintos idiomas | J5: Generación de xml y PDF | K5: Revisión OK | L5: Javi Granadino / Esther Rigo (M. Simón) | M5: 45669 | N5: 45673 | Q5: DazelMessage_378644.xml Este XML contiene: NroOficial Nombre del XML Nombre del PDF Tipo de Cálculo ND 2599/00000078 DazelMessage_378644.xml DazelMessage_378644_F401.afp.pdf Recalculo ND 2589/00000409 DazelMessage_378644.xml DazelMessage_378644_F401.afp.pdf Ajuste NC 2597/00000214 DazelMessage_378644.xml DazelMessage_378644_F401.afp.pdf Anulación | R5: DazelMessage_378644_F401.afp.pdf Detalle de cada documento: ND 2599/00000078 – Factura de Recalculo En el XML: <tipoCalculo>Recalculo</tipoCalculo> Corresponde a una factura normal con recálculo de consumos. ND 2589/00000409 – Nota de Débito de Ajuste En el XML: <tipoCalculo>Ajuste</tipoCalculo> Es una nota de débito que complementa una factura anterior por diferencias en consumos. NC 2597/00000214 – Nota de Crédito de Anulación En el XML: <tipoCalculo>Anulacion</tipoCalculo> Es una nota de crédito que anula y rectifica íntegramente una factura previa.
A6: Proyecto Compositor Documental - GNCOM | B6: Caso prueba | C6: Nueva | D6: Normal | E6: FAC_005 | F6: Factura de recálculo Gas Portugal (F401) | G6: FACTURACIÓN | H6: Factura de recálculo Gas Portugal Formulario: F401 Subformulario:F411/F421 Idioma: PT | I6: Impresión facturas en los distintos idiomas | J6: Generación de xml y PDF | K6: Revisión OK | L6: Javi Granadino / Esther Rigo (M. Simón) | M6: 45669 | N6: 45673 | Q6: DazelMessage_378644.xml Este XML contiene: NroOficial Nombre del XML Nombre del PDF Tipo de Cálculo ND 2599/00000078 DazelMessage_378644.xml DazelMessage_378644_F401.afp.pdf Recalculo ND 2589/00000409 DazelMessage_378644.xml DazelMessage_378644_F401.afp.pdf Ajuste NC 2597/00000214 DazelMessage_378644.xml DazelMessage_378644_F401.afp.pdf Anulación | R6: DazelMessage_378644_F401.afp.pdf Detalle de cada documento: ND 2599/00000078 – Factura de Recalculo En el XML: <tipoCalculo>Recalculo</tipoCalculo> Corresponde a una factura normal con recálculo de consumos. ND 2589/00000409 – Nota de Débito de Ajuste En el XML: <tipoCalculo>Ajuste</tipoCalculo> Es una nota de débito que complementa una factura anterior por diferencias en consumos. NC 2597/00000214 – Nota de Crédito de Anulación En el XML: <tipoCalculo>Anulacion</tipoCalculo> Es una nota de crédito que anula y rectifica íntegramente una factura previa.
A7: Proyecto Compositor Documental - GNCOM | B7: Caso prueba | C7: Nueva | D7: Normal | E7: FAC_006 | F7: Factura de anulación Gas Portugal (F401) | G7: FACTURACIÓN | H7: Factura de anulación Gas Portugal Formulario: F401 Subformulario: F411/F421 Idioma: PT | I7: Impresión facturas en los distintos idiomas | J7: Generación de xml y PDF | K7: Revisión OK | L7: Javi Granadino / Esther Rigo (M. Simón) | M7: 45669 | N7: 45673 | Q7: DazelMessage_378644.xml Este XML contiene: NroOficial Nombre del XML Nombre del PDF Tipo de Cálculo ND 2599/00000078 DazelMessage_378644.xml DazelMessage_378644_F401.afp.pdf Recalculo ND 2589/00000409 DazelMessage_378644.xml DazelMessage_378644_F401.afp.pdf Ajuste NC 2597/00000214 DazelMessage_378644.xml DazelMessage_378644_F401.afp.pdf Anulación | R7: DazelMessage_378644_F401.afp.pdf Detalle de cada documento: ND 2599/00000078 – Factura de Recalculo En el XML: <tipoCalculo>Recalculo</tipoCalculo> Corresponde a una factura normal con recálculo de consumos. ND 2589/00000409 – Nota de Débito de Ajuste En el XML: <tipoCalculo>Ajuste</tipoCalculo> Es una nota de débito que complementa una factura anterior por diferencias en consumos. NC 2597/00000214 – Nota de Crédito de Anulación En el XML: <tipoCalculo>Anulacion</tipoCalculo> Es una nota de crédito que anula y rectifica íntegramente una factura previa.
A8: Proyecto Compositor Documental - GNCOM | B8: Caso prueba | C8: Nueva | D8: Normal | E8: FAC_007 | F8: Factura Electricidad Portugal F402-F412 Subformulario Electricidad Portugal | G8: FACTURACIÓN | H8: Factura Electricidad Portugal Formulario: F402 Subformulario: F412 Idioma: PT | I8: Impresión facturas en los distintos idiomas | J8: Generación de xml y PDF | K8: Revisión OK | L8: Javi Granadino / Esther Rigo (M. Simón) | M8: 45669 | N8: 45673 | Q8: FAC_007_PT_FT 259800004169 | R8: FAC_007_PT_FT 259800004169.pdf
A9: Proyecto Compositor Documental - GNCOM | B9: Caso prueba | C9: Nueva | D9: Normal | E9: FAC_008 | F9: Factura Electricidad Portugal CV (F402) | G9: FACTURACIÓN | H9: Factura Electricidad Portugal CV (Cargo Vario) Formulario: F402 Subformulario: N/A Idioma: PT | I9: Impresión facturas en los distintos idiomas | J9: Generación de xml y PDF | K9: Revisión OK | L9: Javi Granadino / Esther Rigo (M. Simón) | M9: 45669 | N9: 45673 | Q9: FAC_008_PT_NC 259200000009.xml | R9: FAC_008_PT_NC 259200000009.pdf
A10: Proyecto Compositor Documental - GNCOM | B10: Caso prueba | C10: Nueva | D10: Normal | E10: FAC_009 | F10: Factura de ajuste Electricidad Portugal (F402) | G10: FACTURACIÓN | H10: Factura de ajuste Electricidad Portugal Formulario: F402 Subformulario: N/A Idioma: PT | I10: Impresión facturas en los distintos idiomas | J10: Generación de xml y PDF | K10: Revisión OK | L10: Javi Granadino / Esther Rigo (M. Simón) | M10: 45669 | N10: 45673 | Q10: DazelMessage_378648.xml | R10: DazelMessage_378648_F402.afp.pdf
A11: Proyecto Compositor Documental - GNCOM | B11: Caso prueba | C11: Nueva | D11: Normal | E11: FAC_010 | F11: Factura de recálculo Electricidad Portugal (F402) | G11: FACTURACIÓN | H11: Factura de recálculo Electricidad Portugal Formulario: F402 Subformulario: N/A Idioma: PT | I11: Impresión facturas en los distintos idiomas | J11: Generación de xml y PDF | K11: Revisión OK | L11: Javi Granadino / Esther Rigo (M. Simón) | M11: 45669 | N11: 45673 | Q11: DazelMessage_378645.xml NroOficial Nombre XML Nombre PDF Tipo de Factura NC 2597/00000203 DazelMessage_378645.xml DazelMessage_378645_F402.afp.pdf Anulación ND 2599/00000077 DazelMessage_378645.xml DazelMessage_378645_F402.afp.pdf Recalculo | R11: DazelMessage_378645_F402.afp.pdf NroOficial Nombre XML Nombre PDF Tipo de Factura NC 2597/00000203 DazelMessage_378645.xml DazelMessage_378645_F402.afp.pdf Anulación ND 2599/00000077 DazelMessage_378645.xml DazelMessage_378645_F402.afp.pdf Recalculo
A12: Proyecto Compositor Documental - GNCOM | B12: Caso prueba | C12: Nueva | D12: Normal | E12: FAC_011 | F12: Factura de anulación Electricidad Portugal (F402) | G12: FACTURACIÓN | H12: Factura de anulación Electricidad Portugal Formulario: F402 Subformulario: N/A Idioma: PT | I12: Impresión facturas en los distintos idiomas | J12: Generación de xml y PDF | K12: Revisión OK | L12: Javi Granadino / Esther Rigo (M. Simón) | M12: 45669 | N12: 45673 | Q12: DazelMessage_378645.xml NroOficial Nombre XML Nombre PDF Tipo de Factura NC 2597/00000203 DazelMessage_378645.xml DazelMessage_378645_F402.afp.pdf Anulación ND 2599/00000077 DazelMessage_378645.xml DazelMessage_378645_F402.afp.pdf Recalculo | R12: DazelMessage_378645_F402.afp.pdf NroOficial Nombre XML Nombre PDF Tipo de Factura NC 2597/00000203 DazelMessage_378645.xml DazelMessage_378645_F402.afp.pdf Anulación ND 2599/00000077 DazelMessage_378645.xml DazelMessage_378645_F402.afp.pdf Recalculo
P13: =(COUNTIF(P2:P12,"OK")/(COUNTBLANK(P2:P12)+(COUNTA(P2:P12)-(COUNTIF(P2:P12,"N/A"))))) -> 0 | Q13: Porcentaje de Avance
P14: =COUNTBLANK(P2:P12)+(COUNTA(P2:P12)-(COUNTIF(P2:P12,"N/A"))-(COUNTIF(P2:P12,"OK"))-(COUNTIF(P2:P12,"KO"))) -> 11 | Q14: Pendiente
P15: =COUNTIF(P2:P12,"KO") -> 0 | Q15: KO
P16: =COUNTIF(P2:P12,"OK") -> 0 | Q16: OK
P17: =COUNTBLANK(P2:P12)+(COUNTA(P2:P12)-(COUNTIF(P2:P12,"N/A"))) -> 11 | Q17: Total

Sheet Cartas GNOMP
A1: Proyecto | B1: Tipo | C1: Estado | D1: Prioridad | E1: Codigo de Prueba | F1: Asunto | G1: Módulos Delta | H1: Datos de prueba | I1: Técnica de pruebas | J1: Resultado esperado | K1: COMENTARIOS NEGOCIO | L1: Responsable | M1: Fecha inicio | N1: Fecha Fin | O1: Fecha Liberado | P1: Resultado OK/KO | Q1: xml papyrus | R1: pdf papyrus
A2: Proyecto Compositor Documental - GNCOM | B2: Caso prueba | C2: Nueva | D2: Normal | E2: COB_018 | F2: Generar carta C401__Carta de reconocimiento de deuda Mayoristas PT modelo Impago | G2: Cobros | H2: Carta anterior de la tipología C401 Idioma: PT | I2: Se marcan los eventos para reprocesar. Se ejecutan los procesos de procesamiento de eventos. Se ejecuta el proceso de generación de xml. | J2: Se genera el xml. | K2: Revisión OK | L2: Joaquin Pozo | M2: 45662 | N2: 45666 | Q2: COB_018_C401__Carta de reconocimiento de deuda Mayoristas PT modelo Impago | R2: COB_018_C401__Carta_de_reconocimiento_de_deuda_Mayoristas_PT_modelo_Impago.afp (1),pdf
A3: Proyecto Compositor Documental - GNCOM | B3: Caso prueba | C3: Nueva | D3: Normal | E3: COB_019 | F3: Generar carta C402__Carta de reconocimiento de deuda Mayoristas PT modelo Sin claúsulas | G3: Cobros | H3: Carta anterior de la tipología C402 Idioma: PT | I3: Se marcan los eventos para reprocesar. Se ejecutan los procesos de procesamiento de eventos. Se ejecuta el proceso de generación de xml. | J3: Se genera el xml. | K3: Revisión OK | L3: Joaquin Pozo | M3: 45662 | N3: 45666 | Q3: COB_019_C402__Carta de reconocimiento de deuda Mayoristas PT modelo Sin claúsulas | R3: COB_019_C402__Carta_de_reconocimiento_de_deuda_Mayoristas_PT_modelo_Sin_claŽ‡sulas.afp (1).pdf
P4: =(COUNTIF(P2:P3,"OK")/(COUNTBLANK(P2:P3)+(COUNTA(P2:P3)-(COUNTIF(P2:P3,"N/A"))))) -> 0 | Q4: Porcentaje de Avance
P5: =COUNTBLANK(P2:P3)+(COUNTA(P2:P3)-(COUNTIF(P2:P3,"N/A"))-(COUNTIF(P2:P3,"OK"))-(COUNTIF(P2:P3,"KO"))) -> 2 | Q5: Pendiente
P6: =COUNTIF(P2:P3,"KO") -> 0 | Q6: KO
P7: =COUNTIF(P2:P3,"OK") -> 0 | Q7: OK
P8: =COUNTBLANK(P2:P3)+(COUNTA(P2:P3)-(COUNTIF(P2:P3,"N/A"))) -> 2 | Q8: Total

Sheet Facturas CRGP
A1: Proyecto | B1: Tipo | C1: Estado | D1: Prioridad | E1: Codigo de Prueba | F1: Asunto | G1: Módulos Delta | H1: Ámbito de prueba | I1: Datos de prueba | J1: Técnica de pruebas | K1: Resultado esperado | L1: Comentarios Negocio | M1: Sector | N1: Responsable | O1: Fecha inicio | P1: Fecha Fin | Q1: Fecha Liberado | R1: Resultado OK/KO | S1: xml papyrus | T1: pdf papyrus
A2: Proyecto Compositor Documental - CRGP | B2: Caso prueba | C2: Nueva | D2: Normal | E2: FAC_001 | F2: Cálculo Emisión Impresión Producto TUR 1 Tarifa ATR RL.1 Factura de energía de gas Idioma: CA, ES, EU, GA Domiciliada | G2: Facturación | H2: Proyecto Compositor Documental | I2: Suministro de Gas Tarifa de acceso RL.1 Sin Planta Satélite Tarifa comercial TUR 1 ATR sin curva diaria Formulario: F351 | J2: 1. Se accede a la pantalla de Gestión de órdenes de cálculo, a través de Menú > Facturación > Proceso de cálculo, se introduce la OC de los datos de prueba y se pulsa Buscar. 2. Se selecciona la OC y se pulsa Calcular. 3. En la pantalla de Consulta de log se recupera el DC generado. 4. Se accede a la pantalla Consulta Documento de Cálculo, se introduce el DC y se pulsa Buscar. 5. Se pulsa sobre el hipervínculo del documento de cálculo para acceder al detalle. 6. Se accede a la pantalla de Facturación masiva de documentos de cálculo, a través de Menú > Facturación > Proceso de emisión, se introduce el cálculo de los datos de prueba y se pulsa Facturar. 7. En la pantalla de Consulta de log se recupera la factura generada. 8. Se accede a la pantalla de Gestión de Facturas, a través de Menú > Facturación > Proceso de Emisión, se introduce la factura de los datos de prueba y se pulsa Buscar. 9. Se pulsa sobre el hiperlink Nº Factura. 10. Se accede a la solapa Ver Doc. Impresión | K2: 1. Se recupera la OC. 2. El cálculo se realiza correctamente. 3. Se recupera correctamente el DC generado. 4. Se accede al detalle y se comprueba que el cálculo se ha generado correctamente: 5. La factura se recupera correctamente. 6. Se accede al detalle de la factura. 7. Se comprueba en el documento de impresión: - Se visualiza la factura en PDF, en el idioma del SE de la cuenta correctamente todos los apartados de la factura de energía de gas | L2: Revisión OK | M2: Gas | N2: Toñi Olivares / Natalia Gil (M. Simón) | O2: 45683 | P2: 45694 | S2: DazelMessage_233568333.xml FE25137021610825 CASTELLANO DazelMessage_233568296.xml FE25137021610825 CATALAN DazelMessage_233568308.xml FE25137021610825 EUSKERA DazelMessage_233568320.xml FE25137021610825 GALLEGO | T2: DazelMessage_233568333.afp FE25137021610825 CASTELLANO DazelMessage_233568296.afp FE25137021610825 CATALAN DazelMessage_233568308.afp FE25137021610825 EUSKERA DazelMessage_233568320.afp FE25137021610825 GALLEGO
A3: Proyecto Compositor Documental - CRGP | B3: Caso prueba | C3: Nueva | D3: Normal | E3: FAC_002 | F3: Cálculo Emisión Impresión Producto TUR 1 Tarifa ATR RL.1 Factura de energía de gas Idioma: CA, ES, EU, GA No Domiciliada (con código de barras) | G3: Facturación | H3: Proyecto Compositor Documental | I3: Suministro de Gas Tarifa de acceso RL.1 Sin Planta Satélite Tarifa comercial TUR 1 ATR sin curva diaria Formulario: F352 | J3: 1. Se accede a la pantalla de Gestión de órdenes de cálculo, a través de Menú > Facturación > Proceso de cálculo, se introduce la OC de los datos de prueba y se pulsa Buscar. 2. Se selecciona la OC y se pulsa Calcular. 3. En la pantalla de Consulta de log se recupera el DC generado. 4. Se accede a la pantalla Consulta Documento de Cálculo, se introduce el DC y se pulsa Buscar. 5. Se pulsa sobre el hipervínculo del documento de cálculo para acceder al detalle. 6. Se accede a la pantalla de Facturación masiva de documentos de cálculo, a través de Menú > Facturación > Proceso de emisión, se introduce el cálculo de los datos de prueba y se pulsa Facturar. 7. En la pantalla de Consulta de log se recupera la factura generada. 8. Se accede a la pantalla de Gestión de Facturas, a través de Menú > Facturación > Proceso de Emisión, se introduce la factura de los datos de prueba y se pulsa Buscar. 9. Se pulsa sobre el hiperlink Nº Factura. 10. Se accede a la solapa Ver Doc. Impresión | K3: 1. Se recupera la OC. 2. El cálculo se realiza correctamente. 3. Se recupera correctamente el DC generado. 4. Se accede al detalle y se comprueba que el cálculo se ha generado correctamente: 5. La factura se recupera correctamente. 6. Se accede al detalle de la factura. 7. Se comprueba en el documento de impresión: - Se visualiza la factura en PDF, en el idioma del SE de la cuenta correctamente todos los apartados de la factura de energía de gas | L3: Revisión OK | M3: Gas | N3: Toñi Olivares / Natalia Gil (M. Simón) | O3: 45683 | P3: 45694 | S3: DazelMessage_233568333.xml FE25137015443779 CASTELLANO DazelMessage_233568296.xml FE25137015443779 CATALAN DazelMessage_233568308.xml FE25137015443779 EUSKERA DazelMessage_233568320.xml FE25137015443779 GALLEGO | T3: DazelMessage_233568333.afp FE25137015443779 CASTELLANO DazelMessage_233568296.afp FE25137015443779 CATALAN DazelMessage_233568308.afp FE25137015443779 EUSKERA DazelMessage_233568320.afp FE25137015443779 GALLEGO
A4: Proyecto Compositor Documental - CRGP | B4: Caso prueba | C4: Nueva | D4: Normal | E4: FAC_003 | F4: Cálculo Emisión Impresión Producto TUR 1 Tarifa ATR RL.1 Factura de energía de gas Idioma: CA, ES, EU, GA Domiciliada | G4: Facturación | H4: Proyecto Compositor Documental | I4: Suministro de Gas Tarifa de acceso RL.1 Con Planta Satélite Tarifa comercial TUR 1 ATR sin curva diaria Formulario: F351 | J4: 1. Se accede a la pantalla de Gestión de órdenes de cálculo, a través de Menú > Facturación > Proceso de cálculo, se introduce la OC de los datos de prueba y se pulsa Buscar. 2. Se selecciona la OC y se pulsa Calcular. 3. En la pantalla de Consulta de log se recupera el DC generado. 4. Se accede a la pantalla Consulta Documento de Cálculo, se introduce el DC y se pulsa Buscar. 5. Se pulsa sobre el hipervínculo del documento de cálculo para acceder al detalle. 6. Se accede a la pantalla de Facturación masiva de documentos de cálculo, a través de Menú > Facturación > Proceso de emisión, se introduce el cálculo de los datos de prueba y se pulsa Facturar. 7. En la pantalla de Consulta de log se recupera la factura generada. 8. Se accede a la pantalla de Gestión de Facturas, a través de Menú > Facturación > Proceso de Emisión, se introduce la factura de los datos de prueba y se pulsa Buscar. 9. Se pulsa sobre el hiperlink Nº Factura. 10. Se accede a la solapa Ver Doc. Impresión | K4: 1. Se recupera la OC. 2. El cálculo se realiza correctamente. 3. Se recupera correctamente el DC generado. 4. Se accede al detalle y se comprueba que el cálculo se ha generado correctamente: 5. La factura se recupera correctamente. 6. Se accede al detalle de la factura. 7. Se comprueba en el documento de impresión: - Se visualiza la factura en PDF, en el idioma del SE de la cuenta correctamente todos los apartados de la factura de energía de gas | L4: Revisión OK | M4: Gas | N4: Toñi Olivares / Natalia Gil (M. Simón) | O4: 45683 | P4: 45694 | S4: No Aplica. Ya hay casos de PS para tarifas RLPS.* | T4: No Aplica. Ya hay casos de PS para tarifas RLPS.*
A5: Proyecto Compositor Documental - CRGP | B5: Caso prueba | C5: Nueva | D5: Normal | E5: FAC_004 | F5: Cálculo Emisión Impresión Producto TUR 2 Tarifa ATR RL.2 Factura de energía de gas Idioma: CA, ES, EU, GA Domiciliada | G5: Facturación | H5: Proyecto Compositor Documental | I5: Suministro de Gas Tarifa de acceso RL.2 Sin Planta Satélite Tarifa comercial TUR 2 ATR sin curva diaria Formulario: F353 | J5: 1. Se accede a la pantalla de Gestión de órdenes de cálculo, a través de Menú > Facturación > Proceso de cálculo, se introduce la OC de los datos de prueba y se pulsa Buscar. 2. Se selecciona la OC y se pulsa Calcular. 3. En la pantalla de Consulta de log se recupera el DC generado. 4. Se accede a la pantalla Consulta Documento de Cálculo, se introduce el DC y se pulsa Buscar. 5. Se pulsa sobre el hipervínculo del documento de cálculo para acceder al detalle. 6. Se accede a la pantalla de Facturación masiva de documentos de cálculo, a través de Menú > Facturación > Proceso de emisión, se introduce el cálculo de los datos de prueba y se pulsa Facturar. 7. En la pantalla de Consulta de log se recupera la factura generada. 8. Se accede a la pantalla de Gestión de Facturas, a través de Menú > Facturación > Proceso de Emisión, se introduce la factura de los datos de prueba y se pulsa Buscar. 9. Se pulsa sobre el hiperlink Nº Factura. 10. Se accede a la solapa Ver Doc. Impresión | K5: 1. Se recupera la OC. 2. El cálculo se realiza correctamente. 3. Se recupera correctamente el DC generado. 4. Se accede al detalle y se comprueba que el cálculo se ha generado correctamente: 5. La factura se recupera correctamente. 6. Se accede al detalle de la factura. 7. Se comprueba en el documento de impresión: - Se visualiza la factura en PDF, en el idioma del SE de la cuenta correctamente todos los apartados de la factura de energía de gas | L5: Revisión OK | M5: Gas | N5: Toñi Olivares / Natalia Gil (M. Simón) | O5: 45683 | P5: 45694 | S5: DazelMessage_233568331.xml FE25137021628868 CASTELLANO DazelMessage_233568293.xml FE25137021628868 CATALAN DazelMessage_233568305.xml FE25137021628868 EUSKERA DazelMessage_233568318.xml FE25137021628868 GALLEGO | T5: DazelMessage_233568331.afp FE25137021628868 CASTELLANO DazelMessage_233568293.afp FE25137021628868 CATALAN DazelMessage_233568305.afp FE25137021628868 EUSKERA DazelMessage_233568318.afp FE25137021628868 GALLEGO
A6: Proyecto Compositor Documental - CRGP | B6: Caso prueba | C6: Nueva | D6: Normal | E6: FAC_005 | F6: Cálculo Emisión Impresión Producto TUR 2 Tarifa ATR RL.2 Factura de energía de gas Idioma: CA, ES, EU, GA No domiciliada (con código de barras) | G6: Facturación | H6: Proyecto Compositor Documental | I6: Suministro de Gas Tarifa de acceso RL.2 Sin Planta Satélite Tarifa comercial TUR 2 ATR sin curva diaria Formulario: F354 | J6: 1. Se accede a la pantalla de Gestión de órdenes de cálculo, a través de Menú > Facturación > Proceso de cálculo, se introduce la OC de los datos de prueba y se pulsa Buscar. 2. Se selecciona la OC y se pulsa Calcular. 3. En la pantalla de Consulta de log se recupera el DC generado. 4. Se accede a la pantalla Consulta Documento de Cálculo, se introduce el DC y se pulsa Buscar. 5. Se pulsa sobre el hipervínculo del documento de cálculo para acceder al detalle. 6. Se accede a la pantalla de Facturación masiva de documentos de cálculo, a través de Menú > Facturación > Proceso de emisión, se introduce el cálculo de los datos de prueba y se pulsa Facturar. 7. En la pantalla de Consulta de log se recupera la factura generada. 8. Se accede a la pantalla de Gestión de Facturas, a través de Menú > Facturación > Proceso de Emisión, se introduce la factura de los datos de prueba y se pulsa Buscar. 9. Se pulsa sobre el hiperlink Nº Factura. 10. Se accede a la solapa Ver Doc. Impresión | K6: 1. Se recupera la OC. 2. El cálculo se realiza correctamente. 3. Se recupera correctamente el DC generado. 4. Se accede al detalle y se comprueba que el cálculo se ha generado correctamente: 5. La factura se recupera correctamente. 6. Se accede al detalle de la factura. 7. Se comprueba en el documento de impresión: - Se visualiza la factura en PDF, en el idioma del SE de la cuenta correctamente todos los apartados de la factura de energía de gas | L6: Revisión OK | M6: Gas | N6: Toñi Olivares / Natalia Gil (M. Simón) | O6: 45683 | P6: 45694 | S6: DazelMessage_233568331.xml FE25137016762935 CASTELLANO DazelMessage_233568293.xml FE25137016762935 CATALAN DazelMessage_233568305.xml FE25137016762935 EUSKERA DazelMessage_233568318.xml FE25137016762935 GALLEGO | T6: DazelMessage_233568331.afp FE25137016762935 CASTELLANO DazelMessage_233568293.afp FE25137016762935 CATALAN DazelMessage_233568305.afp FE25137016762935 EUSKERA DazelMessage_233568318.afp FE25137016762935 GALLEGO
A7: Proyecto Compositor Documental - CRGP | B7: Caso prueba | C7: Nueva | D7: Normal | E7: FAC_006 | F7: Cálculo Emisión Impresión Producto TUR 3 Tarifa ATR RL.3 Factura de energía de gas Idioma: CA, ES, EU, GA Domiciliada | G7: Facturación | H7: Proyecto Compositor Documental | I7: Suministro de Gas Tarifa de acceso RL.3 Sin Planta Satélite Tarifa comercial TUR 3 ATR sin curva diaria Formulario: F365 | J7: 1. Se accede a la pantalla de Gestión de órdenes de cálculo, a través de Menú > Facturación > Proceso de cálculo, se introduce la OC de los datos de prueba y se pulsa Buscar. 2. Se selecciona la OC y se pulsa Calcular. 3. En la pantalla de Consulta de log se recupera el DC generado. 4. Se accede a la pantalla Consulta Documento de Cálculo, se introduce el DC y se pulsa Buscar. 5. Se pulsa sobre el hipervínculo del documento de cálculo para acceder al detalle. 6. Se accede a la pantalla de Facturación masiva de documentos de cálculo, a través de Menú > Facturación > Proceso de emisión, se introduce el cálculo de los datos de prueba y se pulsa Facturar. 7. En la pantalla de Consulta de log se recupera la factura generada. 8. Se accede a la pantalla de Gestión de Facturas, a través de Menú > Facturación > Proceso de Emisión, se introduce la factura de los datos de prueba y se pulsa Buscar. 9. Se pulsa sobre el hiperlink Nº Factura. 10. Se accede a la solapa Ver Doc. Impresión | K7: 1. Se recupera la OC. 2. El cálculo se realiza correctamente. 3. Se recupera correctamente el DC generado. 4. Se accede al detalle y se comprueba que el cálculo se ha generado correctamente: 5. La factura se recupera correctamente. 6. Se accede al detalle de la factura. 7. Se comprueba en el documento de impresión: - Se visualiza la factura en PDF, en el idioma del SE de la cuenta correctamente todos los apartados de la factura de energía de gas | L7: Revisión OK | M7: Gas | N7: Toñi Olivares / Natalia Gil (M. Simón) | O7: 45683 | P7: 45694 | S7: DazelMessage_233568339.xml FE25137021620562 CASTELLANO DazelMessage_233568295.xml FE25137021620562 CATALAN DazelMessage_233568310.xml FE25137021620562 EUSKERA DazelMessage_233568321.xml FE25137021620562 GALLEGO | T7: DazelMessage_233568339.afp FE25137021620562 CASTELLANO DazelMessage_233568295.afp FE25137021620562 CATALAN DazelMessage_233568310.afp FE25137021620562 EUSKERA DazelMessage_233568321.afp FE25137021620562 GALLEGO
A8: Proyecto Compositor Documental - CRGP | B8: Caso prueba | C8: Nueva | D8: Normal | E8: FAC_007 | F8: Cálculo Emisión Impresión Producto TUR 3 Tarifa ATR RL.3 Factura de energía de gas Idioma: CA, ES, EU, GA No domiciliada (con código de barras) | G8: Facturación | H8: Proyecto Compositor Documental | I8: Suministro de Gas Tarifa de acceso RL.3 Sin Planta Satélite Tarifa comercial TUR 3 ATR sin curva diaria Formulario: F366 | J8: 1. Se accede a la pantalla de Gestión de órdenes de cálculo, a través de Menú > Facturación > Proceso de cálculo, se introduce la OC de los datos de prueba y se pulsa Buscar. 2. Se selecciona la OC y se pulsa Calcular. 3. En la pantalla de Consulta de log se recupera el DC generado. 4. Se accede a la pantalla Consulta Documento de Cálculo, se introduce el DC y se pulsa Buscar. 5. Se pulsa sobre el hipervínculo del documento de cálculo para acceder al detalle. 6. Se accede a la pantalla de Facturación masiva de documentos de cálculo, a través de Menú > Facturación > Proceso de emisión, se introduce el cálculo de los datos de prueba y se pulsa Facturar. 7. En la pantalla de Consulta de log se recupera la factura generada. 8. Se accede a la pantalla de Gestión de Facturas, a través de Menú > Facturación > Proceso de Emisión, se introduce la factura de los datos de prueba y se pulsa Buscar. 9. Se pulsa sobre el hiperlink Nº Factura. 10. Se accede a la solapa Ver Doc. Impresión | K8: 1. Se recupera la OC. 2. El cálculo se realiza correctamente. 3. Se recupera correctamente el DC generado. 4. Se accede al detalle y se comprueba que el cálculo se ha generado correctamente: 5. La factura se recupera correctamente. 6. Se accede al detalle de la factura. 7. Se comprueba en el documento de impresión: - Se visualiza la factura en PDF, en el idioma del SE de la cuenta correctamente todos los apartados de la factura de energía de gas | L8: Revisión OK | M8: Gas | N8: Toñi Olivares / Natalia Gil (M. Simón) | O8: 45683 | P8: 45694 | S8: DazelMessage_233568339.xml FE25137017148531 CASTELLANO DazelMessage_233568295.xml FE25137017148531 CATALAN DazelMessage_233568310.xml FE25137017148531 EUSKERA DazelMessage_233568321.xml FE25137017148531 GALLEGO | T8: DazelMessage_233568339.afp FE25137017148531 CASTELLANO DazelMessage_233568295.afp FE25137017148531 CATALAN DazelMessage_233568310.afp FE25137017148531 EUSKERA DazelMessage_233568321.afp FE25137017148531 GALLEGO
A9: Proyecto Compositor Documental - CRGP | B9: Caso prueba | C9: Nueva | D9: Normal | E9: FAC_008 | F9: Cálculo Emisión Impresión Producto TUR 1, TUR2 o TUR3 Cualquier Tarifa ATR anterior a peajes 2025 RLPS.1, RLPS.2 o RLPS.3 Factura de energía de gas Idioma: CA, ES, EU, GA Domiciliada | G9: Facturación | H9: Proyecto Compositor Documental | I9: Suministro de Gas Cualquier Tarifa de acceso anterior a peajes 2025 ATR RLPS.1, RLPS.2 o RLPS.3 Tarifa comercial TUR1, TUR2 o TUR3 ATR con o sin curva diaria Formularios: F351, F353 o F365 | J9: 1. Se accede a la pantalla de Gestión de órdenes de cálculo, a través de Menú > Facturación > Proceso de cálculo, se introduce la OC de los datos de prueba y se pulsa Buscar. 2. Se selecciona la OC y se pulsa Calcular. 3. En la pantalla de Consulta de log se recupera el DC generado. 4. Se accede a la pantalla Consulta Documento de Cálculo, se introduce el DC y se pulsa Buscar. 5. Se pulsa sobre el hipervínculo del documento de cálculo para acceder al detalle. 6. Se accede a la pantalla de Facturación masiva de documentos de cálculo, a través de Menú > Facturación > Proceso de emisión, se introduce el cálculo de los datos de prueba y se pulsa Facturar. 7. En la pantalla de Consulta de log se recupera la factura generada. 8. Se accede a la pantalla de Gestión de Facturas, a través de Menú > Facturación > Proceso de Emisión, se introduce la factura de los datos de prueba y se pulsa Buscar. 9. Se pulsa sobre el hiperlink Nº Factura. 10. Se accede a la solapa Ver Doc. Impresión | K9: 1. Se recupera la OC. 2. El cálculo se realiza correctamente. 3. Se recupera correctamente el DC generado. 4. Se accede al detalle y se comprueba que el cálculo se ha generado correctamente: 5. La factura se recupera correctamente. 6. Se accede al detalle de la factura. 7. Se comprueba en el documento de impresión: - Se visualiza la factura en PDF, en el idioma del SE de la cuenta correctamente todos los apartados de la factura de energía de gas | L9: Revisión OK | M9: Gas | N9: Toñi Olivares / Natalia Gil (M. Simón) | O9: 45683 | P9: 45694 | S9: DazelMessage_233568338.xml FE25137021547483 CASTELLANO DazelMessage_233568297.xml FE25137021547483 CATALAN DazelMessage_233568309.xml FE25137021547483 EUSKERA DazelMessage_233568326.xml FE25137021547483 GALLEGO | T9: DazelMessage_233568338.afp FE25137021547483 CASTELLANO DazelMessage_233568297.afp FE25137021547483 CATALAN DazelMessage_233568309.afp FE25137021547483 EUSKERA DazelMessage_233568326.afp FE25137021547483 GALLEGO
A10: Proyecto Compositor Documental - CRGP | B10: Caso prueba | C10: Nueva | D10: Normal | E10: FAC_009 | F10: Cálculo de abono Factura de anulación Impresión Producto TUR 1, TUR2 o TUR3 Cualquier Tarifa ATR RL.1, RL.2 o RL.3 Factura de energía de gas Idioma: CA, ES, EU, GA Domiciliada | G10: Facturación | H10: Proyecto Compositor Documental | I10: Suministro de Gas Cualquier Tarifa de acceso RL.1, RL.2 o RL.3 con o sin Planta Satélite Tarifa comercial TUR1, TUR2 o TUR3 ATR con o sin curva diaria Formularios: F351, F353 o F365 | J10: 1. Se accede a la pantalla de Gestión de órdenes de cálculo, a través de Menú > Facturación > Proceso de cálculo, se introduce la OC de los datos de prueba y se pulsa Buscar. 2. Se selecciona la OC y se pulsa Calcular. 3. En la pantalla de Consulta de log se recupera el DC generado. 4. Se accede a la pantalla Consulta Documento de Cálculo, se introduce el DC y se pulsa Buscar. 5. Se pulsa sobre el hipervínculo del documento de cálculo para acceder al detalle. 6. Se accede a la pantalla de Facturación masiva de documentos de cálculo, a través de Menú > Facturación > Proceso de emisión, se introduce el cálculo de los datos de prueba y se pulsa Facturar. 7. En la pantalla de Consulta de log se recupera la factura generada. 8. Se accede a la pantalla de Gestión de Facturas, a través de Menú > Facturación > Proceso de Emisión, se introduce la factura de los datos de prueba y se pulsa Buscar. 9. Se pulsa sobre el hiperlink Nº Factura. 10. Se accede a la solapa Ver Doc. Impresión | K10: 1. Se recupera la OC. 2. El cálculo se realiza correctamente. 3. Se recupera correctamente el DC generado. 4. Se accede al detalle y se comprueba que el cálculo se ha generado correctamente: 5. La factura se recupera correctamente. 6. Se accede al detalle de la factura. 7. Se comprueba en el documento de impresión: - Se visualiza la factura en PDF, en el idioma del SE de la cuenta correctamente todos los apartados de la factura de energía de gas | L10: Revisión OK | M10: Gas | N10: Toñi Olivares / Natalia Gil (M. Simón) | O10: 45683 | P10: 45694 | S10: DazelMessage_233568331.xml SU25137000160153 CASTELLANO DazelMessage_233568293.xml SU25137000160153 CATALAN DazelMessage_233568305.xml SU25137000160153 EUSKERA DazelMessage_233568318.xml SU25137000160153 GALLEGO | T10: DazelMessage_233568331.afp SU25137000160153 CASTELLANO DazelMessage_233568293.afp SU25137000160153 CATALAN DazelMessage_233568305.afp SU25137000160153 EUSKERA DazelMessage_233568318.afp SU25137000160153 GALLEGO
A11: Proyecto Compositor Documental - CRGP | B11: Caso prueba | C11: Nueva | D11: Normal | E11: FAC_010 | F11: Recálculo Refacturación Impresión Producto TUR 1, TUR2 o TUR3 Cualquier Tarifa ATR RL.1, RL.2 o RL.3 Factura de energía de gas Idioma: CA, ES, EU, GA Domiciliada | G11: Facturación | H11: Proyecto Compositor Documental | I11: Suministro de Gas Cualquier Tarifa de acceso RL.1, RL.2 o RL.3 con o sin Planta Satélite Tarifa comercial TUR1, TUR2 o TUR3 ATR con o sin curva diaria Formularios: F351, F353 o F365 | J11: 1. Se accede a la pantalla de Gestión de órdenes de cálculo, a través de Menú > Facturación > Proceso de cálculo, se introduce la OC de los datos de prueba y se pulsa Buscar. 2. Se selecciona la OC y se pulsa Calcular. 3. En la pantalla de Consulta de log se recupera el DC generado. 4. Se accede a la pantalla Consulta Documento de Cálculo, se introduce el DC y se pulsa Buscar. 5. Se pulsa sobre el hipervínculo del documento de cálculo para acceder al detalle. 6. Se accede a la pantalla de Facturación masiva de documentos de cálculo, a través de Menú > Facturación > Proceso de emisión, se introduce el cálculo de los datos de prueba y se pulsa Facturar. 7. En la pantalla de Consulta de log se recupera la factura generada. 8. Se accede a la pantalla de Gestión de Facturas, a través de Menú > Facturación > Proceso de Emisión, se introduce la factura de los datos de prueba y se pulsa Buscar. 9. Se pulsa sobre el hiperlink Nº Factura. 10. Se accede a la solapa Ver Doc. Impresión | K11: 1. Se recupera la OC. 2. El cálculo se realiza correctamente. 3. Se recupera correctamente el DC generado. 4. Se accede al detalle y se comprueba que el cálculo se ha generado correctamente: 5. La factura se recupera correctamente. 6. Se accede al detalle de la factura. 7. Se comprueba en el documento de impresión: - Se visualiza la factura en PDF, en el idioma del SE de la cuenta correctamente todos los apartados de la factura de energía de gas | L11: Revisión OK | M11: Gas | N11: Toñi Olivares / Natalia Gil (M. Simón) | O11: 45683 | P11: 45694 | S11: DazelMessage_233568339.xml RE25137000100915 CASTELLANO DazelMessage_233568295.xml RE25137000100915 CATALAN DazelMessage_233568310.xml RE25137000100915 EUSKERA DazelMessage_233568321.xml RE25137000100915 GALLEGO | T11: DazelMessage_233568339.afp RE25137000100915 CASTELLANO DazelMessage_233568295.afp RE25137000100915 CATALAN DazelMessage_233568310.afp RE25137000100915 EUSKERA DazelMessage_233568321.afp RE25137000100915 GALLEGO
A12: Proyecto Compositor Documental - CRGP | B12: Caso prueba | C12: Nueva | D12: Normal | E12: FAC_011 | F12: Cálculo de Ajuste Factura de ajuste Impresión Producto TUR 1, TUR2 o TUR3 Cualquier Tarifa ATR RL.1, RL.2 o RL.3 Factura de energía de gas Idioma: CA, ES, EU, GA Domiciliada | G12: Facturación | H12: Proyecto Compositor Documental | I12: Suministro de Gas Cualquier Tarifa de acceso RL.1, RL.2 o RL.3 con o sin Planta Satélite Tarifa comercial TUR1, TUR2 o TUR3 ATR con o sin curva diaria Formularios: F351, F353 o F365 | J12: 1. Se accede a la pantalla de Gestión de órdenes de cálculo, a través de Menú > Facturación > Proceso de cálculo, se introduce la OC de los datos de prueba y se pulsa Buscar. 2. Se selecciona la OC y se pulsa Calcular. 3. En la pantalla de Consulta de log se recupera el DC generado. 4. Se accede a la pantalla Consulta Documento de Cálculo, se introduce el DC y se pulsa Buscar. 5. Se pulsa sobre el hipervínculo del documento de cálculo para acceder al detalle. 6. Se accede a la pantalla de Facturación masiva de documentos de cálculo, a través de Menú > Facturación > Proceso de emisión, se introduce el cálculo de los datos de prueba y se pulsa Facturar. 7. En la pantalla de Consulta de log se recupera la factura generada. 8. Se accede a la pantalla de Gestión de Facturas, a través de Menú > Facturación > Proceso de Emisión, se introduce la factura de los datos de prueba y se pulsa Buscar. 9. Se pulsa sobre el hiperlink Nº Factura. 10. Se accede a la solapa Ver Doc. Impresión | K12: 1. Se recupera la OC. 2. El cálculo se realiza correctamente. 3. Se recupera correctamente el DC generado. 4. Se accede al detalle y se comprueba que el cálculo se ha generado correctamente: 5. La factura se recupera correctamente. 6. Se accede al detalle de la factura. 7. Se comprueba en el documento de impresión: - Se visualiza la factura en PDF, en el idioma del SE de la cuenta correctamente todos los apartados de la factura de energía de gas | L12: Revisión OK | M12: Gas | N12: Toñi Olivares / Natalia Gil (M. Simón) | O12: 45683 | P12: 45694 | S12: DazelMessage_233568333.xml AE25137000349203 CASTELLANO DazelMessage_233568296.xml AE25137000349203 CATALAN DazelMessage_233568308.xml AE25137000349203 EUSKERA DazelMessage_233568320.xml AE25137000349203 GALLEGO | T12: DazelMessage_233568333.afp AE25137000349203 CASTELLANO DazelMessage_233568296.afp AE25137000349203 CATALAN DazelMessage_233568308.afp AE25137000349203 EUSKERA DazelMessage_233568320.afp AE25137000349203 GALLEGO
A13: Proyecto Compositor Documental - CRGP | B13: Caso prueba | C13: Nueva | D13: Normal | E13: FAC_012 | F13: Cálculo Factura Impresión Producto TUR 1, TUR2 o TUR3 Cualquier Tarifa ATR RL.1, RL.2 o RL.3 Factura de energía de gas con cambio de precios Idioma: CA, ES, EU, GA Domiciliada | G13: Facturación | H13: Proyecto Compositor Documental | I13: Suministro de Gas con cambio de precios Cualquier Tarifa de acceso RL.1, RL.2 o RL.3 con o sin Planta Satélite Tarifa comercial TUR1, TUR2 o TUR3 ATR con o sin curva diaria Formularios: F351, F353 o F365 | J13: 1. Se accede a la pantalla de Gestión de órdenes de cálculo, a través de Menú > Facturación > Proceso de cálculo, se introduce la OC de los datos de prueba y se pulsa Buscar. 2. Se selecciona la OC y se pulsa Calcular. 3. En la pantalla de Consulta de log se recupera el DC generado. 4. Se accede a la pantalla Consulta Documento de Cálculo, se introduce el DC y se pulsa Buscar. 5. Se pulsa sobre el hipervínculo del documento de cálculo para acceder al detalle. 6. Se accede a la pantalla de Facturación masiva de documentos de cálculo, a través de Menú > Facturación > Proceso de emisión, se introduce el cálculo de los datos de prueba y se pulsa Facturar. 7. En la pantalla de Consulta de log se recupera la factura generada. 8. Se accede a la pantalla de Gestión de Facturas, a través de Menú > Facturación > Proceso de Emisión, se introduce la factura de los datos de prueba y se pulsa Buscar. 9. Se pulsa sobre el hiperlink Nº Factura. 10. Se accede a la solapa Ver Doc. Impresión | K13: 1. Se recupera la OC. 2. El cálculo se realiza correctamente. 3. Se recupera correctamente el DC generado. 4. Se accede al detalle y se comprueba que el cálculo se ha generado correctamente: 5. La factura se recupera correctamente. 6. Se accede al detalle de la factura. 7. Se comprueba en el documento de impresión: - Se visualiza la factura en PDF, en el idioma del SE de la cuenta correctamente todos los apartados de la factura de energía de gas | L13: Revisión OK | M13: Gas | N13: Toñi Olivares / Natalia Gil (M. Simón) | O13: 45683 | P13: 45694 | S13: DazelMessage_233568338.xml FE25137004394691 CASTELLANO DazelMessage_233568297.xml FE25137004394691 CATALAN DazelMessage_233568309.xml FE25137004394691 EUSKERA DazelMessage_233568326.xml FE25137004394691 GALLEGO | T13: DazelMessage_233568338.afp FE25137004394691 CASTELLANO DazelMessage_233568297.afp FE25137004394691 CATALAN DazelMessage_233568309.afp FE25137004394691 EUSKERA DazelMessage_233568326.afp FE25137004394691 GALLEGO
... A96: Proyecto Compositor Documental - CRGP | B96: Caso prueba | C96: Nueva | D96: Normal | E96: FAC_095 | F96: Cálculo Factura Impresión Producto PVPC con marca microempresa Idioma: CA, ES, EU, GA Domiciliada | G96: Facturación | H96: Proyecto Compositor Documental | I96: Suministro de Electricidad producto PVPC marca microempresa | J96: 1. Se accede a la pantalla de Gestión de órdenes de cálculo, a través de Menú > Facturación > Proceso de cálculo, se introduce la OC de los datos de prueba y se pulsa Buscar. 2. Se selecciona la OC y se pulsa Calcular. 3. En la pantalla de Consulta de log se recupera el DC generado. 4. Se accede a la pantalla Consulta Documento de Cálculo, se introduce el DC y se pulsa Buscar. 5. Se pulsa sobre el hipervínculo del documento de cálculo para acceder al detalle. 6. Se accede a la pantalla de Facturación masiva de documentos de cálculo, a través de Menú > Facturación > Proceso de emisión, se introduce el cálculo de los datos de prueba y se pulsa Facturar. 7. En la pantalla de Consulta de log se recupera la factura generada. 8. Se accede a la pantalla de Gestión de Facturas, a través de Menú > Facturación > Proceso de Emisión, se introduce la factura de los datos de prueba y se pulsa Buscar. 9. Se pulsa sobre el hiperlink Nº Factura. 10. Se accede a la solapa Ver Doc. Impresión | K96: 1. Se recupera la OC. 2. El cálculo se realiza correctamente. 3. Se recupera correctamente el DC generado. 4. Se accede al detalle y se comprueba que el cálculo se ha generado correctamente: 5. La factura se recupera correctamente. 6. Se accede al detalle de la factura. 7. Se comprueba en el documento de impresión: - Se visualiza la factura en PDF, en el idioma del SE de la cuenta correctamente todos los apartados de la factura de energía de electricidad o factura separada de cargos varios de electricidad | L96: Revisión OK | M96: Electricidad | N96: Toñi Olivares / Natalia Gil (M. Simón) | O96: 45683 | P96: 45694 | S96: DazelMessage_233668257.xml FE25137020485119 CASTELLANO DazelMessage_233668264.xml FE25137020485119 CATALAN DazelMessage_233668272.xml FE25137020485119 EUSKERA DazelMessage_233668275.xml FE25137020485119 GALLEGO | T96: DazelMessage_233668257_ele.afp FE25137020485119 CASTELLANO DazelMessage_233668264_ele.afp FE25137020485119 CATALAN DazelMessage_233668272_ele.afp FE25137020485119 EUSKERA DazelMessage_233668275_ele.afp FE25137020485119 GALLEGO
A97: Proyecto Compositor Documental - CRGP | B97: Caso prueba | C97: Nueva | D97: Normal | E97: FAC_096 | F97: Cálculo Factura Impresión Producto electricidad con Ajuste con varios IIEE Idioma: CA, ES, EU, GA Domiciliada | I97: Cálculo Factura Impresión Producto electricidad con Ajuste con varios IIEE | J97: 1. Se accede a la pantalla de Gestión de órdenes de cálculo, a través de Menú > Facturación > Proceso de cálculo, se introduce la OC de los datos de prueba y se pulsa Buscar. 2. Se selecciona la OC y se pulsa Calcular. 3. En la pantalla de Consulta de log se recupera el DC generado. 4. Se accede a la pantalla Consulta Documento de Cálculo, se introduce el DC y se pulsa Buscar. 5. Se pulsa sobre el hipervínculo del documento de cálculo para acceder al detalle. 6. Se accede a la pantalla de Facturación masiva de documentos de cálculo, a través de Menú > Facturación > Proceso de emisión, se introduce el cálculo de los datos de prueba y se pulsa Facturar. 7. En la pantalla de Consulta de log se recupera la factura generada. 8. Se accede a la pantalla de Gestión de Facturas, a través de Menú > Facturación > Proceso de Emisión, se introduce la factura de los datos de prueba y se pulsa Buscar. 9. Se pulsa sobre el hiperlink Nº Factura. 10. Se accede a la solapa Ver Doc. Impresión | K97: 1. Se recupera la OC. 2. El cálculo se realiza correctamente. 3. Se recupera correctamente el DC generado. 4. Se accede al detalle y se comprueba que el cálculo se ha generado correctamente: 5. La factura se recupera correctamente. 6. Se accede al detalle de la factura. 7. Se comprueba en el documento de impresión: - Se visualiza la factura en PDF, en el idioma del SE de la cuenta correctamente todos los apartados de la factura de energía de electricidad o factura separada de cargos varios de electricidad | L97: Revisión OK | M97: Electricidad | N97: Toñi Olivares / Natalia Gil (M. Simón) | O97: 45683 | P97: 45694 | S97: DazelMessage_233648256.xml AE24137000201940 CASTELLANO DazelMessage_233648262.xml AE24137000201940 CATALAN DazelMessage_233648272.xml AE24137000201940 EUSKERA DazelMessage_233648276.xml AE24137000201940 GALLEGO | T97: DazelMessage_233648256.afp AE24137000201940 CASTELLANO DazelMessage_233648262.afp AE24137000201940 CATALAN DazelMessage_233648272.afp AE24137000201940 EUSKERA DazelMessage_233648276.afp AE24137000201940 GALLEGO
A98: Proyecto Compositor Documental - CRGP | B98: Caso prueba | C98: Nueva | D98: Normal | E98: FAC_097 | F98: Cálculo Factura Impresión Producto electricidad con Factura que tenga Mínimo Comunitario Idioma: CA, ES, EU, GA Domiciliada | I98: Cálculo Factura Impresión Producto electricidad con Factura que tenga Mínimo Comunitario | J98: 1. Se accede a la pantalla de Gestión de órdenes de cálculo, a través de Menú > Facturación > Proceso de cálculo, se introduce la OC de los datos de prueba y se pulsa Buscar. 2. Se selecciona la OC y se pulsa Calcular. 3. En la pantalla de Consulta de log se recupera el DC generado. 4. Se accede a la pantalla Consulta Documento de Cálculo, se introduce el DC y se pulsa Buscar. 5. Se pulsa sobre el hipervínculo del documento de cálculo para acceder al detalle. 6. Se accede a la pantalla de Facturación masiva de documentos de cálculo, a través de Menú > Facturación > Proceso de emisión, se introduce el cálculo de los datos de prueba y se pulsa Facturar. 7. En la pantalla de Consulta de log se recupera la factura generada. 8. Se accede a la pantalla de Gestión de Facturas, a través de Menú > Facturación > Proceso de Emisión, se introduce la factura de los datos de prueba y se pulsa Buscar. 9. Se pulsa sobre el hiperlink Nº Factura. 10. Se accede a la solapa Ver Doc. Impresión | K98: 1. Se recupera la OC. 2. El cálculo se realiza correctamente. 3. Se recupera correctamente el DC generado. 4. Se accede al detalle y se comprueba que el cálculo se ha generado correctamente: 5. La factura se recupera correctamente. 6. Se accede al detalle de la factura. 7. Se comprueba en el documento de impresión: - Se visualiza la factura en PDF, en el idioma del SE de la cuenta correctamente todos los apartados de la factura de energía de electricidad o factura separada de cargos varios de electricidad | L98: Revisión OK | M98: Electricidad | N98: Toñi Olivares / Natalia Gil (M. Simón) | O98: 45683 | P98: 45694 | S98: DazelMessage_233648258.xml RE21137000121046 CASTELLANO DazelMessage_233648261.xml RE21137000121046 CATALAN DazelMessage_233648266.xml RE21137000121046 EUSKERA DazelMessage_233648275.xml RE21137000121046 GALLEGO | T98: DazelMessage_233648258.afp RE21137000121046 CASTELLANO DazelMessage_233648261.afp RE21137000121046 CATALAN DazelMessage_233648266.afp RE21137000121046 EUSKERA DazelMessage_233648275.afp RE21137000121046 GALLEGO
A99: Proyecto Compositor Documental - CRGP | B99: Caso prueba | C99: Nueva | D99: Normal | E99: FAC_098 | F99: Cálculo Factura Impresión Producto electricidad con PVPC que incluya compensación excedente, límite compensación excedente, retardo autoconsumo distribuidor o comercializador y su limite correspondiente. Idioma: CA, ES, EU, GA Domiciliada | I99: Cálculo Factura Impresión Producto electricidad con PVPC que incluya compensación excedente, límite compensación excedente, retardo autoconsumo distribuidor o comercializador y su límite correspondiente. | J99: 1. Se accede a la pantalla de Gestión de órdenes de cálculo, a través de Menú > Facturación > Proceso de cálculo, se introduce la OC de los datos de prueba y se pulsa Buscar. 2. Se selecciona la OC y se pulsa Calcular. 3. En la pantalla de Consulta de log se recupera el DC generado. 4. Se accede a la pantalla Consulta Documento de Cálculo, se introduce el DC y se pulsa Buscar. 5. Se pulsa sobre el hipervínculo del documento de cálculo para acceder al detalle. 6. Se accede a la pantalla de Facturación masiva de documentos de cálculo, a través de Menú > Facturación > Proceso de emisión, se introduce el cálculo de los datos de prueba y se pulsa Facturar. 7. En la pantalla de Consulta de log se recupera la factura generada. 8. Se accede a la pantalla de Gestión de Facturas, a través de Menú > Facturación > Proceso de Emisión, se introduce la factura de los datos de prueba y se pulsa Buscar. 9. Se pulsa sobre el hiperlink Nº Factura. 10. Se accede a la solapa Ver Doc. Impresión | K99: 1. Se recupera la OC. 2. El cálculo se realiza correctamente. 3. Se recupera correctamente el DC generado. 4. Se accede al detalle y se comprueba que el cálculo se ha generado correctamente: 5. La factura se recupera correctamente. 6. Se accede al detalle de la factura. 7. Se comprueba en el documento de impresión: - Se visualiza la factura en PDF, en el idioma del SE de la cuenta correctamente todos los apartados de la factura de energía de electricidad o factura separada de cargos varios de electricidad | L99: Revisión OK | M99: Electricidad | N99: Toñi Olivares / Natalia Gil (M. Simón) | O99: 45683 | P99: 45694 | S99: DazelMessage_233648258.xml FE25137019644941 CASTELLANO DazelMessage_233648261.xml FE25137019644941 CATALAN DazelMessage_233648266.xml FE25137019644941 EUSKERA DazelMessage_233648275.xml FE25137019644941 GALLEGO DazelMessage_233648258.xml FE25137002448799 CASTELLANO DazelMessage_233648261.xml FE25137002448799 CATALAN DazelMessage_233648266.xml FE25137002448799 EUSKERA DazelMessage_233648275.xml FE25137002448799 GALLEGO DazelMessage_233648258.xml FE25137001939522 CASTELLANO DazelMessage_233648261.xml FE25137001939522 CATALAN DazelMessage_233648266.xml FE25137001939522 EUSKERA DazelMessage_233648275.xml FE25137001939522 GALLEGO | T99: DazelMessage_233648258.afp FE25137019644941 CASTELLANO DazelMessage_233648261.afp FE25137019644941 CATALAN DazelMessage_233648266.afp FE25137019644941 EUSKERA DazelMessage_233648275.afp FE25137019644941 GALLEGO DazelMessage_233648258.afp FE25137002448799 CASTELLANO DazelMessage_233648261.afp FE25137002448799 CATALAN DazelMessage_233648266.afp FE25137002448799 EUSKERA DazelMessage_233648275.afp FE25137002448799 GALLEGO DazelMessage_233648258.afp FE25137001939522 CASTELLANO DazelMessage_233648261.afp FE25137001939522 CATALAN DazelMessage_233648266.afp FE25137001939522 EUSKERA DazelMessage_233648275.afp FE25137001939522 GALLEGO
A100: Proyecto Compositor Documental - CRGP | B100: Caso prueba | C100: Nueva | D100: Normal | E100: FAC_099 | F100: Cálculo Factura Impresión Producto electricidad con Bono Social Vulnerable que incluya compensación excedente, límite compensación excedente, retardo autoconsumo distribuidor o comercializador y su limite correspondiente. Idioma: CA, ES, EU, GA Domiciliada | I100: Cálculo Factura Impresión Producto electricidad con Bono Social Vulnerable que incluya compensación excedente, límite compensación excedente, retardo autoconsumo distribuidor o comercializador y su límite correspondiente. | J100: 1. Se accede a la pantalla de Gestión de órdenes de cálculo, a través de Menú > Facturación > Proceso de cálculo, se introduce la OC de los datos de prueba y se pulsa Buscar. 2. Se selecciona la OC y se pulsa Calcular. 3. En la pantalla de Consulta de log se recupera el DC generado. 4. Se accede a la pantalla Consulta Documento de Cálculo, se introduce el DC y se pulsa Buscar. 5. Se pulsa sobre el hipervínculo del documento de cálculo para acceder al detalle. 6. Se accede a la pantalla de Facturación masiva de documentos de cálculo, a través de Menú > Facturación > Proceso de emisión, se introduce el cálculo de los datos de prueba y se pulsa Facturar. 7. En la pantalla de Consulta de log se recupera la factura generada. 8. Se accede a la pantalla de Gestión de Facturas, a través de Menú > Facturación > Proceso de Emisión, se introduce la factura de los datos de prueba y se pulsa Buscar. 9. Se pulsa sobre el hiperlink Nº Factura. 10. Se accede a la solapa Ver Doc. Impresión | K100: 1. Se recupera la OC. 2. El cálculo se realiza correctamente. 3. Se recupera correctamente el DC generado. 4. Se accede al detalle y se comprueba que el cálculo se ha generado correctamente: 5. La factura se recupera correctamente. 6. Se accede al detalle de la factura. 7. Se comprueba en el documento de impresión: - Se visualiza la factura en PDF, en el idioma del SE de la cuenta correctamente todos los apartados de la factura de energía de electricidad o factura separada de cargos varios de electricidad | L100: Revisión OK | M100: Electricidad | N100: Toñi Olivares / Natalia Gil (M. Simón) | O100: 45683 | P100: 45694 | S100: DazelMessage_233648257.xml FE24137026414443 CASTELLANO DazelMessage_233648263.xml FE24137026414443 CATALAN DazelMessage_233648267.xml FE24137026414443 EUSKERA DazelMessage_233648273.xml FE24137026414443 GALLEGO DazelMessage_233648257.xml FE25137001929477 CASTELLANO DazelMessage_233648263.xml FE25137001929477 CATALAN DazelMessage_233648267.xml FE25137001929477 EUSKERA DazelMessage_233648273.xml FE25137001929477 GALLEGO DazelMessage_233648257.xml FE25137019681393 CASTELLANO DazelMessage_233648263.xml FE25137019681393 CATALAN DazelMessage_233648267.xml FE25137019681393 EUSKERA DazelMessage_233648273.xml FE25137019681393 GALLEGO | T100: DazelMessage_233648257.afp FE24137026414443 CASTELLANO DazelMessage_233648263.afp FE24137026414443 CATALAN DazelMessage_233648267.afp FE24137026414443 EUSKERA DazelMessage_233648273.afp FE24137026414443 GALLEGO DazelMessage_233648257.afp FE25137001929477 CASTELLANO DazelMessage_233648263.afp FE25137001929477 CATALAN DazelMessage_233648267.afp FE25137001929477 EUSKERA DazelMessage_233648273.afp FE25137001929477 GALLEGO DazelMessage_233648257.afp FE25137019681393 CASTELLANO DazelMessage_233648263.afp FE25137019681393 CATALAN DazelMessage_233648267.afp FE25137019681393 EUSKERA DazelMessage_233648273.afp FE25137019681393 GALLEGO
A101: Proyecto Compositor Documental - CRGP | B101: Caso prueba | C101: Nueva | D101: Normal | E101: FAC_100 | F101: Factura que contenga el mensaje del topado con el megawatio/hora. Idioma: CA, ES, EU, GA Domiciliada | I101: Factura que contenga el mensaje del topado con el megawatio/hora. | J101: 1. Se accede a la pantalla de Gestión de órdenes de cálculo, a través de Menú > Facturación > Proceso de cálculo, se introduce la OC de los datos de prueba y se pulsa Buscar. 2. Se selecciona la OC y se pulsa Calcular. 3. En la pantalla de Consulta de log se recupera el DC generado. 4. Se accede a la pantalla Consulta Documento de Cálculo, se introduce el DC y se pulsa Buscar. 5. Se pulsa sobre el hipervínculo del documento de cálculo para acceder al detalle. 6. Se accede a la pantalla de Facturación masiva de documentos de cálculo, a través de Menú > Facturación > Proceso de emisión, se introduce el cálculo de los datos de prueba y se pulsa Facturar. 7. En la pantalla de Consulta de log se recupera la factura generada. 8. Se accede a la pantalla de Gestión de Facturas, a través de Menú > Facturación > Proceso de Emisión, se introduce la factura de los datos de prueba y se pulsa Buscar. 9. Se pulsa sobre el hiperlink Nº Factura. 10. Se accede a la solapa Ver Doc. Impresión | K101: 1. Se recupera la OC. 2. El cálculo se realiza correctamente. 3. Se recupera correctamente el DC generado. 4. Se accede al detalle y se comprueba que el cálculo se ha generado correctamente: 5. La factura se recupera correctamente. 6. Se accede al detalle de la factura. 7. Se comprueba en el documento de impresión: - Se visualiza la factura en PDF, en el idioma del SE de la cuenta correctamente todos los apartados de la factura de energía de electricidad o factura separada de cargos varios de electricidad | L101: Revisión OK | M101: Electricidad | N101: Toñi Olivares / Natalia Gil (M. Simón) | O101: 45683 | P101: 45694 | S101: DazelMessage_233668256.xml FE23137011512470 CASTELLANO DazelMessage_233668262.xml FE23137011512470 CATALAN DazelMessage_233668266.xml FE23137011512470 EUSKERA DazelMessage_233668274.xml FE23137011512470 GALLEGO | T101: DazelMessage_233668256_ele.afp FE23137011512470 CASTELLANO DazelMessage_233668262_ele.afp FE23137011512470 CATALAN DazelMessage_233668266_ele.afp FE23137011512470 EUSKERA DazelMessage_233668274_ele.afp FE23137011512470 GALLEGO
A102: Proyecto Compositor Documental - CRGP | B102: Caso prueba | C102: Nueva | D102: Normal | E102: FAC_101 | F102: Factura que contenga Operaciones a Presentar de Gas. Idioma: CA, ES, EU, GA Domiciliada | G102: Facturación | H102: Proyecto Compositor Documental | I102: Factura que contenga OPs de Gas. | J102: 1. Se accede a la pantalla de Gestión de órdenes de cálculo, a través de Menú > Facturación > Proceso de cálculo, se introduce la OC de los datos de prueba y se pulsa Buscar. 2. Se selecciona la OC y se pulsa Calcular. 3. En la pantalla de Consulta de log se recupera el DC generado. 4. Se accede a la pantalla Consulta Documento de Cálculo, se introduce el DC y se pulsa Buscar. 5. Se pulsa sobre el hipervínculo del documento de cálculo para acceder al detalle. 6. Se accede a la pantalla de Facturación masiva de documentos de cálculo, a través de Menú > Facturación > Proceso de emisión, se introduce el cálculo de los datos de prueba y se pulsa Facturar. 7. En la pantalla de Consulta de log se recupera la factura generada. 8. Se accede a la pantalla de Gestión de Facturas, a través de Menú > Facturación > Proceso de Emisión, se introduce la factura de los datos de prueba y se pulsa Buscar. 9. Se pulsa sobre el hiperlink Nº Factura. 10. Se accede a la solapa Ver Doc. Impresión | K102: 1. Se recupera la OC. 2. El cálculo se realiza correctamente. 3. Se recupera correctamente el DC generado. 4. Se accede al detalle y se comprueba que el cálculo se ha generado correctamente: 5. La factura se recupera correctamente. 6. Se accede al detalle de la factura. 7. Se comprueba en el documento de impresión: - Se visualiza la factura en PDF, en el idioma del SE de la cuenta correctamente todos los apartados de la factura de gas | M102: Gas | N102: Toñi Olivares / Natalia Gil (M. Simón) | O102: 45683 | P102: 45694 | S102: DazelMessage_233648253.xml FE21137028558574 CASTELLANO DazelMessage_233648265.xml FE21137028558574 CATALAN DazelMessage_233648268.xml FE21137028558574 EUSKERA DazelMessage_233648278.xml FE21137028558574 GALLEGO | T102: DazelMessage_233648253.afp FE21137028558574 CASTELLANO DazelMessage_233648265.afp FE21137028558574 CATALAN DazelMessage_233648268.afp FE21137028558574 EUSKERA DazelMessage_233648278.afp FE21137028558574 GALLEGO
A103: Proyecto Compositor Documental - CRGP | B103: Caso prueba | C103: Nueva | D103: Normal | E103: FAC_102 | F103: Factura que contenga Operaciones a Presentar de Electricidad. Idioma: CA, ES, EU, GA Domiciliada | G103: Facturación | H103: Proyecto Compositor Documental | I103: Factura que contenga OPs de Electricidad. | J103: 1. Se accede a la pantalla de Gestión de órdenes de cálculo, a través de Menú > Facturación > Proceso de cálculo, se introduce la OC de los datos de prueba y se pulsa Buscar. 2. Se selecciona la OC y se pulsa Calcular. 3. En la pantalla de Consulta de log se recupera el DC generado. 4. Se accede a la pantalla Consulta Documento de Cálculo, se introduce el DC y se pulsa Buscar. 5. Se pulsa sobre el hipervínculo del documento de cálculo para acceder al detalle. 6. Se accede a la pantalla de Facturación masiva de documentos de cálculo, a través de Menú > Facturación > Proceso de emisión, se introduce el cálculo de los datos de prueba y se pulsa Facturar. 7. En la pantalla de Consulta de log se recupera la factura generada. 8. Se accede a la pantalla de Gestión de Facturas, a través de Menú > Facturación > Proceso de Emisión, se introduce la factura de los datos de prueba y se pulsa Buscar. 9. Se pulsa sobre el hiperlink Nº Factura. 10. Se accede a la solapa Ver Doc. Impresión | K103: 1. Se recupera la OC. 2. El cálculo se realiza correctamente. 3. Se recupera correctamente el DC generado. 4. Se accede al detalle y se comprueba que el cálculo se ha generado correctamente: 5. La factura se recupera correctamente. 6. Se accede al detalle de la factura. 7. Se comprueba en el documento de impresión: - Se visualiza la factura en PDF, en el idioma del SE de la cuenta correctamente todos los apartados de la factura de electricidad | M103: Electricidad | N103: Toñi Olivares / Natalia Gil (M. Simón) | O103: 45683 | P103: 45694 | S103: DazelMessage_233648257.xml FE25137019309628 CASTELLANO DazelMessage_233648263.xml FE25137019309628 CATALAN DazelMessage_233648267.xml FE25137019309628 EUSKERA DazelMessage_233648273.xml FE25137019309628 GALLEGO | T103: DazelMessage_233648257.afp FE25137019309628 CASTELLANO DazelMessage_233648263.afp FE25137019309628 CATALAN DazelMessage_233648267.afp FE25137019309628 EUSKERA DazelMessage_233648273.afp FE25137019309628 GALLEGO
R104: =(COUNTIF(R2:R103,"OK")/(COUNTBLANK(R2:R103)+(COUNTA(R2:R103)-(COUNTIF(R2:R103,"N/A"))))) -> 0 | S104: Porcentaje de Avance
R105: =COUNTBLANK(R2:R103)+(COUNTA(R2:R103)-(COUNTIF(R2:R103,"N/A"))-(COUNTIF(R2:R103,"OK"))-(COUNTIF(R2:R103,"KO"))) -> 102 | S105: Pendiente
R106: =COUNTIF(R2:R103,"KO") -> 0 | S106: KO
R107: =COUNTIF(R2:R103,"OK") -> 0 | S107: OK
R108: =COUNTBLANK(R2:R103)+(COUNTA(R2:R103)-(COUNTIF(R2:R103,"N/A"))) -> 102 | S108: Total

Sheet Cartas CRGP
A1: Proyecto | B1: Tipo | C1: Estado | D1: Prioridad | E1: Codigo de Prueba | F1: Asunto | G1: Módulos Delta | H1: Datos de prueba | I1: Técnica de pruebas | J1: Resultado esperado | K1: COMENTARIOS NEGOCIO | L1: Sector | M1: Responsable | N1: Fecha inicio | O1: Fecha Fin | P1: Fecha Liberado | Q1: Resultado OK/KO | R1: xml papyrus | S1: pdf papyrus
A2: Proyecto Compositor Documental - CRGP | B2: Caso prueba | C2: Nueva | D2: Normal | E2: COB_001 | F2: Generación carta C101_Carta 347 total - Declaración anual de operaciones con terceras personas | G2: Cobros | H2: Carta de la misma tipología e idioma generada con anterioridad. Idiomas: ES, CA, EU, GA | I2: Se localiza la última carta de esta tipología para cada idioma. Se actualiza el evento para volver a generarla con las fechas actuales. Se ejecutan los procesos procesadores de eventos: DECBD6101P, DECBD6102P, DECBD6103P, DECB6104P, DECBD6105P. Se ejecutan el proceso de generación de xml/envio a Dazel DECBD6199P. | J2: Se genera el xml de la carta. | K2: Revisión OK | L2: Elect/Gas | M2: Lola Lozano Sauras /Cristina Rincón (M. Simón) | N2: 45690 | O2: 45694 | R2: DazelMessage_234568252.xml | S2: C101.pdf
A3: Proyecto Compositor Documental - CRGP | B3: Caso prueba | C3: Nueva | D3: Normal | E3: COB_002 | F3: Generación carta C102_Carta 347 detalle - Declaración anual de operaciones con terceras personas | G3: Cobros | H3: Carta de la misma tipología e idioma generada con anterioridad. Idiomas: ES, CA, EU, GA | I3: Se localiza la última carta de esta tipología para cada idioma. Se actualiza el evento para volver a generarla con las fechas actuales. Se ejecutan los procesos procesadores de eventos: DECBD6101P, DECBD6102P, DECBD6103P, DECB6104P, DECBD6105P. Se ejecutan el proceso de generación de xml/envio a Dazel DECBD6199P. | J3: Se genera el xml de la carta. | K3: Revisión OK | L3: Elect/Gas | M3: Lola Lozano Sauras /Cristina Rincón (M. Simón) | N3: 45690 | O3: 45694 | R3: DazelMessage_233548252.xml | S3: C102.pdf
A4: Proyecto Compositor Documental - CRGP | B4: Caso prueba | C4: Nueva | D4: Normal | E4: COB_003 | F4: Generación carta C103_Carta auditores | G4: Cobros | H4: Carta de la misma tipología e idioma generada con anterioridad. Idiomas: ES, CA, EU, GA | I4: Se localiza la última carta de esta tipología para cada idioma. Se actualiza el evento para volver a generarla con las fechas actuales. Se ejecutan los procesos procesadores de eventos: DECBD6101P, DECBD6102P, DECBD6103P, DECB6104P, DECBD6105P. Se ejecutan el proceso de generación de xml/envio a Dazel DECBD6199P. | J4: Se genera el xml de la carta. | K4: Revisión OK | L4: Elect/Gas | M4: Lola Lozano Sauras /Cristina Rincón (M. Simón) | N4: 45690 | O4: 45694 | R4: DazelMessage_233548252.xml | S4: C103.pdf
A5: Proyecto Compositor Documental - CRGP | B5: Caso prueba | C5: Nueva | D5: Normal | E5: COB_004 | F5: Generación carta C104_Carta auditores saldo cero | G5: Cobros | H5: Carta de la misma tipología e idioma generada con anterioridad. Idiomas: ES, CA, EU, GA | I5: Se localiza la última carta de esta tipología para cada idioma. Se actualiza el evento para volver a generarla con las fechas actuales. Se ejecutan los procesos procesadores de eventos: DECBD6101P, DECBD6102P, DECBD6103P, DECB6104P, DECBD6105P. Se ejecutan el proceso de generación de xml/envio a Dazel DECBD6199P. | J5: Se genera el xml de la carta. | K5: Revisión OK | L5: Elect/Gas | M5: Lola Lozano Sauras /Cristina Rincón (M. Simón) | N5: 45690 | O5: 45694 | R5: DazelMessage_233548252.xml | S5: C104.pdf
A6: Proyecto Compositor Documental - CRGP | B6: Caso prueba | C6: Nueva | D6: Normal | E6: COB_005 | F6: Generación carta C105_Carta reconocimiento de deuda (Minorista) | G6: Cobros | H6: Carta de la misma tipología e idioma generada con anterioridad. Idiomas: ES, CA, EU, GA | I6: Se localiza la última carta de esta tipología para cada idioma. Se actualiza el evento para volver a generarla con las fechas actuales. Se ejecutan los procesos procesadores de eventos: DECBD6101P, DECBD6102P, DECBD6103P, DECB6104P, DECBD6105P. Se ejecutan el proceso de generación de xml/envio a Dazel DECBD6199P. | J6: Se genera el xml de la carta. | K6: Revisión OK | L6: Elect/Gas | M6: Lola Lozano Sauras /Cristina Rincón (M. Simón) | N6: 45690 | O6: 45694 | R6: DazelMessage_233548252.xml | S6: C105.pdf
A7: Proyecto Compositor Documental - CRGP | B7: Caso prueba | C7: Nueva | D7: Normal | E7: COB_006 | F7: Generación carta C107_Carta documento de pago | G7: Cobros | H7: Carta de la misma tipología e idioma generada con anterioridad. Idiomas: ES, CA, EU, GA | I7: Se localiza la última carta de esta tipología para cada idioma. Se actualiza el evento para volver a generarla con las fechas actuales. Se ejecutan los procesos procesadores de eventos: DECBD6101P, DECBD6102P, DECBD6103P, DECB6104P, DECBD6105P. Se ejecutan el proceso de generación de xml/envio a Dazel DECBD6199P. | J7: Se genera el xml de la carta. | K7: Revisión OK | L7: Elect/Gas | M7: Lola Lozano Sauras /Cristina Rincón (M. Simón) | N7: 45690 | O7: 45694 | R7: DazelMessage_234568252.xml | S7: C107.pdf
A8: Proyecto Compositor Documental - CRGP | B8: Caso prueba | C8: Nueva | D8: Normal | E8: COB_007 | F8: Generación carta C109_Carta recibo domiciliada | G8: Cobros | H8: Carta de la misma tipología e idioma generada con anterioridad. Idiomas: ES, CA, EU, GA | I8: Se localiza la última carta de esta tipología para cada idioma. Se actualiza el evento para volver a generarla con las fechas actuales. Se ejecutan los procesos procesadores de eventos: DECBD6101P, DECBD6102P, DECBD6103P, DECB6104P, DECBD6105P. Se ejecutan el proceso de generación de xml/envio a Dazel DECBD6199P. | J8: Se genera el xml de la carta. | K8: Revisión OK | L8: Elect/Gas | M8: Lola Lozano Sauras /Cristina Rincón (M. Simón) | N8: 45690 | O8: 45694 | R8: DazelMessage_234588253.xml | S8: C109.pdf
A9: Proyecto Compositor Documental - CRGP | B9: Caso prueba | C9: Nueva | D9: Normal | E9: COB_008 | F9: Generación carta C110_Carta recibo no domiciliado | G9: Cobros | H9: Carta de la misma tipología e idioma generada con anterioridad. Idiomas: ES, CA, EU, GA | I9: Se localiza la última carta de esta tipología para cada idioma. Se actualiza el evento para volver a generarla con las fechas actuales. Se ejecutan los procesos procesadores de eventos: DECBD6101P, DECBD6102P, DECBD6103P, DECB6104P, DECBD6105P. Se ejecutan el proceso de generación de xml/envio a Dazel DECBD6199P. | J9: Se genera el xml de la carta. | K9: Revisión OK | L9: Elect/Gas | M9: Lola Lozano Sauras /Cristina Rincón (M. Simón) | N9: 45690 | O9: 45694 | R9: DazelMessage_234588253.xml | S9: C110.pdf
A10: Proyecto Compositor Documental - CRGP | B10: Caso prueba | C10: Nueva | D10: Normal | E10: COB_009 | F10: Generación carta C111_Carta recibo AAPP y clientes grupo | G10: Cobros | H10: Carta de la misma tipología e idioma generada con anterioridad. Idiomas: ES, CA, EU, GA | I10: Se localiza la última carta de esta tipología para cada idioma. Se actualiza el evento para volver a generarla con las fechas actuales. Se ejecutan los procesos procesadores de eventos: DECBD6101P, DECBD6102P, DECBD6103P, DECB6104P, DECBD6105P. Se ejecutan el proceso de generación de xml/envio a Dazel DECBD6199P. | J10: Se genera el xml de la carta. | K10: Revisión OK | L10: Elect/Gas | M10: Lola Lozano Sauras /Cristina Rincón (M. Simón) | N10: 45690 | O10: 45694 | R10: DazelMessage_234588253.xml | S10: C111.pdf
A11: Proyecto Compositor Documental - CRGP | B11: Caso prueba | C11: Nueva | D11: Normal | E11: COB_010 | F11: Generación carta C112_Carta justificante de cobro | G11: Cobros | H11: Carta de la misma tipología e idioma generada con anterioridad. Idiomas: ES, CA, EU, GA | I11: Se localiza la última carta de esta tipología para cada idioma. Se actualiza el evento para volver a generarla con las fechas actuales. Se ejecutan los procesos procesadores de eventos: DECBD6101P, DECBD6102P, DECBD6103P, DECB6104P, DECBD6105P. Se ejecutan el proceso de generación de xml/envio a Dazel DECBD6199P. | J11: Se genera el xml de la carta. | K11: Revisión OK | L11: Elect/Gas | M11: Lola Lozano Sauras /Cristina Rincón (M. Simón) | N11: 45690 | O11: 45694 | R11: DazelMessage_233548253.xml | S11: C112.pdf
A12: Proyecto Compositor Documental - CRGP | B12: Caso prueba | C12: Nueva | D12: Normal | E12: COB_011 | F12: Generación carta C113_Carta devolución tarjeta | G12: Cobros | H12: Carta de la misma tipología e idioma generada con anterioridad. Idiomas: ES, CA, EU, GA | I12: Se localiza la última carta de esta tipología para cada idioma. Se actualiza el evento para volver a generarla con las fechas actuales. Se ejecutan los procesos procesadores de eventos: DECBD6101P, DECBD6102P, DECBD6103P, DECB6104P, DECBD6105P. Se ejecutan el proceso de generación de xml/envio a Dazel DECBD6199P. | J12: Se genera el xml de la carta. | K12: Revisión OK | L12: Elect/Gas | M12: Lola Lozano Sauras /Cristina Rincón (M. Simón) | N12: 45690 | O12: 45694 | R12: DazelMessage_234568252.xml | S12: C113.pdf
A13: Proyecto Compositor Documental - CRGP | B13: Caso prueba | C13: Nueva | D13: Normal | E13: COB_012 | F13: Generación carta C114_Carta devolución domiciliada | G13: Cobros | H13: Carta de la misma tipología e idioma generada con anterioridad. Idiomas: ES, CA, EU, GA | I13: Se localiza la última carta de esta tipología para cada idioma. Se actualiza el evento para volver a generarla con las fechas actuales. Se ejecutan los procesos procesadores de eventos: DECBD6101P, DECBD6102P, DECBD6103P, DECB6104P, DECBD6105P. Se ejecutan el proceso de generación de xml/envio a Dazel DECBD6199P. | J13: Se genera el xml de la carta. | K13: Revisión OK | L13: Elect/Gas | M13: Lola Lozano Sauras /Cristina Rincón (M. Simón) | N13: 45690 | O13: 45694 | R13: DazelMessage_234568252.xml | S13: C114.pdf
... A37: Proyecto Compositor Documental - CRGP | B37: Caso prueba | C37: Nueva | D37: Normal | E37: CYV_014 | F37: Generación Carta_A046 Carta de Subrogación de Contrato | G37: Contratación | H37: Cliente con contrato activo Idioma: CA, ES, EU, GA | I37: *Realizar cambio de titular en un contrato activo sobre otro cliente *Al terminar el proceso se ha de ejecutar el batch D5ATD075P | J37: Se generará el xml A046 Carta de Subrogación de Contrato | K37: Revisión OK | L37: Electricidad | M37: Lola Lozano Sauras /Cristina Rincón (M. Simón) | N37: 45690 | O37: 45694 | R37: A046_E.xml A046_C.xml A046_K.xml A046_G.xml | S37: A046_E.afp.pdf A046_C.afp.pdf A046_K.afp.pdf A046_G.afp.pdf
Q38: =(COUNTIF(Q2:Q37,"OK")/(COUNTBLANK(Q2:Q37)+(COUNTA(Q2:Q37)-(COUNTIF(Q2:Q37,"N/A"))))) -> 0 | R38: Porcentaje de Avance
Q39: =COUNTBLANK(Q2:Q37)+(COUNTA(Q2:Q37)-(COUNTIF(Q2:Q37,"N/A"))-(COUNTIF(Q2:Q37,"OK"))-(COUNTIF(Q2:Q37,"KO"))) -> 36 | R39: Pendiente
Q40: =COUNTIF(Q2:Q37,"KO") -> 0 | R40: KO
Q41: =COUNTIF(Q2:Q37,"OK") -> 0 | R41: OK
Q42: =COUNTBLANK(Q2:Q37)+(COUNTA(Q2:Q37)-(COUNTIF(Q2:Q37,"N/A"))) -> 36 | R42: Total

Sheet Contratos CRGP
A1: Proyecto | B1: Tipo | C1: Estado | D1: Prioridad | E1: Codigo de Prueba | F1: Asunto | G1: Módulos Delta | H1: Datos de prueba | I1: Técnica de pruebas | J1: Resultado esperado | K1: COMENTARIOS NEGOCIO | L1: Sector | M1: Responsable | N1: Fecha inicio | O1: Fecha Fin | P1: Fecha Liberado | Q1: Resultado OK/KO | R1: xml papyrus | S1: pdf papyrus
A2: Proyecto Compositor Documental - CRGP | B2: Caso prueba | C2: Nueva | D2: Normal | E2: CYV_001 | F2: Generación Carta_G013 Alta contrato PVPC 2.0TD | G2: Contratación | H2: Nuevo contrato sobre cliente existente sin contrato activo en el suministro Idioma: CA, ES, EU, GA | I2: *Dar de alta un contrato eléctrico a través de la posición de cliente. * Seleccionar la ubicación y crear oferta * Rellenar los datos de producto, potencias, formas de pago a través de la LO * Validar oferta quedando esta en curso. * Se ha de ejecutar el batch de impresión de contratos | J2: Se generará el xml Carta_G013 Alta contrato PVPC 2.0TD | K2: Revisión OK | L2: Electricidad | M2: Javier Alvarez | N2: 45690 | O2: 45694 | R2: G13 1_C.xml G13 1_E.xml G13 1_G.xml G13 1_K.xml | S2: G13 1_C.afp.pdf G13 1_E.afp.pdf G13 1_G.afp.pdf G13 1_K.afp.pdf
A3: Proyecto Compositor Documental - CRGP | B3: Caso prueba | C3: Nueva | D3: Normal | E3: CYV_002 | F3: Generación Carta_G311 G341 Alta contrato Gas | G3: Contratación | H3: Nuevo contrato sobre cliente existente sin contrato activo en el suministro Idioma: CA, ES, EU, GA | I3: *Dar de alta un contrato gas a través de la posición de cliente. * Seleccionar la ubicación y crear oferta * Rellenar los datos de producto,caudal, formas de pago a través de la LO * Validar oferta quedando esta en curso. * Se ha de ejecutar el batch de impresión de contratos | J3: Se generará el xml Carta_G311 G341 Alta contrato Gas | K3: Revisión OK | L3: Gas | M3: Javier Alvarez | N3: 45690 | O3: 45694 | R3: G311 G341_C.xml G311 G341_E.xml G311 G341_K.xml G311 G341_G.xml | S3: G311 G341_C.afp.pdf G311 G341_E.afp.pdf G311 G341_K.afp.pdf G311 G341_G.afp.pdf
A4: Proyecto Compositor Documental - CRGP | B4: Caso prueba | C4: Nueva | D4: Normal | E4: CYV_003 | F4: Generación Carta_G311 G342 Solicitud copia de contrato | G4: Contratación | H4: Cliente con contrato activo en un producto de gas Idioma: CA, ES, EU, GA | I4: *Seleccionar en las opciones de lo "duplicado de contrato" * Seleccionar copia de impresión y aceptar * Se ha de ejecutar el batch de impresión de contratos | J4: Se generará el xml Carta_G311 G342 Solicitud copia de contrato | K4: Revisión OK | L4: Gas | M4: Javier Alvarez | N4: 45690 | O4: 45694 | R4: G311 G342_C.xml G311 G342_E.xml G311 G342_K.xml G311 G342_G.xml | S4: G311 G342_C.afp.pdf G311 G342_E.afp.pdf G311 G342_K.afp.pdf G311 G342_G.afp.pdf
A5: Proyecto Compositor Documental - CRGP | B5: Caso prueba | C5: Nueva | D5: Normal | E5: CYV_004 | F5: Generación Carta_G311 G343 Contrato tras CT | G5: Contratación | H5: Nuevo contrato sobre cliente existente sin contrato activo en el suministro Idioma: CA, ES, EU, GA | I5: *Realizar cambio de titular en un contrato activo sobre otro cliente *Al terminar el proceso se ha de ejecutar el batch de impresión para generar la carta | J5: Se generará el xml Carta_G311 G343 Contrato tras CT | K5: Revisión OK | L5: Gas | M5: Javier Alvarez | N5: 45690 | O5: 45694 | R5: G311 G343_C.xml G311 G343_E.xml G311 G343_K.xml G311 G343_G.xml | S5: G311 G343_C.afp.pdf G311 G343_E.afp.pdf G311 G343_K.afp.pdf G311 G343_G.afp.pdf
A6: Proyecto Compositor Documental - CRGP | B6: Caso prueba | C6: Nueva | D6: Normal | E6: CYV_005 | F6: Generación Carta_G311 G344 Contrato tras cambio tarifa | G6: Contratación | H6: Nuevo contrato sobre cliente existente sin contrato activo en el suministro Idioma: CA, ES, EU, GA | I6: *Seleccionar un contrato con tarifa gas activa *En las opciones de la Lo solicitamos un cambio de producto *Al validar la oferta se creará la solicitud de impresión *Se ha de ejecutar el batch de impresión de contratos | J6: Se generará el xml Carta_G311 G344 Contrato tras cambio tarifa | K6: Revisión OK | L6: Gas | M6: Javier Alvarez | N6: 45690 | O6: 45694 | R6: G311 G344_C.xml G311 G344_E.xml G311 G344_K.xml G311 G344_G.xml | S6: G311 G344_C.afp.pdf G311 G344_E.afp.pdf G311 G344_K.afp.pdf G311 G344_G.afp.pdf
Q7: =(COUNTIF(Q2:Q6,"OK")/(COUNTBLANK(Q2:Q6)+(COUNTA(Q2:Q6)-(COUNTIF(Q2:Q6,"N/A"))))) -> 0 | R7: Porcentaje de Avance
Q8: =COUNTBLANK(Q2:Q6)+(COUNTA(Q2:Q6)-(COUNTIF(Q2:Q6,"N/A"))-(COUNTIF(Q2:Q6,"OK"))-(COUNTIF(Q2:Q6,"KO"))) -> 5 | R8: Pendiente
Q9: =COUNTIF(Q2:Q6,"KO") -> 0 | R9: KO
Q10: =COUNTIF(Q2:Q6,"OK") -> 0 | R10: OK
Q11: =COUNTBLANK(Q2:Q6)+(COUNTA(Q2:Q6)-(COUNTIF(Q2:Q6,"N/A"))) -> 5 | R11: Total

Sheet MEGA
A1: E380 - 00000 - Validar Impresión Facturas SERVINFORM / Versión 2023/12
AB2: Pruebas integradas
A3: Sistema / Aplicación | B3: PdP | C3: Nombre Versión | D3: Version | E3: Entidad Asociada | F3: COD Entidad Asociada | G3: Tipo PdP | H3: Equipo Asociado | I3: Módulo | J3: Proceso | K3: Subproceso | L3: Funcionalidad | M3: Código CdP | N3: Nombre CdP | O3: Resumen | P3: Precondiciones | Q3: Juego de datos | R3: Tipo de Ejecución | S3: Criticidad | T3: Autor | U3: Datos del CdP Papyrus | V3: Datos del CdP Servinform | W3: Tipo de CdP | X3: Estado CdP | Y3: Código de Carga | Z3: Tiempo de Diseño (mins) | AA3: Tiempo de Ejecución Estimado (mins) | AB3: Objeto / Componente | AC3: Sistema Origen | AD3: Resultado Esperado Origen | AE3: Sistema Destino | AF3: Resultado Esperado Destino | AG3: Comentarios Negocio | AH3: Responsable | AI3: Fecha inicio | AJ3: Fecha Fin | AK3: Fecha liberado | AL3: Resultado OK/KO
A4: MEGA | B4: 00000 - Validar Impresión Facturas SERVINFORM | C4: v9.25 | D4: 2023/12 | E4: Mantenimiento Evolutivo | F4: 1044365 | G4: Funcional / Certificación | H4: MEGA | I4: Facturación | J4: Facturación | K4: Impresión de facturas | L4: SERVINFORM | M4: MEG-2618 | N4: Envío Impresión Certificaciones | O4: Envío Impresión Certificaciones | P4: 1 idioma | R4: Manual | S4: Media | T4: 90018116 | W4: Funcional | X4: TERMINADO | Z4: 3 | AA4: 3 | AG4: Revisión OK | AH4: Lorena Bernuz /Kiko | AI4: 46378 | AJ4: 46382 | AK4: pendiente
A5: MEGA | B5: 00000 - Validar Impresión Facturas SERVINFORM | C5: v9.25 | D5: 2023/12 | E5: Mantenimiento Evolutivo | F5: 1044365 | G5: Funcional / Certificación | H5: MEGA | I5: Facturación | J5: Facturación | K5: Impresión de facturas | L5: SERVINFORM | M5: MEG-2616 | N5: Envío Impresión Facturas | O5: Envío Impresión Facturas | P5: 2 idiomas | R5: Manual | S5: Media | T5: 90018116 | W5: Funcional | X5: TERMINADO | Z5: 3 | AA5: 3 | AG5: Revisión OK | AH5: Lorena Bernuz /Kiko | AI5: 46371 | AJ5: 46382 | AL5: N/A
A6: MEGA | B6: 00000 - Validar Impresión Facturas SERVINFORM | C6: v9.25 | D6: 2023/12 | E6: Mantenimiento Evolutivo | F6: 1044365 | G6: Funcional / Certificación | H6: MEGA | I6: Facturación | J6: Facturación | K6: Impresión de facturas | L6: SERVINFORM | M6: MEG-2617 | N6: Envío Impresión Cartas | O6: Envío Impresión Cartas | P6: 2 idiomas | R6: Manual | S6: Media | T6: 90018116 | W6: Funcional | X6: TERMINADO | Z6: 3 | AA6: 3 | AG6: Revisión OK | AH6: Lorena Bernuz /Kiko | AI6: 46378 | AJ6: 46382 | AK6: pendiente
A7: MEGA | B7: 00000 - Validar Impresión Facturas SERVINFORM | C7: v9.25 | D7: 2023/12 | E7: Mantenimiento Evolutivo | F7: 1044365 | G7: Funcional / Certificación | H7: MEGA | I7: Facturación | J7: Facturación | K7: Impresión de facturas | L7: SERVINFORM | M7: MEG-2617 | N7: Envío Impresión Cartas | O7: Envío Impresión Cartas | P7: Catalan | S7: Funcional | T7: TERMINADO | W7: Funcional | AG7: Revisión OK | AH7: Lorena Bernuz /Kiko | AI7: 46378 | AJ7: 46382 | AK7: pendiente
A8: MEGA | B8: 00000 - Validar Impresión Facturas SERVINFORM | C8: v9.25 | D8: 2023/12 | E8: Mantenimiento Evolutivo | F8: 1044365 | G8: Funcional / Certificación | H8: MEGA | I8: Facturación | J8: Facturación | K8: Impresión de facturas | L8: SERVINFORM | M8: MEG-2617 | N8: Envío Impresión Cartas | O8: Envío Impresión Cartas | P8: Portugues | S8: Funcional | T8: TERMINADO | W8: Funcional | AG8: Revisión OK | AH8: Lorena Bernuz /Kiko | AI8: 46378 | AJ8: 46382 | AK8: pendiente
A9: MEGA | B9: 00000 - Validar Impresión Facturas SERVINFORM | C9: v9.25 | D9: 2023/12 | E9: Mantenimiento Evolutivo | F9: 1044365 | G9: Funcional / Certificación | H9: MEGA | I9: Facturación | J9: Facturación | K9: Impresión de facturas | L9: SERVINFORM | M9: MEG-2619 | N9: Impresión Facturas - Fichero Respuestas | O9: Impresión Facturas - Fichero Respuestas | P9: 2 idiomas | R9: Manual | S9: Media | T9: 90018116 | W9: Funcional | X9: TERMINADO | Z9: 3 | AA9: 3 | AG9: Revisión OK | AH9: Lorena Bernuz /Kiko | AI9: 46371 | AJ9: 46382 | AL9: N/A
A10: MEGA | B10: 00000 - Validar Impresión Facturas SERVINFORM | C10: v9.25 | D10: 2023/12 | E10: Mantenimiento Evolutivo | F10: 1044365 | G10: Funcional / Certificación | H10: MEGA | I10: Facturación | J10: Facturación | K10: Impresión de facturas | L10: SERVINFORM | M10: MEG-2620 | N10: Impresión Cartas - Fichero Respuestas | O10: Impresión Facturas - Fichero Respuestas | P10: 2 idiomas | R10: Manual | S10: Media | T10: 90018116 | W10: Funcional | X10: TERMINADO | Z10: 3 | AA10: 3 | AG10: Revisión OK | AH10: Lorena Bernuz /Kiko | AI10: 46378 | AJ10: 46382 | AL10: N/A
A11: MEGA | B11: 00000 - Validar Impresión Facturas SERVINFORM | C11: v9.25 | D11: 2023/12 | E11: Mantenimiento Evolutivo | F11: 1044365 | G11: Funcional / Certificación | H11: MEGA | I11: Facturación | J11: Facturación | K11: Impresión de facturas | L11: SERVINFORM | M11: MEG-2621 | N11: Impresión Certificaciones - Fichero Respuestas | O11: Impresión Certificaciones - Fichero Respuestas | P11: 2 idiomas | R11: Manual | S11: Media | T11: 90018116 | W11: Funcional | X11: TERMINADO | Z11: 3 | AA11: 3 | AG11: Revisión OK | AH11: Lorena Bernuz /Kiko | AI11: 46378 | AJ11: 46382 | AL11: N/A
A12: MEGA | B12: 00000 - Validar Impresión Facturas SERVINFORM | C12: v9.25 | D12: 2023/12 | E12: Mantenimiento Evolutivo | F12: 1044365 | G12: Funcional / Certificación | H12: MEGA | I12: Facturación | J12: Facturación | K12: Impresión de facturas | L12: SERVINFORM | M12: MEG-2622 | N12: Impresión Factura - Parámetros circuito | O12: Se valida que la sección continen un identificador de envío único. | P12: 2 idiomas | R12: Manual | S12: Media | T12: 90018116 | W12: Funcional | X12: TERMINADO | Z12: 3 | AA12: 3 | AG12: Revisión OK | AH12: Lorena Bernuz /Kiko | AI12: 46371 | AJ12: 46382 | AL12: N/A
A13: MEGA | B13: 00000 - Validar Impresión Facturas SERVINFORM | C13: v9.25 | D13: 2023/12 | E13: Mantenimiento Evolutivo | F13: 1044365 | G13: Funcional / Certificación | H13: MEGA | I13: Facturación | J13: Facturación | K13: Impresión de facturas | L13: SERVINFORM | M13: MEG-2624 | N13: Impresión Factura - Datos Documento | O13: Se valida que el formato de los apartados: Datos de factura: Fechas, Número de documento, contrato, etc. Dirección correspondencia, Razón social, Punto de suministro | P13: Castellano | R13: Manual | S13: Media | T13: 90018116 | U13: CASTELLANO solfac A 00004444 2025FA00012807.pdf solfac B 00004484 2025FA00012808.pdf solfac C 90023950 2025FA00012831.pdf solfac D 90031924 2025FA00012643.pdf solfac E 90032372 2025FA00012874.pdf solfac F 90033198 2025FA00012891.pdf solfac G 90043847 2023FA00008653.pdf solfac H 90043855 2025FA00020476.pdf | V13: CASTELLANO: 2025FA00012807_25121516511616.pdf 2025FA00012808_25121516512222.pdf 2025FA00012831_25121516512828.pdf 2025FA00012643_25121516511010.pdf 2025FA00012874_25121516513434.pdf 2025FA00012891_25121516514141.pdf 2023FA00008653_25121516510303.pdf 202500020476_25121516544444.pdf | W13: Funcional | X13: TERMINADO | Z13: 3 | AA13: 3 | AG13: Revisión OK | AH13: Lorena Bernuz /Kiko | AI13: 46006 | AJ13: 46017 | AK13: 46008 | AL13: KO
A14: MEGA | B14: 00000 - Validar Impresión Facturas SERVINFORM | C14: v9.25 | D14: 2023/12 | E14: Mantenimiento Evolutivo | F14: 1044365 | G14: Funcional / Certificación | H14: MEGA | I14: Facturación | J14: Facturación | K14: Impresión de facturas | L14: SERVINFORM | M14: MEG-2624 | N14: Impresión Factura - Datos Documento | O14: Se valida que el formato de los apartados: Datos de factura: Fechas, Número de documento, contrato, etc. Dirección correspondencia, Razón social, Punto de suministro | P14: Catalan | S14: Funcional | T14: TERMINADO | U14: impresionNuevaFactura_C_00004444_2025FA00012807_1535227_20251205_141008.afp impresionNuevaFactura_C_00004484_2025FA00012808_1535228_20251205_141010.afp impresionNuevaFactura_C_90023950_2025FA00012831_1535284_20251205_141011.afp impresionNuevaFactura_C_90031924_2025FA00012643_1532880_20251205_141005.afp impresionNuevaFactura_C_90032372_2025FA00012874_1535413_20251205_141014.afp impresionNuevaFactura_C_90033198_2025FA00012891_1535433_20251205_141017.afp impresionNuevaFactura_C_90043847_2023FA00008653_1309170_20251205_141003.afp impresionNuevaFactura_C_90043855_202500020476_1537214_20251210_152232.afp | W14: Funcional | AG14: Revisión OK | AH14: Lorena Bernuz /Kiko | AI14: 46006 | AJ14: 46017 | AK14: 46385
A15: MEGA | B15: 00000 - Validar Impresión Facturas SERVINFORM | C15: v9.25 | D15: 2023/12 | E15: Mantenimiento Evolutivo | F15: 1044365 | G15: Funcional / Certificación | H15: MEGA | I15: Facturación | J15: Facturación | K15: Impresión de facturas | L15: SERVINFORM | M15: MEG-2624 | N15: Impresión Factura - Datos Documento | O15: Se valida que el formato de los apartados: Datos de factura: Fechas, Número de documento, contrato, etc. Dirección correspondencia, Razón social, Punto de suministro | P15: Portugues | S15: Funcional | T15: TERMINADO | W15: Funcional | AG15: Revisión OK | AH15: Lorena Bernuz /Kiko | AI15: 46006 | AJ15: 46017 | AK15: 46385
A16: MEGA | B16: 00000 - Validar Impresión Facturas SERVINFORM | C16: v9.25 | D16: 2023/12 | E16: Mantenimiento Evolutivo | F16: 1044365 | G16: Funcional / Certificación | H16: MEGA | I16: Facturación | J16: Facturación | K16: Impresión de facturas | L16: SERVINFORM | M16: MEG-2625 | N16: Impresión Factura - Conceptos Facturación - Categoría única | O16: Se valida que el formato del apartado Conceptos Facturación | P16: Castellano | R16: Manual | S16: Media | T16: 90018116 | U16: CASTELLANO solfac B 00004484 2025FA00012808.pdf solfac C 90023950 2025FA00012831.pdf solfac D 90031924 2025FA00012643.pdf solfac H 90043855 2025FA00020476.pdf | V16: CASTELLANO: 2025FA00012808_25121516512222.pdf 2025FA00012831_25121516512828.pdf 2025FA00012643_25121516511010.pdf 202500020476_25121516544444.pdf | W16: Funcional | X16: TERMINADO | Z16: 3 | AA16: 3 | AG16: Revisión OK | AH16: Lorena Bernuz /Kiko | AI16: 46006 | AJ16: 46017 | AK16: 46008 | AL16: OK
A17: MEGA | B17: 00000 - Validar Impresión Facturas SERVINFORM | C17: v9.25 | D17: 2023/12 | E17: Mantenimiento Evolutivo | F17: 1044365 | G17: Funcional / Certificación | H17: MEGA | I17: Facturación | J17: Facturación | K17: Impresión de facturas | L17: SERVINFORM | M17: MEG-2625 | N17: Impresión Factura - Conceptos Facturación - Categoría única | O17: Se valida que el formato del apartado Conceptos Facturación | P17: Catalan | S17: Funcional | T17: TERMINADO | U17: impresionNuevaFactura_C_00004484_2025FA00012808_1535228_20251205_141010.afp impresionNuevaFactura_C_90023950_2025FA00012831_1535284_20251205_141011.afp impresionNuevaFactura_C_90031924_2025FA00012643_1532880_20251205_141005.afp impresionNuevaFactura_C_90043855_202500020476_1537214_20251210_152232.afp | W17: Funcional | AG17: Revisión OK | AH17: Lorena Bernuz /Kiko | AI17: 46006 | AJ17: 46017 | AK17: 46385
A18: MEGA | B18: 00000 - Validar Impresión Facturas SERVINFORM | C18: v9.25 | D18: 2023/12 | E18: Mantenimiento Evolutivo | F18: 1044365 | G18: Funcional / Certificación | H18: MEGA | I18: Facturación | J18: Facturación | K18: Impresión de facturas | L18: SERVINFORM | M18: MEG-2625 | N18: Impresión Factura - Conceptos Facturación - Categoría única | O18: Se valida que el formato del apartado Conceptos Facturación | P18: Portugues | S18: Funcional | T18: TERMINADO | W18: Funcional | AG18: Revisión OK | AH18: Lorena Bernuz /Kiko | AI18: 46006 | AJ18: 46017 | AK18: 46385
A19: MEGA | B19: 00000 - Validar Impresión Facturas SERVINFORM | C19: v9.25 | D19: 2023/12 | E19: Mantenimiento Evolutivo | F19: 1044365 | G19: Funcional / Certificación | H19: MEGA | I19: Facturación | J19: Facturación | K19: Impresión de facturas | L19: SERVINFORM | M19: MEG-2626 | N19: Impresión Factura - Conceptos Facturación - Categoría única + Lista promociones | O19: Se valida que el formato del apartado Conceptos Facturación | P19: Castellano | R19: Manual | S19: Media | T19: 90018116 | U19: CASTELLANO solfac A 00004444 2025FA00012807.pdf solfac F 90033198 2025FA00012891.pdf | V19: CASTELLANO: 2025FA00012807_25121516511616.pdf 2025FA00012891_25121516514141.pdf | W19: Funcional | X19: TERMINADO | Z19: 3 | AA19: 3 | AG19: Revisión OK | AH19: Lorena Bernuz /Kiko | AI19: 46006 | AJ19: 46017 | AK19: 46008 | AL19: OK
A20: MEGA | B20: 00000 - Validar Impresión Facturas SERVINFORM | C20: v9.25 | D20: 2023/12 | E20: Mantenimiento Evolutivo | F20: 1044365 | G20: Funcional / Certificación | H20: MEGA | I20: Facturación | J20: Facturación | K20: Impresión de facturas | L20: SERVINFORM | M20: MEG-2626 | N20: Impresión Factura - Conceptos Facturación - Categoría única + Lista promociones | O20: Se valida que el formato del apartado Conceptos Facturación | P20: Catalan | S20: Funcional | T20: TERMINADO | U20: impresionNuevaFactura_C_00004444_2025FA00012807_1535227_20251205_141008.afp impresionNuevaFactura_C_90033198_2025FA00012891_1535433_20251205_141017.afp | AG20: Revisión OK | AH20: Lorena Bernuz /Kiko | AI20: 46006 | AJ20: 46017 | AK20: 46385
A21: MEGA | B21: 00000 - Validar Impresión Facturas SERVINFORM | C21: v9.25 | D21: 2023/12 | E21: Mantenimiento Evolutivo | F21: 1044365 | G21: Funcional / Certificación | H21: MEGA | I21: Facturación | J21: Facturación | K21: Impresión de facturas | L21: SERVINFORM | M21: MEG-2626 | N21: Impresión Factura - Conceptos Facturación - Categoría única + Lista promociones | O21: Se valida que el formato del apartado Conceptos Facturación | P21: Portugues | S21: Funcional | T21: TERMINADO | AG21: Revisión OK | AH21: Lorena Bernuz /Kiko | AI21: 46006 | AJ21: 46017 | AK21: 46385
A22: MEGA | B22: 00000 - Validar Impresión Facturas SERVINFORM | C22: v9.25 | D22: 2023/12 | E22: Mantenimiento Evolutivo | F22: 1044365 | G22: Funcional / Certificación | H22: MEGA | I22: Facturación | J22: Facturación | K22: Impresión de facturas | L22: SERVINFORM | M22: MEG-2627 | N22: Impresión Factura - Conceptos Facturación - Varias Categorías | O22: Se valida que el formato del apartado Conceptos Facturación | P22: Castellano | R22: Manual | S22: Media | T22: 90018116 | U22: CASTELLANO solfac E 90032372 2025FA00012874.pdf solfac F 90033198 2025FA00012891.pdf | V22: CASTELLANO: 2025FA00012874_25121516513434.pdf 2025FA00012891_25121516514141.pdf | W22: Funcional | X22: TERMINADO | Z22: 3 | AA22: 3 | AG22: Revisión OK | AH22: Lorena Bernuz /Kiko | AI22: 46006 | AJ22: 46017 | AK22: 46008 | AL22: OK
A23: MEGA | B23: 00000 - Validar Impresión Facturas SERVINFORM | C23: v9.25 | D23: 2023/12 | E23: Mantenimiento Evolutivo | F23: 1044365 | G23: Funcional / Certificación | H23: MEGA | I23: Facturación | J23: Facturación | K23: Impresión de facturas | L23: SERVINFORM | M23: MEG-2627 | N23: Impresión Factura - Conceptos Facturación - Varias Categorías | O23: Se valida que el formato del apartado Conceptos Facturación | P23: Catalan | S23: Funcional | T23: TERMINADO | U23: impresionNuevaFactura_C_90032372_2025FA00012874_1535413_20251205_141014.afp impresionNuevaFactura_C_90033198_2025FA00012891_1535433_20251205_141017.afp | AG23: Revisión OK | AH23: Lorena Bernuz /Kiko | AI23: 46006 | AJ23: 46017 | AK23: 46385
A24: MEGA | B24: 00000 - Validar Impresión Facturas SERVINFORM | C24: v9.25 | D24: 2023/12 | E24: Mantenimiento Evolutivo | F24: 1044365 | G24: Funcional / Certificación | H24: MEGA | I24: Facturación | J24: Facturación | K24: Impresión de facturas | L24: SERVINFORM | M24: MEG-2627 | N24: Impresión Factura - Conceptos Facturación - Varias Categorías | O24: Se valida que el formato del apartado Conceptos Facturación | P24: Portugues | S24: Funcional | T24: TERMINADO | AG24: Revisión OK | AH24: Lorena Bernuz /Kiko | AI24: 46006 | AJ24: 46017 | AK24: 46385
A25: MEGA | B25: 00000 - Validar Impresión Facturas SERVINFORM | C25: v9.25 | D25: 2023/12 | E25: Mantenimiento Evolutivo | F25: 1044365 | G25: Funcional / Certificación | H25: MEGA | I25: Facturación | J25: Facturación | K25: Impresión de facturas | L25: SERVINFORM | M25: MEG-2628 | N25: Impresión Factura - Notas Conceptos Facturación | O25: Se valida que el formato del apartado Notas Conceptos Facturación | P25: Castellano | R25: Manual | S25: Media | T25: 90018116 | U25: CASTELLANO solfac G 90043847 2023FA00008653.pdf | V25: CASTELLANO: 2023FA00008653_25121516510303.pdf | W25: Funcional | X25: TERMINADO | Z25: 3 | AA25: 3 | AG25: Revisión OK | AH25: Lorena Bernuz /Kiko | AI25: 46006 | AJ25: 46017 | AK25: 46008 | AL25: OK
A26: MEGA | B26: 00000 - Validar Impresión Facturas SERVINFORM | C26: v9.25 | D26: 2023/12 | E26: Mantenimiento Evolutivo | F26: 1044365 | G26: Funcional / Certificación | H26: MEGA | I26: Facturación | J26: Facturación | K26: Impresión de facturas | L26: SERVINFORM | M26: MEG-2628 | N26: Impresión Factura - Notas Conceptos Facturación | O26: Se valida que el formato del apartado Notas Conceptos Facturación | P26: Catalan | S26: Funcional | T26: TERMINADO | U26: impresionNuevaFactura_C_90043847_2023FA00008653_1309170_20251205_141003.afp | AG26: Revisión OK | AH26: Lorena Bernuz /Kiko | AI26: 46006 | AJ26: 46017 | AK26: 46385
A27: MEGA | B27: 00000 - Validar Impresión Facturas SERVINFORM | C27: v9.25 | D27: 2023/12 | E27: Mantenimiento Evolutivo | F27: 1044365 | G27: Funcional / Certificación | H27: MEGA | I27: Facturación | J27: Facturación | K27: Impresión de facturas | L27: SERVINFORM | M27: MEG-2628 | N27: Impresión Factura - Notas Conceptos Facturación | O27: Se valida que el formato del apartado Notas Conceptos Facturación | P27: Portugues | S27: Funcional | T27: TERMINADO | AG27: Revisión OK | AH27: Lorena Bernuz /Kiko | AI27: 46006 | AJ27: 46017 | AK27: 46385
A28: MEGA | B28: 00000 - Validar Impresión Facturas SERVINFORM | C28: v9.25 | D28: 2023/12 | E28: Mantenimiento Evolutivo | F28: 1044365 | G28: Funcional / Certificación | H28: MEGA | I28: Facturación | J28: Facturación | K28: Impresión de facturas | L28: SERVINFORM | M28: MEG-2630 | N28: Impresión Factura - Datos planes de pago | O28: Se valida que el formato del apartado Datos planes de pago | P28: Castellano | R28: Manual | S28: Media | T28: 90018116 | U28: CASTELLANO solfac A 00004444 2025FA00012807.pdf | V28: CASTELLANO: 2025FA00012807_25121516511616.pdf | W28: Funcional | X28: TERMINADO | Z28: 3 | AA28: 3 | AG28: Revisión OK | AH28: Lorena Bernuz /Kiko | AI28: 46006 | AJ28: 46017 | AK28: 46008 | AL28: KO
A29: MEGA | B29: 00000 - Validar Impresión Facturas SERVINFORM | C29: v9.25 | D29: 2023/12 | E29: Mantenimiento Evolutivo | F29: 1044365 | G29: Funcional / Certificación | H29: MEGA | I29: Facturación | J29: Facturación | K29: Impresión de facturas | L29: SERVINFORM | M29: MEG-2630 | N29: Impresión Factura - Datos planes de pago | O29: Se valida que el formato del apartado Datos planes de pago | P29: Catalan | U29: impresionNuevaFactura_C_00004444_2025FA00012807_1535227_20251205_141008.afp | AG29: Revisión OK | AH29: Lorena Bernuz /Kiko | AI29: 46006 | AJ29: 46017 | AK29: 46385
A30: MEGA | B30: 00000 - Validar Impresión Facturas SERVINFORM | C30: v9.25 | D30: 2023/12 | E30: Mantenimiento Evolutivo | F30: 1044365 | G30: Funcional / Certificación | H30: MEGA | I30: Facturación | J30: Facturación | K30: Impresión de facturas | L30: SERVINFORM | M30: MEG-2630 | N30: Impresión Factura - Datos planes de pago | O30: Se valida que el formato del apartado Datos planes de pago | P30: Portugues | AG30: Revisión OK | AH30: Lorena Bernuz /Kiko | AI30: 46006 | AJ30: 46017 | AK30: 46385
A31: MEGA | B31: 00000 - Validar Impresión Facturas SERVINFORM | C31: v9.25 | D31: 2023/12 | E31: Mantenimiento Evolutivo | F31: 1044365 | G31: Funcional / Certificación | H31: MEGA | I31: Facturación | J31: Facturación | K31: Impresión de facturas | L31: SERVINFORM | M31: MEG-2631 | N31: Impresión Factura - Resultado final | O31: Se valida que el formato del apartado Resultado final | P31: Castellano | R31: Manual | S31: Media | T31: 90018116 | U31: CASTELLANO solfac A 00004444 2025FA00012807.pdf solfac E 90032372 2025FA00012874.pdf | V31: CASTELLANO: 2025FA00012807_25121516511616.pdf 2025FA00012874_25121516513434.pdf | W31: Funcional | X31: TERMINADO | Z31: 3 | AA31: 3 | AG31: Revisión OK | AH31: Lorena Bernuz /Kiko | AI31: 46006 | AJ31: 46017 | AK31: 46008 | AL31: OK
A32: MEGA | B32: 00000 - Validar Impresión Facturas SERVINFORM | C32: v9.25 | D32: 2023/12 | E32: Mantenimiento Evolutivo | F32: 1044365 | G32: Funcional / Certificación | H32: MEGA | I32: Facturación | J32: Facturación | K32: Impresión de facturas | L32: SERVINFORM | M32: MEG-2631 | N32: Impresión Factura - Resultado final | O32: Se valida que el formato del apartado Resultado final | P32: Catalan | U32: impresionNuevaFactura_C_00004444_2025FA00012807_1535227_20251205_141008.afp impresionNuevaFactura_C_90032372_2025FA00012874_1535413_20251205_141014.afp | AG32: Revisión OK | AH32: Lorena Bernuz /Kiko | AI32: 46006 | AJ32: 46017 | AK32: 46385
A33: MEGA | B33: 00000 - Validar Impresión Facturas SERVINFORM | C33: v9.25 | D33: 2023/12 | E33: Mantenimiento Evolutivo | F33: 1044365 | G33: Funcional / Certificación | H33: MEGA | I33: Facturación | J33: Facturación | K33: Impresión de facturas | L33: SERVINFORM | M33: MEG-2631 | N33: Impresión Factura - Resultado final | O33: Se valida que el formato del apartado Resultado final | P33: Portugues | AG33: Revisión OK | AH33: Lorena Bernuz /Kiko | AI33: 46006 | AJ33: 46017 | AK33: 46385
A34: MEGA | B34: 00000 - Validar Impresión Facturas SERVINFORM | C34: v9.25 | D34: 2023/12 | E34: Mantenimiento Evolutivo | F34: 1044365 | G34: Funcional / Certificación | H34: MEGA | I34: Facturación | J34: Facturación | K34: Impresión de facturas | L34: SERVINFORM | M34: MEG-2632 | N34: Impresión Factura - Consumos Regularización | O34: Se valida que el formato del apartado Consumos Regularización | P34: Castellano | R34: Manual | S34: Media | T34: 90018116 | U34: CASTELLANO solfac A 00004444 2025FA00012807.pdf solfac E 90032372 2025FA00012874.pdf | V34: CASTELLANO: 2025FA00012807_25121516511616.pdf 2025FA00012874_25121516513434.pdf | W34: Funcional | X34: TERMINADO | Z34: 3 | AA34: 3 | AG34: Revisión OK | AH34: Lorena Bernuz /Kiko | AI34: 46006 | AJ34: 46017 | AK34: 46008 | AL34: KO
A35: MEGA | B35: 00000 - Validar Impresión Facturas SERVINFORM | C35: v9.25 | D35: 2023/12 | E35: Mantenimiento Evolutivo | F35: 1044365 | G35: Funcional / Certificación | H35: MEGA | I35: Facturación | J35: Facturación | K35: Impresión de facturas | L35: SERVINFORM | M35: MEG-2632 | N35: Impresión Factura - Consumos Regularización | O35: Se valida que el formato del apartado Consumos Regularización | P35: Catalan | U35: impresionNuevaFactura_C_00004444_2025FA00012807_1535227_20251205_141008.afp impresionNuevaFactura_C_90032372_2025FA00012874_1535413_20251205_141014.afp | AG35: Revisión OK | AH35: Lorena Bernuz /Kiko | AI35: 46006 | AJ35: 46017 | AK35: 46385
A36: MEGA | B36: 00000 - Validar Impresión Facturas SERVINFORM | C36: v9.25 | D36: 2023/12 | E36: Mantenimiento Evolutivo | F36: 1044365 | G36: Funcional / Certificación | H36: MEGA | I36: Facturación | J36: Facturación | K36: Impresión de facturas | L36: SERVINFORM | M36: MEG-2632 | N36: Impresión Factura - Consumos Regularización | O36: Se valida que el formato del apartado Consumos Regularización | P36: Portugues | AG36: Revisión OK | AH36: Lorena Bernuz /Kiko | AI36: 46006 | AJ36: 46017 | AK36: 46385
A37: MEGA | B37: 00000 - Validar Impresión Facturas SERVINFORM | C37: v9.25 | D37: 2023/12 | E37: Mantenimiento Evolutivo | F37: 1044365 | G37: Funcional / Certificación | H37: MEGA | I37: Facturación | J37: Facturación | K37: Impresión de facturas | L37: SERVINFORM | M37: MEG-2633 | N37: Impresión Factura - Consumos Contador | O37: Se valida que el formato del apartado Consumos Contador | P37: Castellano | R37: Manual | S37: Media | T37: 90018116 | U37: CASTELLANO solfac A 00004444 2025FA00012807.pdf solfac B 00004484 2025FA00012808.pdf solfac C 90023950 2025FA00012831.pdf solfac E 90032372 2025FA00012874.pdf solfac G 90043847 2023FA00008653.pdf | V37: CASTELLANO: 2025FA00012807_25121516511616.pdf 2025FA00012808_25121516512222.pdf 2025FA00012831_25121516512828.pdf 2025FA00012874_25121516513434.pdf 2023FA00008653_25121516510303.pdf | W37: Funcional | X37: TERMINADO | Z37: 3 | AA37: 3 | AG37: Revisión OK | AH37: Lorena Bernuz /Kiko | AI37: 46006 | AJ37: 46017 | AK37: 46008 | AL37: OK
A38: MEGA | B38: 00000 - Validar Impresión Facturas SERVINFORM | C38: v9.25 | D38: 2023/12 | E38: Mantenimiento Evolutivo | F38: 1044365 | G38: Funcional / Certificación | H38: MEGA | I38: Facturación | J38: Facturación | K38: Impresión de facturas | L38: SERVINFORM | M38: MEG-2633 | N38: Impresión Factura - Consumos Contador | O38: Se valida que el formato del apartado Consumos Contador | P38: Catalan | U38: impresionNuevaFactura_C_00004444_2025FA00012807_1535227_20251205_141008.afp impresionNuevaFactura_C_00004484_2025FA00012808_1535228_20251205_141010.afp impresionNuevaFactura_C_90023950_2025FA00012831_1535284_20251205_141011.afp impresionNuevaFactura_C_90032372_2025FA00012874_1535413_20251205_141014.afp impresionNuevaFactura_C_90043847_2023FA00008653_1309170_20251205_141003.afp | AG38: Revisión OK | AH38: Lorena Bernuz /Kiko | AI38: 46006 | AJ38: 46017 | AK38: 46385
A39: MEGA | B39: 00000 - Validar Impresión Facturas SERVINFORM | C39: v9.25 | D39: 2023/12 | E39: Mantenimiento Evolutivo | F39: 1044365 | G39: Funcional / Certificación | H39: MEGA | I39: Facturación | J39: Facturación | K39: Impresión de facturas | L39: SERVINFORM | M39: MEG-2633 | N39: Impresión Factura - Consumos Contador | O39: Se valida que el formato del apartado Consumos Contador | P39: Portugues | AG39: Revisión OK | AH39: Lorena Bernuz /Kiko | AI39: 46006 | AJ39: 46017 | AK39: 46385
A40: MEGA | B40: 00000 - Validar Impresión Facturas SERVINFORM | C40: v9.25 | D40: 2023/12 | E40: Mantenimiento Evolutivo | F40: 1044365 | G40: Funcional / Certificación | H40: MEGA | I40: Facturación | J40: Facturación | K40: Impresión de facturas | L40: SERVINFORM | M40: MEG-2634 | N40: Impresión Factura - Consumos GNL | O40: Se valida que el formato del apartado Consumos GNL | P40: Castellano | R40: Manual | S40: Media | T40: 90018116 | U40: CASTELLANO solfac D 90031924 2025FA00012643.pdf | V40: CASTELLANO: 2025FA00012643_25121516511010.pdf | W40: Funcional | X40: TERMINADO | Z40: 3 | AA40: 3 | AG40: Revisión OK | AH40: Lorena Bernuz /Kiko | AI40: 46006 | AJ40: 46017 | AK40: 46008 | AL40: KO
A41: MEGA | B41: 00000 - Validar Impresión Facturas SERVINFORM | C41: v9.25 | D41: 2023/12 | E41: Mantenimiento Evolutivo | F41: 1044365 | G41: Funcional / Certificación | H41: MEGA | I41: Facturación | J41: Facturación | K41: Impresión de facturas | L41: SERVINFORM | M41: MEG-2634 | N41: Impresión Factura - Consumos GNL | O41: Se valida que el formato del apartado Consumos GNL | P41: Catalan | U41: impresionNuevaFactura_C_90031924_2025FA00012643_1532880_20251205_141005.afp | AG41: Revisión OK | AH41: Lorena Bernuz /Kiko | AI41: 46006 | AJ41: 46017 | AK41: 46385
A42: MEGA | B42: 00000 - Validar Impresión Facturas SERVINFORM | C42: v9.25 | D42: 2023/12 | E42: Mantenimiento Evolutivo | F42: 1044365 | G42: Funcional / Certificación | H42: MEGA | I42: Facturación | J42: Facturación | K42: Impresión de facturas | L42: SERVINFORM | M42: MEG-2634 | N42: Impresión Factura - Consumos GNL | O42: Se valida que el formato del apartado Consumos GNL | P42: Portugues | AG42: Revisión OK | AH42: Lorena Bernuz /Kiko | AI42: 46006 | AJ42: 46017 | AK42: 46385
A43: MEGA | B43: 00000 - Validar Impresión Facturas SERVINFORM | C43: v9.25 | D43: 2023/12 | E43: Mantenimiento Evolutivo | F43: 1044365 | G43: Funcional / Certificación | H43: MEGA | I43: Facturación | J43: Facturación | K43: Impresión de facturas | L43: SERVINFORM | M43: MEG-2635 | N43: Impresión Factura - Consumos GNV | O43: Se valida que el formato del apartado Consumos GNV | P43: Castellano | R43: Manual | S43: Media | T43: 90018116 | U43: CASTELLANO solfac H 90043855 2025FA00020476.pdf | V43: CASTELLANO: 202500020476_25121516544444.pdf | W43: Funcional | X43: TERMINADO | Z43: 3 | AA43: 3 | AG43: Revisión OK | AH43: Lorena Bernuz /Kiko | AI43: 46006 | AJ43: 46017 | AK43: 46008 | AL43: KO
A44: MEGA | B44: 00000 - Validar Impresión Facturas SERVINFORM | C44: v9.25 | D44: 2023/12 | E44: Mantenimiento Evolutivo | F44: 1044365 | G44: Funcional / Certificación | H44: MEGA | I44: Facturación | J44: Facturación | K44: Impresión de facturas | L44: SERVINFORM | M44: MEG-2635 | N44: Impresión Factura - Consumos GNV | O44: Se valida que el formato del apartado Consumos GNV | P44: Catalan | U44: impresionNuevaFactura_C_90043855_202500020476_1537214_20251210_152232.afp | AG44: Revisión OK | AH44: Lorena Bernuz /Kiko | AI44: 46006 | AJ44: 46017 | AK44: 46385
A45: MEGA | B45: 00000 - Validar Impresión Facturas SERVINFORM | C45: v9.25 | D45: 2023/12 | E45: Mantenimiento Evolutivo | F45: 1044365 | G45: Funcional / Certificación | H45: MEGA | I45: Facturación | J45: Facturación | K45: Impresión de facturas | L45: SERVINFORM | M45: MEG-2635 | N45: Impresión Factura - Consumos GNV | O45: Se valida que el formato del apartado Consumos GNV | P45: Portugues | AG45: Revisión OK | AH45: Lorena Bernuz /Kiko | AI45: 46006 | AJ45: 46017 | AK45: 46385
A46: MEGA | B46: 00000 - Validar Impresión Facturas SERVINFORM | C46: v9.25 | D46: 2023/12 | E46: Mantenimiento Evolutivo | F46: 1044365 | G46: Funcional / Certificación | H46: MEGA | I46: Facturación | J46: Facturación | K46: Impresión de facturas | L46: SERVINFORM | M46: MEG-2636 | N46: Impresión Factura - Facturas Anteriores | O46: Se valida que el formato del apartado Facturas Anteriores | P46: Castellano | R46: Manual | S46: Media | T46: 90018116 | U46: CASTELLANO solfac B 00004484 2025FA00012808.pdf solfac C 90023950 2025FA00012831.pdf solfac G 90043847 2023FA00008653.pdf | V46: CASTELLANO: 2025FA00012808_25121516512222.pdf 2025FA00012831_25121516512828.pdf 2023FA00008653_25121516510303.pdf | W46: Funcional | X46: TERMINADO | Z46: 3 | AA46: 3 | AG46: Revisión OK | AH46: Lorena Bernuz /Kiko | AI46: 46006 | AJ46: 46017 | AK46: 46008 | AL46: OK
A47: MEGA | B47: 00000 - Validar Impresión Facturas SERVINFORM | C47: v9.25 | D47: 2023/12 | E47: Mantenimiento Evolutivo | F47: 1044365 | G47: Funcional / Certificación | H47: MEGA | I47: Facturación | J47: Facturación | K47: Impresión de facturas | L47: SERVINFORM | M47: MEG-2636 | N47: Impresión Factura - Facturas Anteriores | O47: Se valida que el formato del apartado Facturas Anteriores | P47: Catalan | U47: impresionNuevaFactura_C_00004484_2025FA00012808_1535228_20251205_141010.afp impresionNuevaFactura_C_90023950_2025FA00012831_1535284_20251205_141011.afp impresionNuevaFactura_C_90043847_2023FA00008653_1309170_20251205_141003.afp | AG47: Revisión OK | AH47: Lorena Bernuz /Kiko | AI47: 46006 | AJ47: 46017 | AK47: 46385
A48: MEGA | B48: 00000 - Validar Impresión Facturas SERVINFORM | C48: v9.25 | D48: 2023/12 | E48: Mantenimiento Evolutivo | F48: 1044365 | G48: Funcional / Certificación | H48: MEGA | I48: Facturación | J48: Facturación | K48: Impresión de facturas | L48: SERVINFORM | M48: MEG-2636 | N48: Impresión Factura - Facturas Anteriores | O48: Se valida que el formato del apartado Facturas Anteriores | P48: Portugues | AG48: Revisión OK | AH48: Lorena Bernuz /Kiko | AI48: 46006 | AJ48: 46017 | AK48: 46385
A49: MEGA | B49: 00000 - Validar Impresión Facturas SERVINFORM | C49: v9.25 | D49: 2023/12 | E49: Mantenimiento Evolutivo | F49: 1044365 | G49: Funcional / Certificación | H49: MEGA | I49: Facturación | J49: Facturación | K49: Impresión de facturas | L49: SERVINFORM | M49: MEG-2638 | N49: Impresión Factura - Cuadros explicativos | O49: Se valida que el formato del apartado Cuadros explicativos | P49: Castellano | R49: Manual | S49: Media | T49: 90018116 | U49: CASTELLANO solfac A 00004444 2025FA00012807.pdf solfac C 90023950 2025FA00012831.pdf solfac E 90032372 2025FA00012874.pdf | V49: CASTELLANO: 2025FA00012807_25121516511616.pdf 2025FA00012831_25121516512828.pdf 2025FA00012874_25121516513434.pdf | W49: Funcional | X49: TERMINADO | Z49: 3 | AA49: 3 | AG49: Revisión OK | AH49: Lorena Bernuz /Kiko | AI49: 46006 | AJ49: 46017 | AK49: 46008 | AL49: OK
A50: MEGA | B50: 00000 - Validar Impresión Facturas SERVINFORM | C50: v9.25 | D50: 2023/12 | E50: Mantenimiento Evolutivo | F50: 1044365 | G50: Funcional / Certificación | H50: MEGA | I50: Facturación | J50: Facturación | K50: Impresión de facturas | L50: SERVINFORM | M50: MEG-2638 | N50: Impresión Factura - Cuadros explicativos | O50: Se valida que el formato del apartado Cuadros explicativos | P50: Catalan | U50: impresionNuevaFactura_C_00004444_2025FA00012807_1535227_20251205_141008.afp impresionNuevaFactura_C_90023950_2025FA00012831_1535284_20251205_141011.afp impresionNuevaFactura_C_90032372_2025FA00012874_1535413_20251205_141014.afp | AG50: Revisión OK | AH50: Lorena Bernuz /Kiko | AI50: 46006 | AJ50: 46017 | AK50: 46385
A51: MEGA | B51: 00000 - Validar Impresión Facturas SERVINFORM | C51: v9.25 | D51: 2023/12 | E51: Mantenimiento Evolutivo | F51: 1044365 | G51: Funcional / Certificación | H51: MEGA | I51: Facturación | J51: Facturación | K51: Impresión de facturas | L51: SERVINFORM | M51: MEG-2638 | N51: Impresión Factura - Cuadros explicativos | O51: Se valida que el formato del apartado Cuadros explicativos | P51: Portugues | AG51: Revisión OK | AH51: Lorena Bernuz /Kiko | AI51: 46006 | AJ51: 46017 | AK51: 46385
A52: MEGA | B52: 00000 - Validar Impresión Facturas SERVINFORM | C52: v9.25 | D52: 2023/12 | E52: Mantenimiento Evolutivo | F52: 1044365 | G52: Funcional / Certificación | H52: MEGA | I52: Facturación | J52: Facturación | K52: Impresión de facturas | L52: SERVINFORM | M52: MEG-2639 | N52: Impresión Factura - Banners | O52: Se valida que el formato del apartado Banners | P52: Castellano | R52: Manual | S52: Media | T52: 90018116 | U52: CASTELLANO solfac H 90043855 2025FA00020476.pdf | V52: CASTELLANO: 202500020476_25121516544444.pdf | W52: Funcional | X52: TERMINADO | Z52: 3 | AA52: 3 | AG52: Revisión OK | AH52: Lorena Bernuz /Kiko | AI52: 46006 | AJ52: 46017 | AK52: 46008 | AL52: OK
A53: MEGA | B53: 00000 - Validar Impresión Facturas SERVINFORM | C53: v9.25 | D53: 2023/12 | E53: Mantenimiento Evolutivo | F53: 1044365 | G53: Funcional / Certificación | H53: MEGA | I53: Facturación | J53: Facturación | K53: Impresión de facturas | L53: SERVINFORM | M53: MEG-2639 | N53: Impresión Factura - Banners | O53: Se valida que el formato del apartado Banners | P53: Catalan | U53: impresionNuevaFactura_C_90043855_202500020476_1537214_20251210_152232.afp | AG53: Revisión OK | AH53: Lorena Bernuz /Kiko | AI53: 46006 | AJ53: 46017 | AK53: 46385
A54: MEGA | B54: 00000 - Validar Impresión Facturas SERVINFORM | C54: v9.25 | D54: 2023/12 | E54: Mantenimiento Evolutivo | F54: 1044365 | G54: Funcional / Certificación | H54: MEGA | I54: Facturación | J54: Facturación | K54: Impresión de facturas | L54: SERVINFORM | M54: MEG-2639 | N54: Impresión Factura - Banners | O54: Se valida que el formato del apartado Banners | P54: Portugues | AG54: Revisión OK | AH54: Lorena Bernuz /Kiko | AI54: 46006 | AJ54: 46017 | AK54: 46385
A55: MEGA | B55: 00000 - Validar Impresión Facturas SERVINFORM | C55: v9.25 | D55: 2023/12 | E55: Mantenimiento Evolutivo | F55: 1044365 | G55: Funcional / Certificación | H55: MEGA | I55: Facturación | J55: Facturación | K55: Impresión de facturas | L55: SERVINFORM | M55: MEG-2650 | N55: Impresión Factura - Histórico de consumos | O55: Se valida que el formato del apartado Histórico de consumos | P55: Castellano | R55: Manual | S55: Media | T55: 90018116 | U55: CASTELLANO solfac A 00004444 2025FA00012807.pdf solfac B 00004484 2025FA00012808.pdf solfac C 90023950 2025FA00012831.pdf solfac D 90031924 2025FA00012643.pdf solfac E 90032372 2025FA00012874.pdf solfac G 90043847 2023FA00008653.pdf solfac H 90043855 2025FA00020476.pdf | V55: CASTELLANO: 2025FA00012807_25121516511616.pdf 2025FA00012808_25121516512222.pdf 2025FA00012831_25121516512828.pdf 2025FA00012643_25121516511010.pdf 2025FA00012874_25121516513434.pdf 2023FA00008653_25121516510303.pdf 202500020476_25121516544444.pdf | W55: Funcional | X55: TERMINADO | Z55: 3 | AA55: 3 | AG55: Revisión OK | AH55: Lorena Bernuz /Kiko | AI55: 46006 | AJ55: 46017 | AK55: 46008 | AL55: OK
A56: MEGA | B56: 00000 - Validar Impresión Facturas SERVINFORM | C56: v9.25 | D56: 2023/12 | E56: Mantenimiento Evolutivo | F56: 1044365 | G56: Funcional / Certificación | H56: MEGA | I56: Facturación | J56: Facturación | K56: Impresión de facturas | L56: SERVINFORM | M56: MEG-2650 | N56: Impresión Factura - Histórico de consumos | O56: Se valida que el formato del apartado Histórico de consumos | P56: Catalan | U56: impresionNuevaFactura_C_00004444_2025FA00012807_1535227_20251205_141008.afp impresionNuevaFactura_C_00004484_2025FA00012808_1535228_20251205_141010.afp impresionNuevaFactura_C_90023950_2025FA00012831_1535284_20251205_141011.afp impresionNuevaFactura_C_90031924_2025FA00012643_1532880_20251205_141005.afp impresionNuevaFactura_C_90032372_2025FA00012874_1535413_20251205_141014.afp impresionNuevaFactura_C_90043847_2023FA00008653_1309170_20251205_141003.afp impresionNuevaFactura_C_90043855_202500020476_1537214_20251210_152232.afp | AG56: Revisión OK | AH56: Lorena Bernuz /Kiko | AI56: 46006 | AJ56: 46017 | AK56: 46385
A57: MEGA | B57: 00000 - Validar Impresión Facturas SERVINFORM | C57: v9.25 | D57: 2023/12 | E57: Mantenimiento Evolutivo | F57: 1044365 | G57: Funcional / Certificación | H57: MEGA | I57: Facturación | J57: Facturación | K57: Impresión de facturas | L57: SERVINFORM | M57: MEG-2650 | N57: Impresión Factura - Histórico de consumos | O57: Se valida que el formato del apartado Histórico de consumos | P57: Portugues | AG57: Revisión OK | AH57: Lorena Bernuz /Kiko | AI57: 46006 | AJ57: 46017 | AK57: 46385
AL58: =(COUNTIF(AL4:AL57,"OK")/(COUNTBLANK(AL4:AL57)+(COUNTA(AL4:AL57)-(COUNTIF(AL4:AL57,"N/A"))))) -> 0.20408163 | AM58: Porcentaje de Avance
AL59: =COUNTBLANK(AL4:AL57)+(COUNTA(AL4:AL57)-(COUNTIF(AL4:AL57,"N/A"))-(COUNTIF(AL4:AL57,"OK"))-(COUNTIF(AL4:AL57,"KO"))) -> 34 | AM59: Pendiente
AL60: =COUNTIF(AL4:AL57,"KO") -> 5 | AM60: KO
AL61: =COUNTIF(AL4:AL57,"OK") -> 10 | AM61: OK
AL62: =COUNTBLANK(AL4:AL57)+(COUNTA(AL4:AL57)-(COUNTIF(AL4:AL57,"N/A"))) -> 49 | AM62: Total

Sheet Listados
A1: Resultados
A2: OK
A3: KO
A4: Pdte
A5: N/A
